Workbook
Name IQ_CH: 110000
Name IQ_CQ: 5000
Name IQ_CY: 10000
Name IQ_DAILY: 500000
Name IQ_FH: 100000
Name IQ_FQ: 500
Name IQ_FY: 1000
Name IQ_LTM: 2000
Name IQ_MONTH: 15000
Name IQ_NTM: 6000
Name IQ_WEEK: 50000
Name IQ_YTD: 3000

Sheet FSM Data Input
C2: ="Financial Statement Model for "&D5 -> Financial Statement Model for Apple
C3: $ in thousands except per share
C5: Company name | D5: Apple
C6: Ticker | D6: AAPL
C7: Circ break 1=off, 0=on | D7: 1
C8: Latest closing share price | D8: 171.25
C9: Latest closing share price date | D9: 43500
C10: Latest fiscal year end date | D10: 43372
C11: Shares outstanding (millions) | D11: 4745.398
C13: INCOME STATEMENT
C14: Fiscal year | D14: =E14-1 -> 2016 | E14: =F14-1 -> 2017 | F14: =YEAR(D10) -> 2018
C15: Fiscal year end date | D15: =EOMONTH(E15,-12) -> 42643 | E15: =EOMONTH(F15,-12) -> 43008 | F15: =D10 -> 43372
C17: Revenue | D17: 215639 | E17: 229234 | F17: 265595
C18: Cost of sales (enter as -) | D18: -131376 | E18: -141048 | F18: -163756
C19: Gross Profit | D19: =SUM(D17:D18) -> 84263 | E19: =SUM(E17:E18) -> 88186 | F19: =SUM(F17:F18) -> 101839
C20: Research & development (enter as -) | D20: -10045 | E20: -11581 | F20: -14236
C21: Selling, general & administrative (enter as -) | D21: -14194 | E21: -15261 | F21: -16705
C22: Operating profit (EBIT) | D22: =SUM(D19:D21) -> 60024 | E22: =SUM(E19:E21) -> 61344 | F22: =SUM(F19:F21) -> 70898
C23: Interest income | D23: 3999 | E23: 5201 | F23: 5686
C24: Interest expense (enter as -) | D24: -1456 | E24: -2323 | F24: -3240
C25: Other expense, net (enter as -) | D25: -1195 | E25: -133 | F25: -441
C26: Pretax profit | D26: =SUM(D22:D25) -> 61372 | E26: =SUM(E22:E25) -> 64089 | F26: =SUM(F22:F25) -> 72903
C27: Taxes (enter expense as -) | D27: -15685 | E27: -15738 | F27: -13372
C28: Net income | D28: =SUM(D26:D27) -> 45687 | E28: =SUM(E26:E27) -> 48351 | F28: =SUM(F26:F27) -> 59531
C30: Depreciation & amortization | D30: 10505 | E30: 10157 | F30: 10903 | H30: From cash flow statement
C31: EBITDA | D31: =D22+D30 -> 70529 | E31: =E22+E30 -> 71501 | F31: =F22+F30 -> 81801 | H31: EBIT + D&A
C32: Stock based compensation | D32: 4210 | E32: 4840 | F32: 5340 | H32: From cash flow statement
C33: Adjusted EBITDA | D33: =SUM(D31:D32) -> 74739 | E33: =SUM(E31:E32) -> 76341 | F33: =SUM(F31:F32) -> 87141 | H33: EBITDA + Stock-based compensation
C35: Growth rates & margins
C36: Revenue growth | E36: =E17/D17-1 -> 0.063045182 | F36: =F17/E17-1 -> 0.15861958 | H36: Current year / Last year - 1
C37: Gross profit margin | D37: =D19/D17 -> 0.39075956 | E37: =E19/E17 -> 0.3846986 | F37: =F19/F17 -> 0.38343719 | H37: Gross profit / revenue
C38: R&D % of sales | D38: =-(D20/D17) -> 0.046582483 | E38: =-(E20/E17) -> 0.050520429 | F38: =-(F20/F17) -> 0.053600407 | H38: R&D / Revenue
C39: SG&A % of sales | D39: =-(D21/D17) -> 0.065822973 | E39: =-(E21/E17) -> 0.066573894 | F39: =-(F21/F17) -> 0.062896515 | H39: SG&A / Revenue
C40: Tax rate | D40: =-(D27/D26) -> 0.25557257 | E40: =-(E27/E26) -> 0.24556476 | F40: =-(F27/F26) -> 0.18342181 | H40: Taxes / Pretax Profit
C42: BALANCE SHEET
C43: =C14 -> Fiscal year | E43: =E14 -> 2017 | F43: =F14 -> 2018
C44: =C15 -> Fiscal year end date | E44: =E15 -> 43008 | F44: =F15 -> 43372
C45: Cash & equivalents, ST and LT marketable securities | E45: =20289+53892+194714 -> 268895 | F45: =25913+40388+170799 -> 237100
C46: Accounts receivable | E46: 17874 | F46: 23186
C47: Inventories | E47: 4855 | F47: 3956
C48: Other current assets | E48: =17799+13936 -> 31735 | F48: =25809+12087 -> 37896 | H48: Include vendor non-trade receivables
C49: Property, plant & equipment | E49: 33783 | F49: 41304
C50: Other non current assets | E50: 18177 | F50: 22283
C51: Total assets | E51: =SUM(E45:E50) -> 375319 | F51: =SUM(F45:F50) -> 365725
C53: Accounts payable | E53: 44242 | F53: 55888
C54: Other current liabilities | E54: 30551 | F54: 32687
C55: Deferred revenue (current and non current) | E55: =7548+2836 -> 10384 | F55: =7543+2797 -> 10340
C56: Commercial paper / revolver | E56: 11977 | F56: 11964
C57: Long term debt (includes current portion) | E57: =6496+97207 -> 103703 | F57: =8784+93735 -> 102519
C58: Other non current liabilities | E58: 40415 | F58: 45180
C59: Total liabilities | E59: =SUM(E53:E58) -> 241272 | F59: =SUM(F53:F58) -> 258578
C61: Common stock | E61: 35867 | F61: 40201
C62: Retained earnings | E62: 98330 | F62: 70400
C63: Other comprehensive income | E63: -150 | F63: -3454
C64: Total equity | E64: =SUM(E61:E63) -> 134047 | F64: =SUM(F61:F63) -> 107147
C66: Balance check | E66: =ROUND(E51-E59-E64,3) -> 0 | F66: =ROUND(F51-F59-F64,3) -> 0
C68: Additional data
C69: Capital expenditures (enter as +) | D69: 12734 | E69: 12451 | F69: 13313
C70: D&A related only to PP&E (enter as -) | D70: -8300 | E70: -8200 | F70: -9300 | H70: Property plant and equipment section - Apple 2018 10K p.45
C71: Dividends | D71: -12188 | E71: -12803 | F71: -13735 | H71: Statement of shareholders equity schedule - p.41 Apple 2018 10K
C72: Repurchases | D72: -29000 | E72: -33001 | F72: -73056 | H72: Statement of shareholders equity schedule - p.41 Apple 2018 10K
C73: Weighted average interest rate on commercial paper | E73: 0.012 | F73: 0.0218 | H73: Note 5 - Debt. Apple 2018 10K p55
C74: Weighted average interest rate on cash | D74: 0.0173 | E74: 0.0199 | F74: 0.0216 | H74: 'Other Income/(Expense), Net' section - Apple 2018 10K p.27

Sheet FSM
C2: ="Financial Statement Model for "&D5 -> Financial Statement Model for Apple
C3: $ in thousands except per share
C5: Company name | D5: Apple
C6: Ticker | D6: AAPL
C7: Circ break 1=off, 0=on | D7: 1
C8: Latest closing share price | D8: 171.25
C9: Latest closing share price date | D9: 43500
C10: Latest fiscal year end date | D10: 43372
C11: Shares outstanding (millions) | D11: 4745.398
C13: INCOME STATEMENT
C14: Fiscal year | D14: =E14-1 -> 2016 | E14: =F14-1 -> 2017 | F14: =YEAR(D10) -> 2018 | G14: =F14+1 -> 2019 | H14: =G14+1 -> 2020 | I14: =H14+1 -> 2021 | J14: =I14+1 -> 2022 | K14: =J14+1 -> 2023
C15: Fiscal year end date | D15: =EOMONTH(E15,-12) -> 42643 | E15: =EOMONTH(F15,-12) -> 43008 | F15: =D10 -> 43372 | G15: =EOMONTH(F15,12) -> 43738 | H15: =EOMONTH(G15,12) -> 44104 | I15: =EOMONTH(H15,12) -> 44469 | J15: =EOMONTH(I15,12) -> 44834 | K15: =EOMONTH(J15,12) -> 45199
C17: Revenue | D17: 215639 | E17: 229234 | F17: 265595 | G17: =F17*(1+G36) -> 254971.2 | H17: =G17*(1+H36) -> 270269.47 | I17: =H17*(1+I36) -> 288918.07 | J17: =I17*(1+J36) -> 308853.41 | K17: =J17*(1+K36) -> 330164.3 | M17: Previous year's revenues x (1+revenue growth rate)
C18: Cost of sales (enter as -) | D18: -131376 | E18: -141048 | F18: -163756 | G18: =G19-G17 -> -158592.09 | H18: =H19-H17 -> -167296.8 | I18: =I19-I17 -> -178551.36 | J18: =J19-J17 -> -190871.41 | K18: =K19-K17 -> -204041.54 | M18: Plug = Revenue - Gross Profit
C19: Gross Profit | D19: =SUM(D17:D18) -> 84263 | E19: =SUM(E17:E18) -> 88186 | F19: =SUM(F17:F18) -> 101839 | G19: =G17*G37 -> 96379.114 | H19: =H17*H37 -> 102972.67 | I19: =I17*I37 -> 110366.7 | J19: =J17*J37 -> 117982 | K19: =K17*K37 -> 126122.76 | M19: Revenue x Gross Profit Margin forecast
C20: Research & development (enter as -) | D20: -10045 | E20: -11581 | F20: -14236 | G20: =-G38*G17 -> -15808.214 | H20: =-H38*H17 -> -17026.977 | I20: =-I38*I17 -> -18201.838 | J20: =-J38*J17 -> -19457.765 | K20: =-K38*K17 -> -20800.351 | M20: Revenue x R&D % of sales forecast
C21: Selling, general & administrative (enter as -) | D21: -14194 | E21: -15261 | F21: -16705 | G21: =-G17*G39 -> -18867.869 | H21: =-H17*H39 -> -18648.594 | I21: =-I17*I39 -> -19935.347 | J21: =-J17*J39 -> -21310.885 | K21: =-K17*K39 -> -22781.337 | M21: Revenue x SG&A % of sales forecast
C22: Operating profit (EBIT) | D22: =D19+D20+D21 -> 60024 | E22: =E19+E20+E21 -> 61344 | F22: =F19+F20+F21 -> 70898 | G22: =G19+G20+G21 -> 61703.03 | H22: =H19+H20+H21 -> 67297.099 | I22: =I19+I20+I21 -> 72229.516 | J22: =J19+J20+J21 -> 77213.353 | K22: =K19+K20+K21 -> 82541.074 | M22: Gross Profit - R&D - SG&A
C23: Interest income | D23: 3999 | E23: 5201 | F23: 5686 | G23: =G156 -> 4744.4371 | H23: =H156 -> 4090.2133 | I23: =I156 -> 3592.0871 | J23: =J156 -> 3200.5876 | K23: =K156 -> 2913.2593 | M23: Reference from interest on cash schedule
C24: Interest expense (enter as -) | D24: -1456 | E24: -2323 | F24: -3240 | G24: =-G142 -> -3223.1469 | H24: =-H142 -> -3223.5393 | I24: =-I142 -> -3223.5393 | J24: =-J142 -> -3223.5393 | K24: =-K142 -> -3223.5393 | M24: Reference from interest expense schedule
C25: Other expense, net (enter as -) | D25: -1195 | E25: -133 | F25: -441 | G25: =F25 -> -441 | H25: =G25 -> -441 | I25: =H25 -> -441 | J25: =I25 -> -441 | K25: =J25 -> -441 | M25: Straight-line
C26: Pretax profit | D26: =SUM(D22:D25) -> 61372 | E26: =SUM(E22:E25) -> 64089 | F26: =SUM(F22:F25) -> 72903 | G26: =SUM(G22:G25) -> 62783.321 | H26: =SUM(H22:H25) -> 67722.773 | I26: =SUM(I22:I25) -> 72157.064 | J26: =SUM(J22:J25) -> 76749.401 | K26: =SUM(K22:K25) -> 81789.794 | M26: EBIT + interest income less interest expense less other expense
C27: Taxes (enter expense as -) | D27: -15685 | E27: -15738 | F27: -13372 | G27: =-G40*G26 -> -10484.815 | H27: =-H40*H26 -> -11512.871 | I27: =-I40*I26 -> -12194.544 | J27: =-J40*J26 -> -12970.649 | K27: =-K40*K26 -> -13822.475 | M27: Pre-tax Profit x Tax Rate forecast
C28: Net income | D28: =SUM(D26:D27) -> 45687 | E28: =SUM(E26:E27) -> 48351 | F28: =SUM(F26:F27) -> 59531 | G28: =SUM(G26:G27) -> 52298.506 | H28: =SUM(H26:H27) -> 56209.901 | I28: =SUM(I26:I27) -> 59962.52 | J28: =SUM(J26:J27) -> 63778.753 | K28: =SUM(K26:K27) -> 67967.319 | M28: Pre-tax Profit less taxes
C30: Depreciation & amortization | D30: 10505 | E30: 10157 | F30: 10903 | G30: =G106 -> 11085.02 | H30: =H106 -> 11711.891 | I30: =I106 -> 12226.381 | J30: =J106 -> 13365.451 | K30: =K106 -> 14603.503 | M30: Reference from D&A schedule
C31: EBITDA | D31: =D22+D30 -> 70529 | E31: =E22+E30 -> 71501 | F31: =F22+F30 -> 81801 | G31: =G22+G30 -> 72788.051 | H31: =H22+H30 -> 79008.989 | I31: =I22+I30 -> 84455.897 | J31: =J22+J30 -> 90578.804 | K31: =K22+K30 -> 97144.578 | M31: EBIT + D&A
C32: Stock based compensation | D32: 4210 | E32: 4840 | F32: 5340 | G32: =F32*(1+G36) -> 5126.4 | H32: =G32*(1+H36) -> 5433.984 | I32: =H32*(1+I36) -> 5808.9289 | J32: =I32*(1+J36) -> 6209.745 | K32: =J32*(1+K36) -> 6638.2174 | M32: WSP assumption: grow SBC in-line with revenue growth
C33: Adjusted EBITDA | D33: =SUM(D31:D32) -> 74739 | E33: =SUM(E31:E32) -> 76341 | F33: =SUM(F31:F32) -> 87141 | G33: =SUM(G31:G32) -> 77914.451 | H33: =SUM(H31:H32) -> 84442.973 | I33: =SUM(I31:I32) -> 90264.826 | J33: =SUM(J31:J32) -> 96788.549 | K33: =SUM(K31:K32) -> 103782.8 | M33: EBITDA + Stock-based compensation
C35: Growth rates & margins
C36: Revenue growth | E36: =E17/D17-1 -> 0.063045182 | F36: =F17/E17-1 -> 0.15861958 | G36: -0.04 | H36: 0.06 | I36: 0.069 | J36: =I36 -> 0.069 | K36: =J36 -> 0.069 | M36: JP Morgan estimates through 2021; straight-line growth rate thereafter
C37: Gross profit margin | D37: =D19/D17 -> 0.39075956 | E37: =E19/E17 -> 0.3846986 | F37: =F19/F17 -> 0.38343719 | G37: 0.378 | H37: 0.381 | I37: 0.382 | J37: =I37 -> 0.382 | K37: =J37 -> 0.382 | M37: JP Morgan estimates through 2021; straight-line margin thereafter
C38: R&D % of sales | D38: =-D20/D17 -> 0.046582483 | E38: =-E20/E17 -> 0.050520429 | F38: =-F20/F17 -> 0.053600407 | G38: 0.062 | H38: 0.063 | I38: 0.063 | J38: =I38 -> 0.063 | K38: =J38 -> 0.063 | M38: JP Morgan estimates through 2021: straight-line margin thereafter
C39: SG&A % of sales | D39: =-D21/D17 -> 0.065822973 | E39: =-E21/E17 -> 0.066573894 | F39: =-F21/F17 -> 0.062896515 | G39: 0.074 | H39: 0.069 | I39: 0.069 | J39: =I39 -> 0.069 | K39: =J39 -> 0.069 | M39: JP Morgan estimates through 2021: straight-line margin thereafter
C40: Tax rate | D40: =-(D27/D26) -> 0.25557257 | E40: =-(E27/E26) -> 0.24556476 | F40: =-(F27/F26) -> 0.18342181 | G40: 0.167 | H40: 0.17 | I40: 0.169 | J40: =I40 -> 0.169 | K40: =J40 -> 0.169 | M40: JP Morgan estimates through 2021: straight-line margin thereafter
C42: BALANCE SHEET
C43: =C14 -> Fiscal year | E43: =E14 -> 2017 | F43: =F14 -> 2018 | G43: =G14 -> 2019 | H43: =H14 -> 2020 | I43: =I14 -> 2021 | J43: =J14 -> 2022 | K43: =K14 -> 2023
C44: =C15 -> Fiscal year end date | E44: =E15 -> 43008 | F44: =F15 -> 43372 | G44: =G15 -> 43738 | H44: =H15 -> 44104 | I44: =I15 -> 44469 | J44: =J15 -> 44834 | K44: =K15 -> 45199
C45: Cash & equivalents, ST and LT marketable securities | E45: =20289+53892+194714 -> 268895 | F45: =25913+40388+170799 -> 237100 | G45: =G90+F45 -> 202199.73 | H45: =H90+G45 -> 176523.72 | I45: =I90+H45 -> 156076.93 | J45: =J90+I45 -> 140273.78 | K45: =K90+J45 -> 129472.46 | M45: Reference from 'net change in cash' line on the cash flow statement
C46: Accounts receivable | E46: 17874 | F46: 23186 | G46: =F46*(1+G36) -> 22258.56 | H46: =G46*(1+H36) -> 23594.074 | I46: =H46*(1+I36) -> 25222.065 | J46: =I46*(1+J36) -> 26962.387 | K46: =J46*(1+K36) -> 28822.792 | M46: Grow in-line with revenue growth
C47: Inventories | E47: 4855 | F47: 3956 | G47: =F47*G18/F18 -> 3831.2507 | H47: =G47*H18/G18 -> 4041.5383 | I47: =H47*I18/H18 -> 4313.4248 | J47: =I47*J18/I18 -> 4611.0512 | K47: =J47*K18/J18 -> 4929.2137 | M47: Grow in-line with cost of sales growth
C48: Other current assets | E48: =17799+13936 -> 31735 | F48: =25809+12087 -> 37896 | G48: =F48*(1+G36) -> 36380.16 | H48: =G48*(1+H36) -> 38562.97 | I48: =H48*(1+I36) -> 41223.815 | J48: =I48*(1+J36) -> 44068.258 | K48: =J48*(1+K36) -> 47108.967 | M48: Grow in-line with revenue growth
C49: Property, plant & equipment | E49: 33783 | F49: 41304 | G49: =G99 -> 45042.86 | H49: =H99 -> 48611.182 | I49: =I99 -> 51947.568 | J49: =J99 -> 55218.714 | K49: =K99 -> 58399.733 | M49: Reference from PP&E schedule
C50: Other non current assets | E50: 18177 | F50: 22283 | G50: =F50*(1+G36) -> 21391.68 | H50: =G50*(1+H36) -> 22675.181 | I50: =H50*(1+I36) -> 24239.768 | J50: =I50*(1+J36) -> 25912.312 | K50: =J50*(1+K36) -> 27700.262 | M50: Grow in-line with revenue growth
C51: Total assets | E51: =SUM(E45:E50) -> 375319 | F51: =SUM(F45:F50) -> 365725 | G51: =SUM(G45:G50) -> 331104.24 | H51: =SUM(H45:H50) -> 314008.67 | I51: =SUM(I45:I50) -> 303023.57 | J51: =SUM(J45:J50) -> 297046.5 | K51: =SUM(K45:K50) -> 296433.42
C53: Accounts payable | E53: 44242 | F53: 55888 | G53: =F53*G18/F18 -> 54125.617 | H53: =G53*H18/G18 -> 57096.435 | I53: =H53*I18/H18 -> 60937.484 | J53: =I53*J18/I18 -> 65142.171 | K53: =J53*K18/J18 -> 69636.98 | M53: Grow in-line with cost of sales growth
C54: Other current liabilities | E54: 30551 | F54: 32687 | G54: =F54*(1+G36) -> 31379.52 | H54: =G54*(1+H36) -> 33262.291 | I54: =H54*(1+I36) -> 35557.389 | J54: =I54*(1+J36) -> 38010.849 | K54: =J54*(1+K36) -> 40633.598 | M54: Grow in-line with revenue growth
C55: Deferred revenue (current and non current) | E55: =7548+2836 -> 10384 | F55: =7543+2797 -> 10340 | G55: =F55*(1+G36) -> 9926.4 | H55: =G55*(1+H36) -> 10521.984 | I55: =H55*(1+I36) -> 11248.001 | J55: =I55*(1+J36) -> 12024.113 | K55: =J55*(1+K36) -> 12853.777 | M55: Grow in-line with revenue growth
C56: Commercial paper / revolver | E56: 11977 | F56: 11964 | G56: =G135 -> 12000 | H56: =H135 -> 12000 | I56: =I135 -> 12000 | J56: =J135 -> 12000 | K56: =K135 -> 12000 | M56: Reference EOP balance from CP/revolver schedule
C57: Long term debt (includes current portion) | E57: =6496+97207 -> 103703 | F57: =8784+93735 -> 102519 | G57: =F57 -> 102519 | H57: =G57 -> 102519 | I57: =H57 -> 102519 | J57: =I57 -> 102519 | K57: =J57 -> 102519 | M57: WSP assumption: straight-line
C58: Other non current liabilities | E58: 40415 | F58: 45180 | G58: =F58*(1+G36) -> 43372.8 | H58: =G58*(1+H36) -> 45975.168 | I58: =H58*(1+I36) -> 49147.455 | J58: =I58*(1+J36) -> 52538.629 | K58: =J58*(1+K36) -> 56163.794 | M58: Grow in-line with revenue growth
C59: Total liabilities | E59: =SUM(E53:E58) -> 241272 | F59: =SUM(F53:F58) -> 258578 | G59: =SUM(G53:G58) -> 253323.34 | H59: =SUM(H53:H58) -> 261374.88 | I59: =SUM(I53:I58) -> 271409.33 | J59: =SUM(J53:J58) -> 282234.76 | K59: =SUM(K53:K58) -> 293807.15
C61: Common stock | E61: 35867 | F61: 40201 | G61: =F61+G32 -> 45327.4 | H61: =G61+H32 -> 50761.384 | I61: =H61+I32 -> 56570.313 | J61: =I61+J32 -> 62780.058 | K61: =J61+K32 -> 69418.275 | M61: Increase by stock-based compensation forecasted in the I/S section
C62: Retained earnings | E62: =98330 -> 98330 | F62: 70400 | G62: =G119 -> 35907.506 | H62: =H119 -> 5326.4074 | I62: =I119 -> -21502.072 | J62: =J119 -> -44514.32 | K62: =K119 -> -63338.001 | M62: Reference from Retained Earnings schedule
C63: Other comprehensive income | E63: -150 | F63: -3454 | G63: =F63 -> -3454 | H63: =G63 -> -3454 | I63: =H63 -> -3454 | J63: =I63 -> -3454 | K63: =J63 -> -3454 | M63: WSP assumption: straight-line
C64: Total equity | E64: =SUM(E61:E63) -> 134047 | F64: =SUM(F61:F63) -> 107147 | G64: =SUM(G61:G63) -> 77780.906 | H64: =SUM(H61:H63) -> 52633.791 | I64: =SUM(I61:I63) -> 31614.241 | J64: =SUM(J61:J63) -> 14811.738 | K64: =SUM(K61:K63) -> 2626.2747
C66: Balance check | E66: =ROUND(E51-E59-E64,3) -> 0 | F66: =ROUND(F51-F59-F64,3) -> 0 | G66: =ROUND(G51-G59-G64,3) -> 0 | H66: =ROUND(H51-H59-H64,3) -> 0 | I66: =ROUND(I51-I59-I64,3) -> 0 | J66: =ROUND(J51-J59-J64,3) -> 0 | K66: =ROUND(K51-K59-K64,3) -> 0
C68: CASH FLOW STATEMENT
C69: =C14 -> Fiscal year | G69: =G14 -> 2019 | H69: =H14 -> 2020 | I69: =I14 -> 2021 | J69: =J14 -> 2022 | K69: =K14 -> 2023
C70: =C15 -> Fiscal year end date | G70: =G15 -> 43738 | H70: =H15 -> 44104 | I70: =I15 -> 44469 | J70: =J15 -> 44834 | K70: =K15 -> 45199
C72: Net income | G72: =G28 -> 52298.506 | H72: =H28 -> 56209.901 | I72: =I28 -> 59962.52 | J72: =J28 -> 63778.753 | K72: =K28 -> 67967.319
C73: Depreciation and amortization | G73: =G30 -> 11085.02 | H73: =H30 -> 11711.891 | I73: =I30 -> 12226.381 | J73: =J30 -> 13365.451 | K73: =K30 -> 14603.503 | M73: Reference from the I/S
C74: Stock based compensation | G74: =G32 -> 5126.4 | H74: =H32 -> 5433.984 | I74: =I32 -> 5808.9289 | J74: =J32 -> 6209.745 | K74: =K32 -> 6638.2174
C75: Decreases / (Increases) in working capital assets | G75: =-1*(SUM(G46:G48)-SUM(F46:F48)) -> 2568.0293 | H75: =-1*(SUM(H46:H48)-SUM(G46:G48)) -> -3728.6108 | I75: =-1*(SUM(I46:I48)-SUM(H46:H48)) -> -4560.7225 | J75: =-1*(SUM(J46:J48)-SUM(I46:I48)) -> -4882.392 | K75: =-1*(SUM(K46:K48)-SUM(J46:J48)) -> -5219.277
C76: Increases / (Decreases) in working capital liabilities | G76: =SUM(G53:G55)-SUM(F53:F55) -> -3483.4631 | H76: =SUM(H53:H55)-SUM(G53:G55) -> 5449.1728 | I76: =SUM(I53:I55)-SUM(H53:H55) -> 6862.1646 | J76: =SUM(J53:J55)-SUM(I53:I55) -> 7434.2583 | K76: =SUM(K53:K55)-SUM(J53:J55) -> 7947.2222
C77: Other non current assets | G77: =-(G111) -> -647.56 | H77: =-(H111) -> -2914.7136 | I77: =-(I111) -> -3308.354 | J77: =-(J111) -> -3536.6304 | K77: =-(K111) -> -3780.6579 | M77: Reference from schedule NOT the B/S: Only include 'Additions' (as outflow)
C78: Other non current liabilities | G78: =G58-F58 -> -1807.2 | H78: =H58-G58 -> 2602.368 | I78: =I58-H58 -> 3172.2866 | J78: =J58-I58 -> 3391.1744 | K78: =K58-J58 -> 3625.1654
C79: Cash from operating activities | G79: =SUM(G72:G78) -> 65139.732 | H79: =SUM(H72:H78) -> 74763.992 | I79: =SUM(I72:I78) -> 80163.205 | J79: =SUM(J72:J78) -> 85760.359 | K79: =SUM(K72:K78) -> 91781.493
C81: Capital expenditures | G81: =-(G97) -> -13285 | H81: =-(H97) -> -13649 | I81: =-(I97) -> -13819 | J81: =-(J97) -> -14772.511 | K81: =-(K97) -> -15791.814 | M81: Reference from PP&E schedule
C82: Cash from investing activities | G82: =IFERROR(G81,"NA") -> -13285 | H82: =IFERROR(H81,"NA") -> -13649 | I82: =IFERROR(I81,"NA") -> -13819 | J82: =IFERROR(J81,"NA") -> -14772.511 | K82: =IFERROR(K81,"NA") -> -15791.814
C84: Long term debt | G84: =G57-F57 -> 0 | H84: =H57-G57 -> 0 | I84: =I57-H57 -> 0 | J84: =J57-I57 -> 0 | K84: =K57-J57 -> 0
C85: Revolver | G85: =G56-F56 -> 36 | H85: =H56-G56 -> 0 | I85: =I56-H56 -> 0 | J85: =J56-I56 -> 0 | K85: =K56-J56 -> 0 | M85: Reference from B/S
C86: Share repurchases | G86: =G118 -> -73056 | H86: =H118 -> -73056 | I86: =I118 -> -73056 | J86: =J118 -> -73056 | K86: =K118 -> -73056 | M86: Reference from Retained Earnings schedule
C87: Common dividends | G87: =G117 -> -13735 | H87: =H117 -> -13735 | I87: =I117 -> -13735 | J87: =J117 -> -13735 | K87: =K117 -> -13735 | M87: Reference from Retained Earnings schedule
C88: Cash from financing activities | G88: =SUM(G84:G87) -> -86755 | H88: =SUM(H84:H87) -> -86791 | I88: =SUM(I84:I87) -> -86791 | J88: =SUM(J84:J87) -> -86791 | K88: =SUM(K84:K87) -> -86791
C90: Net change in cash during period | G90: =G79+G82+G88 -> -34900.268 | H90: =H79+H82+H88 -> -25676.008 | I90: =I79+I82+I88 -> -20446.795 | J90: =J79+J82+J88 -> -15803.152 | K90: =K79+K82+K88 -> -10801.322
C92: PROPERTY, PLANT & EQUIPMENT
C93: =C14 -> Fiscal year | D93: =D14 -> 2016 | E93: =E14 -> 2017 | F93: =F14 -> 2018 | G93: =G14 -> 2019 | H93: =H14 -> 2020 | I93: =I14 -> 2021 | J93: =J14 -> 2022 | K93: =K14 -> 2023
C94: =C15 -> Fiscal year end date | D94: =D15 -> 42643 | E94: =E15 -> 43008 | F94: =F15 -> 43372 | G94: =G15 -> 43738 | H94: =H15 -> 44104 | I94: =I15 -> 44469 | J94: =J15 -> 44834 | K94: =K15 -> 45199
G95: Forecast
C96: Beginning of period | G96: =F99 -> 41304 | H96: =G99 -> 45042.86 | I96: =H99 -> 48611.182 | J96: =I99 -> 51947.568 | K96: =J99 -> 55218.714 | M96: BOP = Previous year EOP
C97: Plus: Capital expenditures | D97: 12734 | E97: 12451 | F97: 13313 | G97: 13285 | H97: 13649 | I97: 13819 | J97: =I97*(1+J36) -> 14772.511 | K97: =J97*(1+K36) -> 15791.814 | M97: JP Morgan through 2021; WSP assumption thereafter
C98: Less: Depreciation | D98: -8300 | E98: -8200 | F98: -9300 | G98: =-(G101*G97) -> -9546.1402 | H98: =-(H101*H97) -> -10080.678 | I98: =-(I101*I97) -> -10482.614 | J98: =-(J101*J97) -> -11501.365 | K98: =-(K101*K97) -> -12610.795 | M98: Capex x 'D&A related to PP&E as a % of capex' ratio (below)
C99: End of period | E99: =E49 -> 33783 | F99: =F49 -> 41304 | G99: =SUM(G96:G98) -> 45042.86 | H99: =SUM(H96:H98) -> 48611.182 | I99: =SUM(I96:I98) -> 51947.568 | J99: =SUM(J96:J98) -> 55218.714 | K99: =SUM(K96:K98) -> 58399.733 | M99: BOP + Capex - Depreciation
M100: Step
C101: D&A related to PP&E as a % of capex | D101: =-(D98/D97) -> 0.65179834 | E101: =-(E98/E97) -> 0.65858164 | F101: =-(F98/F97) -> 0.69856531 | G101: =F101+$M$101 -> 0.71856531 | H101: =G101+$M$101 -> 0.73856531 | I101: =H101+$M$101 -> 0.75856531 | J101: =I101+$M$101 -> 0.77856531 | K101: =J101+$M$101 -> 0.79856531 | M101: 0.02
C103: IMPUTING TOTAL DEPRECIATION & AMORTIZATION
C104: D&A not related to PP&E | D104: =D106+D98 -> 2205 | E104: =E106+E98 -> 1957 | F104: =F106+F98 -> 1603 | G104: =G105*G17 -> 1538.88 | H104: =H105*H17 -> 1631.2128 | I104: =I105*I17 -> 1743.7665 | J104: =J105*J17 -> 1864.0864 | K104: =K105*K17 -> 1992.7083 | M104: Revenue x 'as % of revenue' assumption
C105: as % of revenue | D105: =D104/D17 -> 0.010225423 | E105: =E104/E17 -> 0.008537128 | F105: =F104/F17 -> 0.0060355052 | G105: =F105 -> 0.0060355052 | H105: =G105 -> 0.0060355052 | I105: =H105 -> 0.0060355052 | J105: =I105 -> 0.0060355052 | K105: =J105 -> 0.0060355052 | M105: Straight line last historical % of revenue - WSP assumption
C106: Depreciation & Amortization - Total | D106: =D30 -> 10505 | E106: =E30 -> 10157 | F106: =F30 -> 10903 | G106: =-G98+G104 -> 11085.02 | H106: =-H98+H104 -> 11711.891 | I106: =-I98+I104 -> 12226.381 | J106: =-J98+J104 -> 13365.451 | K106: =-K98+K104 -> 14603.503 | M106: D&A from PP&E + D&A not from PP&E
C108: OTHER NON-CURRENT ASSETS
C109: Beginning of period | G109: =F112 -> 22283 | H109: =G112 -> 21391.68 | I109: =H112 -> 22675.181 | J109: =I112 -> 24239.768 | K109: =J112 -> 25912.312 | M109: BOP = Previous year EOP
C110: Less: Amortization of intangible assets | G110: =-(G104) -> -1538.88 | H110: =-(H104) -> -1631.2128 | I110: =-(I104) -> -1743.7665 | J110: =-(J104) -> -1864.0864 | K110: =-(K104) -> -1992.7083 | M110: Assume all D&A not from PP&E is in non-current assets
C111: Plus: Additions | G111: =G112-G110-G109 -> 647.56 | H111: =H112-H110-H109 -> 2914.7136 | I111: =I112-I110-I109 -> 3308.354 | J111: =J112-J110-J109 -> 3536.6304 | K111: =K112-K110-K109 -> 3780.6579 | M111: Because we already know the EOP balance, this is a plug: EOP - D&A not from PP&E - BOP
C112: End of period | E112: =E50 -> 18177 | F112: =F50 -> 22283 | G112: =G50 -> 21391.68 | H112: =H50 -> 22675.181 | I112: =I50 -> 24239.768 | J112: =J50 -> 25912.312 | K112: =K50 -> 27700.262 | M112: Referenced from balance sheet
C114: RETAINED EARNINGS
C115: Beginning of period | G115: =F119 -> 70400 | H115: =G119 -> 35907.506 | I115: =H119 -> 5326.4074 | J115: =I119 -> -21502.072 | K115: =J119 -> -44514.32 | M115: BOP = Previous year EOP
C116: Plus: Net income | D116: =D28 -> 45687 | E116: =E28 -> 48351 | F116: =F28 -> 59531 | G116: =G28 -> 52298.506 | H116: =H28 -> 56209.901 | I116: =I28 -> 59962.52 | J116: =J28 -> 63778.753 | K116: =K28 -> 67967.319 | M116: Reference from income statement
C117: Less: Dividends | D117: -12188 | E117: -12803 | F117: -13735 | G117: =F117 -> -13735 | H117: =G117 -> -13735 | I117: =H117 -> -13735 | J117: =I117 -> -13735 | K117: =J117 -> -13735 | M117: WSP assumption: Straight-line last historical year dividends
C118: Less: Repurchases | D118: -29000 | E118: -33001 | F118: -73056 | G118: =F118 -> -73056 | H118: =G118 -> -73056 | I118: =H118 -> -73056 | J118: =I118 -> -73056 | K118: =J118 -> -73056 | M118: WSP assumption: Straight-line last historical year repurchases
C119: End of period | D119: =D62 -> 0 | E119: =E62 -> 98330 | F119: =F62 -> 70400 | G119: =SUM(G115:G118) -> 35907.506 | H119: =SUM(H115:H118) -> 5326.4074 | I119: =SUM(I115:I118) -> -21502.072 | J119: =SUM(J115:J118) -> -44514.32 | K119: =SUM(K115:K118) -> -63338.001 | M119: BOP + net income - dividends - repurchases
...

Sheet Extras
C2: ="Financial Statement Model for "&D5 -> Financial Statement Model for Apple
C3: $ in thousands except per share
C5: Company name | D5: Apple
C6: Ticker | D6: AAPL
C7: Circ break 1=off, 0=on | D7: 1
C8: Latest closing share price | D8: 171.25
C9: Latest closing share price date | D9: 43500
C10: Latest fiscal year end date | D10: 43372
C11: Shares outstanding (millions) | D11: 4745.398
C12: Select an operating scenario: | D12: Base case
C14: INCOME STATEMENT
C15: Fiscal year | D15: =E15-1 -> 2016 | E15: =F15-1 -> 2017 | F15: =YEAR(D10) -> 2018 | G15: =F15+1 -> 2019 | H15: =G15+1 -> 2020 | I15: =H15+1 -> 2021 | J15: =I15+1 -> 2022 | K15: =J15+1 -> 2023
C16: Fiscal year end date | D16: =EOMONTH(E16,-12) -> 42643 | E16: =EOMONTH(F16,-12) -> 43008 | F16: =D10 -> 43372 | G16: =EOMONTH(F16,12) -> 43738 | H16: =EOMONTH(G16,12) -> 44104 | I16: =EOMONTH(H16,12) -> 44469 | J16: =EOMONTH(I16,12) -> 44834 | K16: =EOMONTH(J16,12) -> 45199
C18: Revenue | D18: 215639 | E18: 229234 | F18: 265595 | G18: =F18*(1+G37) -> 254971.2 | H18: =G18*(1+H37) -> 270269.47 | I18: =H18*(1+I37) -> 288918.07 | J18: =I18*(1+J37) -> 308853.41 | K18: =J18*(1+K37) -> 330164.3 | M18: Previous year's revenues x (1+revenue growth rate)
C19: Cost of sales (enter as -) | D19: -131376 | E19: -141048 | F19: -163756 | G19: =G20-G18 -> -158592.09 | H19: =H20-H18 -> -167296.8 | I19: =I20-I18 -> -178551.36 | J19: =J20-J18 -> -190871.41 | K19: =K20-K18 -> -204041.54 | M19: Plug = Revenue - Gross Profit
C20: Gross Profit | D20: =SUM(D18:D19) -> 84263 | E20: =SUM(E18:E19) -> 88186 | F20: =SUM(F18:F19) -> 101839 | G20: =G18*G38 -> 96379.114 | H20: =H18*H38 -> 102972.67 | I20: =I18*I38 -> 110366.7 | J20: =J18*J38 -> 117982 | K20: =K18*K38 -> 126122.76 | M20: Revenue x Gross Profit Margin forecast
C21: Research & development (enter as -) | D21: -10045 | E21: -11581 | F21: -14236 | G21: =-G39*G18 -> -15808.214 | H21: =-H39*H18 -> -17026.977 | I21: =-I39*I18 -> -18201.838 | J21: =-J39*J18 -> -19457.765 | K21: =-K39*K18 -> -20800.351 | M21: Revenue x R&D % of sales forecast
C22: Selling, general & administrative (enter as -) | D22: -14194 | E22: -15261 | F22: -16705 | G22: =-G18*G40 -> -18867.869 | H22: =-H18*H40 -> -18648.594 | I22: =-I18*I40 -> -19935.347 | J22: =-J18*J40 -> -21310.885 | K22: =-K18*K40 -> -22781.337 | M22: Revenue x SG&A % of sales forecast
C23: Operating profit (EBIT) | D23: =D20+D21+D22 -> 60024 | E23: =E20+E21+E22 -> 61344 | F23: =F20+F21+F22 -> 70898 | G23: =G20+G21+G22 -> 61703.03 | H23: =H20+H21+H22 -> 67297.099 | I23: =I20+I21+I22 -> 72229.516 | J23: =J20+J21+J22 -> 77213.353 | K23: =K20+K21+K22 -> 82541.074 | M23: Gross Profit - R&D - SG&A
C24: Interest income | D24: 3999 | E24: 5201 | F24: 5686 | G24: =G157 -> 4744.4371 | H24: =H157 -> 4090.2133 | I24: =I157 -> 3592.0871 | J24: =J157 -> 3200.5876 | K24: =K157 -> 2913.2593 | M24: Reference from interest on cash schedule
C25: Interest expense (enter as -) | D25: -1456 | E25: -2323 | F25: -3240 | G25: =-G143 -> -3223.1469 | H25: =-H143 -> -3223.5393 | I25: =-I143 -> -3223.5393 | J25: =-J143 -> -3223.5393 | K25: =-K143 -> -3223.5393 | M25: Reference from interest expense schedule
C26: Other expense, net (enter as -) | D26: -1195 | E26: -133 | F26: -441 | G26: =F26 -> -441 | H26: =G26 -> -441 | I26: =H26 -> -441 | J26: =I26 -> -441 | K26: =J26 -> -441 | M26: Straight-line
C27: Pretax profit | D27: =SUM(D23:D26) -> 61372 | E27: =SUM(E23:E26) -> 64089 | F27: =SUM(F23:F26) -> 72903 | G27: =SUM(G23:G26) -> 62783.321 | H27: =SUM(H23:H26) -> 67722.773 | I27: =SUM(I23:I26) -> 72157.064 | J27: =SUM(J23:J26) -> 76749.401 | K27: =SUM(K23:K26) -> 81789.794 | M27: EBIT + interest income less interest expense less other expense
C28: Taxes (enter expense as -) | D28: -15685 | E28: -15738 | F28: -13372 | G28: =-G41*G27 -> -10484.815 | H28: =-H41*H27 -> -11512.871 | I28: =-I41*I27 -> -12194.544 | J28: =-J41*J27 -> -12970.649 | K28: =-K41*K27 -> -13822.475 | M28: Pre-tax Profit x Tax Rate forecast
C29: Net income | D29: =SUM(D27:D28) -> 45687 | E29: =SUM(E27:E28) -> 48351 | F29: =SUM(F27:F28) -> 59531 | G29: =SUM(G27:G28) -> 52298.506 | H29: =SUM(H27:H28) -> 56209.901 | I29: =SUM(I27:I28) -> 59962.52 | J29: =SUM(J27:J28) -> 63778.753 | K29: =SUM(K27:K28) -> 67967.319 | M29: Pre-tax Profit less taxes
C31: Depreciation & amortization | D31: 10505 | E31: 10157 | F31: 10903 | G31: =G107 -> 11085.02 | H31: =H107 -> 11711.891 | I31: =I107 -> 12226.381 | J31: =J107 -> 13365.451 | K31: =K107 -> 14603.503 | M31: Reference from D&A schedule
C32: EBITDA | D32: =D23+D31 -> 70529 | E32: =E23+E31 -> 71501 | F32: =F23+F31 -> 81801 | G32: =G23+G31 -> 72788.051 | H32: =H23+H31 -> 79008.989 | I32: =I23+I31 -> 84455.897 | J32: =J23+J31 -> 90578.804 | K32: =K23+K31 -> 97144.578 | M32: EBIT + D&A
C33: Stock based compensation | D33: 4210 | E33: 4840 | F33: 5340 | G33: =F33*(1+G37) -> 5126.4 | H33: =G33*(1+H37) -> 5433.984 | I33: =H33*(1+I37) -> 5808.9289 | J33: =I33*(1+J37) -> 6209.745 | K33: =J33*(1+K37) -> 6638.2174 | M33: WSP assumption: grow SBC in-line with revenue growth
C34: Adjusted EBITDA | D34: =SUM(D32:D33) -> 74739 | E34: =SUM(E32:E33) -> 76341 | F34: =SUM(F32:F33) -> 87141 | G34: =SUM(G32:G33) -> 77914.451 | H34: =SUM(H32:H33) -> 84442.973 | I34: =SUM(I32:I33) -> 90264.826 | J34: =SUM(J32:J33) -> 96788.549 | K34: =SUM(K32:K33) -> 103782.8 | M34: EBITDA + Stock-based compensation
C36: Growth rates & margins
C37: Revenue growth | E37: =E18/D18-1 -> 0.063045182 | F37: =F18/E18-1 -> 0.15861958 | G37: =G175 -> -0.04 | H37: =H175 -> 0.06 | I37: =I175 -> 0.069 | J37: =J175 -> 0.069 | K37: =K175 -> 0.069 | M37: From scenario analysis below
C38: Gross profit margin | D38: =D20/D18 -> 0.39075956 | E38: =E20/E18 -> 0.3846986 | F38: =F20/F18 -> 0.38343719 | G38: =G176 -> 0.378 | H38: =H176 -> 0.381 | I38: =I176 -> 0.382 | J38: =J176 -> 0.382 | K38: =K176 -> 0.382 | M38: From scenario analysis below
C39: R&D % of sales | D39: =-D21/D18 -> 0.046582483 | E39: =-E21/E18 -> 0.050520429 | F39: =-F21/F18 -> 0.053600407 | G39: =G177 -> 0.062 | H39: =H177 -> 0.063 | I39: =I177 -> 0.063 | J39: =J177 -> 0.063 | K39: =K177 -> 0.063 | M39: From scenario analysis below
C40: SG&A % of sales | D40: =-D22/D18 -> 0.065822973 | E40: =-E22/E18 -> 0.066573894 | F40: =-F22/F18 -> 0.062896515 | G40: =G178 -> 0.074 | H40: =H178 -> 0.069 | I40: =I178 -> 0.069 | J40: =J178 -> 0.069 | K40: =K178 -> 0.069 | M40: From scenario analysis below
C41: Tax rate | D41: =-(D28/D27) -> 0.25557257 | E41: =-(E28/E27) -> 0.24556476 | F41: =-(F28/F27) -> 0.18342181 | G41: 0.167 | H41: 0.17 | I41: 0.169 | J41: =I41 -> 0.169 | K41: =J41 -> 0.169 | M41: JP Morgan estimates through 2021: straight-line margin thereafter
C43: BALANCE SHEET
C44: =C15 -> Fiscal year | E44: =E15 -> 2017 | F44: =F15 -> 2018 | G44: =G15 -> 2019 | H44: =H15 -> 2020 | I44: =I15 -> 2021 | J44: =J15 -> 2022 | K44: =K15 -> 2023
C45: =C16 -> Fiscal year end date | E45: =E16 -> 43008 | F45: =F16 -> 43372 | G45: =G16 -> 43738 | H45: =H16 -> 44104 | I45: =I16 -> 44469 | J45: =J16 -> 44834 | K45: =K16 -> 45199
C46: Cash & equivalents, ST and LT marketable securities | E46: =20289+53892+194714 -> 268895 | F46: =25913+40388+170799 -> 237100 | G46: =G91+F46 -> 202199.73 | H46: =H91+G46 -> 176523.72 | I46: =I91+H46 -> 156076.93 | J46: =J91+I46 -> 140273.78 | K46: =K91+J46 -> 129472.46 | M46: Reference from 'net change in cash' line on the cash flow statement
C47: Accounts receivable | E47: 17874 | F47: 23186 | G47: =F47*(1+G37) -> 22258.56 | H47: =G47*(1+H37) -> 23594.074 | I47: =H47*(1+I37) -> 25222.065 | J47: =I47*(1+J37) -> 26962.387 | K47: =J47*(1+K37) -> 28822.792 | M47: Grow in-line with revenue growth
C48: Inventories | E48: 4855 | F48: 3956 | G48: =F48*G19/F19 -> 3831.2507 | H48: =G48*H19/G19 -> 4041.5383 | I48: =H48*I19/H19 -> 4313.4248 | J48: =I48*J19/I19 -> 4611.0512 | K48: =J48*K19/J19 -> 4929.2137 | M48: Grow in-line with cost of sales growth
C49: Other current assets | E49: =17799+13936 -> 31735 | F49: =25809+12087 -> 37896 | G49: =F49*(1+G37) -> 36380.16 | H49: =G49*(1+H37) -> 38562.97 | I49: =H49*(1+I37) -> 41223.815 | J49: =I49*(1+J37) -> 44068.258 | K49: =J49*(1+K37) -> 47108.967 | M49: Grow in-line with revenue growth
C50: Property, plant & equipment | E50: 33783 | F50: 41304 | G50: =G100 -> 45042.86 | H50: =H100 -> 48611.182 | I50: =I100 -> 51947.568 | J50: =J100 -> 55218.714 | K50: =K100 -> 58399.733 | M50: Reference from PP&E schedule
C51: Other non current assets | E51: 18177 | F51: 22283 | G51: =F51*(1+G37) -> 21391.68 | H51: =G51*(1+H37) -> 22675.181 | I51: =H51*(1+I37) -> 24239.768 | J51: =I51*(1+J37) -> 25912.312 | K51: =J51*(1+K37) -> 27700.262 | M51: Grow in-line with revenue growth
C52: Total assets | E52: =SUM(E46:E51) -> 375319 | F52: =SUM(F46:F51) -> 365725 | G52: =SUM(G46:G51) -> 331104.24 | H52: =SUM(H46:H51) -> 314008.67 | I52: =SUM(I46:I51) -> 303023.57 | J52: =SUM(J46:J51) -> 297046.5 | K52: =SUM(K46:K51) -> 296433.42
C54: Accounts payable | E54: 44242 | F54: 55888 | G54: =F54*G19/F19 -> 54125.617 | H54: =G54*H19/G19 -> 57096.435 | I54: =H54*I19/H19 -> 60937.484 | J54: =I54*J19/I19 -> 65142.171 | K54: =J54*K19/J19 -> 69636.98 | M54: Grow in-line with cost of sales growth
C55: Other current liabilities | E55: 30551 | F55: 32687 | G55: =F55*(1+G37) -> 31379.52 | H55: =G55*(1+H37) -> 33262.291 | I55: =H55*(1+I37) -> 35557.389 | J55: =I55*(1+J37) -> 38010.849 | K55: =J55*(1+K37) -> 40633.598 | M55: Grow in-line with revenue growth
C56: Deferred revenue (current and non current) | E56: =7548+2836 -> 10384 | F56: =7543+2797 -> 10340 | G56: =F56*(1+G37) -> 9926.4 | H56: =G56*(1+H37) -> 10521.984 | I56: =H56*(1+I37) -> 11248.001 | J56: =I56*(1+J37) -> 12024.113 | K56: =J56*(1+K37) -> 12853.777 | M56: Grow in-line with revenue growth
C57: Commercial paper / revolver | E57: 11977 | F57: 11964 | G57: =G136 -> 12000 | H57: =H136 -> 12000 | I57: =I136 -> 12000 | J57: =J136 -> 12000 | K57: =K136 -> 12000 | M57: Reference EOP balance from CP/revolver schedule
C58: Long term debt (includes current portion) | E58: =6496+97207 -> 103703 | F58: =8784+93735 -> 102519 | G58: =F58 -> 102519 | H58: =G58 -> 102519 | I58: =H58 -> 102519 | J58: =I58 -> 102519 | K58: =J58 -> 102519 | M58: WSP assumption: straight-line
C59: Other non current liabilities | E59: 40415 | F59: 45180 | G59: =F59*(1+G37) -> 43372.8 | H59: =G59*(1+H37) -> 45975.168 | I59: =H59*(1+I37) -> 49147.455 | J59: =I59*(1+J37) -> 52538.629 | K59: =J59*(1+K37) -> 56163.794 | M59: Grow in-line with revenue growth
C60: Total liabilities | E60: =SUM(E54:E59) -> 241272 | F60: =SUM(F54:F59) -> 258578 | G60: =SUM(G54:G59) -> 253323.34 | H60: =SUM(H54:H59) -> 261374.88 | I60: =SUM(I54:I59) -> 271409.33 | J60: =SUM(J54:J59) -> 282234.76 | K60: =SUM(K54:K59) -> 293807.15
C62: Common stock | E62: 35867 | F62: 40201 | G62: =F62+G33 -> 45327.4 | H62: =G62+H33 -> 50761.384 | I62: =H62+I33 -> 56570.313 | J62: =I62+J33 -> 62780.058 | K62: =J62+K33 -> 69418.275 | M62: Increase by stock-based compensation forecasted in the I/S section
C63: Retained earnings | E63: =98330 -> 98330 | F63: 70400 | G63: =G120 -> 35907.506 | H63: =H120 -> 5326.4074 | I63: =I120 -> -21502.072 | J63: =J120 -> -44514.32 | K63: =K120 -> -63338.001 | M63: Reference from Retained Earnings schedule
C64: Other comprehensive income | E64: -150 | F64: -3454 | G64: =F64 -> -3454 | H64: =G64 -> -3454 | I64: =H64 -> -3454 | J64: =I64 -> -3454 | K64: =J64 -> -3454 | M64: WSP assumption: straight-line
C65: Total equity | E65: =SUM(E62:E64) -> 134047 | F65: =SUM(F62:F64) -> 107147 | G65: =SUM(G62:G64) -> 77780.906 | H65: =SUM(H62:H64) -> 52633.791 | I65: =SUM(I62:I64) -> 31614.241 | J65: =SUM(J62:J64) -> 14811.738 | K65: =SUM(K62:K64) -> 2626.2747
C67: Balance check | E67: =ROUND(E52-E60-E65,3) -> 0 | F67: =ROUND(F52-F60-F65,3) -> 0 | G67: =ROUND(G52-G60-G65,3) -> 0 | H67: =ROUND(H52-H60-H65,3) -> 0 | I67: =ROUND(I52-I60-I65,3) -> 0 | J67: =ROUND(J52-J60-J65,3) -> 0 | K67: =ROUND(K52-K60-K65,3) -> 0
C69: CASH FLOW STATEMENT
C70: =C15 -> Fiscal year | G70: =G15 -> 2019 | H70: =H15 -> 2020 | I70: =I15 -> 2021 | J70: =J15 -> 2022 | K70: =K15 -> 2023
C71: =C16 -> Fiscal year end date | G71: =G16 -> 43738 | H71: =H16 -> 44104 | I71: =I16 -> 44469 | J71: =J16 -> 44834 | K71: =K16 -> 45199
C73: Net income | G73: =G29 -> 52298.506 | H73: =H29 -> 56209.901 | I73: =I29 -> 59962.52 | J73: =J29 -> 63778.753 | K73: =K29 -> 67967.319
C74: Depreciation and amortization | G74: =G31 -> 11085.02 | H74: =H31 -> 11711.891 | I74: =I31 -> 12226.381 | J74: =J31 -> 13365.451 | K74: =K31 -> 14603.503 | M74: Reference from the I/S
C75: Stock based compensation | G75: =G33 -> 5126.4 | H75: =H33 -> 5433.984 | I75: =I33 -> 5808.9289 | J75: =J33 -> 6209.745 | K75: =K33 -> 6638.2174
C76: Decreases / (Increases) in working capital assets | G76: =-1*(SUM(G47:G49)-SUM(F47:F49)) -> 2568.0293 | H76: =-1*(SUM(H47:H49)-SUM(G47:G49)) -> -3728.6108 | I76: =-1*(SUM(I47:I49)-SUM(H47:H49)) -> -4560.7225 | J76: =-1*(SUM(J47:J49)-SUM(I47:I49)) -> -4882.392 | K76: =-1*(SUM(K47:K49)-SUM(J47:J49)) -> -5219.277
C77: Increases / (Decreases) in working capital liabilities | G77: =SUM(G54:G56)-SUM(F54:F56) -> -3483.4631 | H77: =SUM(H54:H56)-SUM(G54:G56) -> 5449.1728 | I77: =SUM(I54:I56)-SUM(H54:H56) -> 6862.1646 | J77: =SUM(J54:J56)-SUM(I54:I56) -> 7434.2583 | K77: =SUM(K54:K56)-SUM(J54:J56) -> 7947.2222
C78: Other non current assets | G78: =-(G112) -> -647.56 | H78: =-(H112) -> -2914.7136 | I78: =-(I112) -> -3308.354 | J78: =-(J112) -> -3536.6304 | K78: =-(K112) -> -3780.6579 | M78: Reference from schedule NOT the B/S: Only include 'Additions' (as outflow)
C79: Other non current liabilities | G79: =G59-F59 -> -1807.2 | H79: =H59-G59 -> 2602.368 | I79: =I59-H59 -> 3172.2866 | J79: =J59-I59 -> 3391.1744 | K79: =K59-J59 -> 3625.1654
C80: Cash from operating activities | G80: =SUM(G73:G79) -> 65139.732 | H80: =SUM(H73:H79) -> 74763.992 | I80: =SUM(I73:I79) -> 80163.205 | J80: =SUM(J73:J79) -> 85760.359 | K80: =SUM(K73:K79) -> 91781.493
C82: Capital expenditures | G82: =-(G98) -> -13285 | H82: =-(H98) -> -13649 | I82: =-(I98) -> -13819 | J82: =-(J98) -> -14772.511 | K82: =-(K98) -> -15791.814 | M82: Reference from PP&E schedule
C83: Cash from investing activities | G83: =IFERROR(G82,"NA") -> -13285 | H83: =IFERROR(H82,"NA") -> -13649 | I83: =IFERROR(I82,"NA") -> -13819 | J83: =IFERROR(J82,"NA") -> -14772.511 | K83: =IFERROR(K82,"NA") -> -15791.814
C85: Long term debt | G85: =G58-F58 -> 0 | H85: =H58-G58 -> 0 | I85: =I58-H58 -> 0 | J85: =J58-I58 -> 0 | K85: =K58-J58 -> 0
C86: Revolver | G86: =G57-F57 -> 36 | H86: =H57-G57 -> 0 | I86: =I57-H57 -> 0 | J86: =J57-I57 -> 0 | K86: =K57-J57 -> 0 | M86: Reference from B/S
C87: Share repurchases | G87: =G119 -> -73056 | H87: =H119 -> -73056 | I87: =I119 -> -73056 | J87: =J119 -> -73056 | K87: =K119 -> -73056 | M87: Reference from Retained Earnings schedule
C88: Common dividends | G88: =G118 -> -13735 | H88: =H118 -> -13735 | I88: =I118 -> -13735 | J88: =J118 -> -13735 | K88: =K118 -> -13735 | M88: Reference from Retained Earnings schedule
C89: Cash from financing activities | G89: =SUM(G85:G88) -> -86755 | H89: =SUM(H85:H88) -> -86791 | I89: =SUM(I85:I88) -> -86791 | J89: =SUM(J85:J88) -> -86791 | K89: =SUM(K85:K88) -> -86791
C91: Net change in cash during period | G91: =G80+G83+G89 -> -34900.268 | H91: =H80+H83+H89 -> -25676.008 | I91: =I80+I83+I89 -> -20446.795 | J91: =J80+J83+J89 -> -15803.152 | K91: =K80+K83+K89 -> -10801.322
C93: PROPERTY, PLANT & EQUIPMENT
C94: =C15 -> Fiscal year | D94: =D15 -> 2016 | E94: =E15 -> 2017 | F94: =F15 -> 2018 | G94: =G15 -> 2019 | H94: =H15 -> 2020 | I94: =I15 -> 2021 | J94: =J15 -> 2022 | K94: =K15 -> 2023
C95: =C16 -> Fiscal year end date | D95: =D16 -> 42643 | E95: =E16 -> 43008 | F95: =F16 -> 43372 | G95: =G16 -> 43738 | H95: =H16 -> 44104 | I95: =I16 -> 44469 | J95: =J16 -> 44834 | K95: =K16 -> 45199
G96: Forecast
C97: Beginning of period | G97: =F100 -> 41304 | H97: =G100 -> 45042.86 | I97: =H100 -> 48611.182 | J97: =I100 -> 51947.568 | K97: =J100 -> 55218.714 | M97: BOP = Previous year EOP
C98: Plus: Capital expenditures | D98: 12734 | E98: 12451 | F98: 13313 | G98: 13285 | H98: 13649 | I98: 13819 | J98: =I98*(1+J37) -> 14772.511 | K98: =J98*(1+K37) -> 15791.814 | M98: JP Morgan through 2021; WSP assumption thereafter
C99: Less: Depreciation | D99: -8300 | E99: -8200 | F99: -9300 | G99: =-(G102*G98) -> -9546.1402 | H99: =-(H102*H98) -> -10080.678 | I99: =-(I102*I98) -> -10482.614 | J99: =-(J102*J98) -> -11501.365 | K99: =-(K102*K98) -> -12610.795 | M99: Capex x 'D&A related to PP&E as a % of capex' ratio (below)
C100: End of period | E100: =E50 -> 33783 | F100: =F50 -> 41304 | G100: =SUM(G97:G99) -> 45042.86 | H100: =SUM(H97:H99) -> 48611.182 | I100: =SUM(I97:I99) -> 51947.568 | J100: =SUM(J97:J99) -> 55218.714 | K100: =SUM(K97:K99) -> 58399.733 | M100: BOP + Capex - Depreciation
M101: Step
C102: D&A related to PP&E as a % of capex | D102: =-(D99/D98) -> 0.65179834 | E102: =-(E99/E98) -> 0.65858164 | F102: =-(F99/F98) -> 0.69856531 | G102: =F102+$M$102 -> 0.71856531 | H102: =G102+$M$102 -> 0.73856531 | I102: =H102+$M$102 -> 0.75856531 | J102: =I102+$M$102 -> 0.77856531 | K102: =J102+$M$102 -> 0.79856531 | M102: 0.02
C104: IMPUTING TOTAL DEPRECIATION & AMORTIZATION
C105: D&A not related to PP&E | D105: =D107+D99 -> 2205 | E105: =E107+E99 -> 1957 | F105: =F107+F99 -> 1603 | G105: =G106*G18 -> 1538.88 | H105: =H106*H18 -> 1631.2128 | I105: =I106*I18 -> 1743.7665 | J105: =J106*J18 -> 1864.0864 | K105: =K106*K18 -> 1992.7083 | M105: Revenue x 'as % of revenue' assumption
C106: as % of revenue | D106: =D105/D18 -> 0.010225423 | E106: =E105/E18 -> 0.008537128 | F106: =F105/F18 -> 0.0060355052 | G106: =F106 -> 0.0060355052 | H106: =G106 -> 0.0060355052 | I106: =H106 -> 0.0060355052 | J106: =I106 -> 0.0060355052 | K106: =J106 -> 0.0060355052 | M106: Straight line last historical % of revenue - WSP assumption
C107: Depreciation & Amortization - Total | D107: =D31 -> 10505 | E107: =E31 -> 10157 | F107: =F31 -> 10903 | G107: =-G99+G105 -> 11085.02 | H107: =-H99+H105 -> 11711.891 | I107: =-I99+I105 -> 12226.381 | J107: =-J99+J105 -> 13365.451 | K107: =-K99+K105 -> 14603.503 | M107: D&A from PP&E + D&A not from PP&E
C109: OTHER NON-CURRENT ASSETS
C110: Beginning of period | G110: =F113 -> 22283 | H110: =G113 -> 21391.68 | I110: =H113 -> 22675.181 | J110: =I113 -> 24239.768 | K110: =J113 -> 25912.312 | M110: BOP = Previous year EOP
C111: Less: Amortization of intangible assets | G111: =-(G105) -> -1538.88 | H111: =-(H105) -> -1631.2128 | I111: =-(I105) -> -1743.7665 | J111: =-(J105) -> -1864.0864 | K111: =-(K105) -> -1992.7083 | M111: Assume all D&A not from PP&E is in non-current assets
C112: Plus: Additions | G112: =G113-G111-G110 -> 647.56 | H112: =H113-H111-H110 -> 2914.7136 | I112: =I113-I111-I110 -> 3308.354 | J112: =J113-J111-J110 -> 3536.6304 | K112: =K113-K111-K110 -> 3780.6579 | M112: Because we already know the EOP balance, this is a plug: EOP - D&A not from PP&E - BOP
C113: End of period | E113: =E51 -> 18177 | F113: =F51 -> 22283 | G113: =G51 -> 21391.68 | H113: =H51 -> 22675.181 | I113: =I51 -> 24239.768 | J113: =J51 -> 25912.312 | K113: =K51 -> 27700.262 | M113: Referenced from balance sheet
C115: RETAINED EARNINGS
C116: Beginning of period | G116: =F120 -> 70400 | H116: =G120 -> 35907.506 | I116: =H120 -> 5326.4074 | J116: =I120 -> -21502.072 | K116: =J120 -> -44514.32 | M116: BOP = Previous year EOP
C117: Plus: Net income | D117: =D29 -> 45687 | E117: =E29 -> 48351 | F117: =F29 -> 59531 | G117: =G29 -> 52298.506 | H117: =H29 -> 56209.901 | I117: =I29 -> 59962.52 | J117: =J29 -> 63778.753 | K117: =K29 -> 67967.319 | M117: Reference from income statement
C118: Less: Dividends | D118: -12188 | E118: -12803 | F118: -13735 | G118: =F118 -> -13735 | H118: =G118 -> -13735 | I118: =H118 -> -13735 | J118: =I118 -> -13735 | K118: =J118 -> -13735 | M118: WSP assumption: Straight-line last historical year dividends
C119: Less: Repurchases | D119: -29000 | E119: -33001 | F119: -73056 | G119: =F119 -> -73056 | H119: =G119 -> -73056 | I119: =H119 -> -73056 | J119: =I119 -> -73056 | K119: =J119 -> -73056 | M119: WSP assumption: Straight-line last historical year repurchases
...

Sheet Rev Build
C2: Price / volume build
C3: =Extras!C15 -> Fiscal year | D3: =Extras!D15 -> 2016 | E3: =Extras!E15 -> 2017 | F3: =Extras!F15 -> 2018 | G3: =Extras!G15 -> 2019 | H3: =Extras!H15 -> 2020 | I3: =Extras!I15 -> 2021 | J3: =Extras!J15 -> 2022 | K3: =Extras!K15 -> 2023
C4: =Extras!C16 -> Fiscal year end date | D4: =Extras!D16 -> 42643 | E4: =Extras!E16 -> 43008 | F4: =Extras!F16 -> 43372 | G4: =Extras!G16 -> 43738 | H4: =Extras!H16 -> 44104 | I4: =Extras!I16 -> 44469 | J4: =Extras!J16 -> 44834 | K4: =Extras!K16 -> 45199
C5: Revenue by product
C6: Core products
C7: iPhone | D7: 136700 | E7: 141319 | F7: 166699 | G7: =G17*G22/1000 -> 137570.4 | H7: =H17*H22/1000 -> 138388 | I7: =I17*I22/1000 -> 138388 | J7: =J17*J22/1000 -> 138388 | K7: =K17*K22/1000 -> 138388
C8: iPad | D8: 20628 | E8: 19222 | F8: 18805 | G8: =G18*G23/1000 -> 20222.922 | H8: =H18*H23/1000 -> 20475.904 | I8: =I18*I23/1000 -> 20475.904 | J8: =J18*J23/1000 -> 20475.904 | K8: =K18*K23/1000 -> 20475.904
C9: Mac | D9: 22831 | E9: 25850 | F9: 25484 | G9: =G19*G24/1000 -> 26515.16 | H9: =H19*H24/1000 -> 26642.88 | I9: =I19*I24/1000 -> 26642.88 | J9: =J19*J24/1000 -> 26642.88 | K9: =K19*K24/1000 -> 26642.88
C11: Services | D11: 24348 | E11: 29980 | F11: 37190 | G11: 45603 | H11: 53592 | I11: =H11*(1+I40) -> 62980.56 | J11: =I11*(1+J40) -> 74013.862 | K11: =J11*(1+K40) -> 86980.043 | M11: CG estimates through 2020; WSP thereafter based on growth rate assumption
C12: Other products | D12: 11132 | E12: 12863 | F12: 17417 | G12: 23079 | H12: 26278 | I12: =H12*(1+I41) -> 29920.416 | J12: =I12*(1+J41) -> 34067.711 | K12: =J12*(1+K41) -> 38789.865 | M12: CG estimates through 2020; WSP thereafter based on growth rate assumption
C13: Total revenue | D13: =SUM(D7:D9)+SUM(D11:D12) -> 215639 | E13: =SUM(E7:E9)+SUM(E11:E12) -> 229234 | F13: =SUM(F7:F9)+SUM(F11:F12) -> 265595 | G13: =SUM(G7:G9)+SUM(G11:G12) -> 252990.48 | H13: =SUM(H7:H9)+SUM(H11:H12) -> 265376.78 | I13: =SUM(I7:I9)+SUM(I11:I12) -> 278407.76 | J13: =SUM(J7:J9)+SUM(J11:J12) -> 293588.36 | K13: =SUM(K7:K9)+SUM(K11:K12) -> 311276.69
C14: % growth | E14: =E13/D13-1 -> 0.063045182 | F14: =F13/E13-1 -> 0.15861958 | G14: =G13/F13-1 -> -0.047457664 | H14: =H13/G13-1 -> 0.048959559 | I14: =I13/H13-1 -> 0.049103677 | J14: =J13/I13-1 -> 0.054526487 | K14: =K13/J13-1 -> 0.060248763
C16: Units
C17: iPhone | D17: 211884 | E17: 216756 | F17: 217722 | G17: 173700 | H17: 190880 | I17: 190880 | J17: 190880 | K17: 190880 | M17: CG estimates through 2020; Straight line therafter
C18: iPad | D18: 45590 | E18: 43753 | F18: 43535 | G18: 46170 | H18: 49260 | I18: 49260 | J18: 49260 | K18: 49260 | M18: CG estimates through 2020; Straight line therafter
C19: Mac | D19: 18484 | E19: 19251 | F19: 18209 | G19: 19670 | H19: 19140 | I19: 19140 | J19: 19140 | K19: 19140 | M19: CG estimates through 2020; Straight line therafter
C21: Average selling price
C22: iPhone | D22: =D7/D17*1000 -> 645.16434 | E22: =E7/E17*1000 -> 651.97273 | F22: =F7/F17*1000 -> 765.65069 | G22: 792 | H22: 725 | I22: 725 | J22: 725 | K22: 725 | M22: CG estimates through 2020; Straight line therafter
C23: iPad | D23: =D8/D18*1000 -> 452.46765 | E23: =E8/E18*1000 -> 439.32987 | F23: =F8/F18*1000 -> 431.9513 | G23: 438.01 | H23: 415.67 | I23: 415.67 | J23: 415.67 | K23: 415.67 | M23: CG estimates through 2020; Straight line therafter
C24: Mac | D24: =D9/D19*1000 -> 1235.1764 | E24: =E9/E19*1000 -> 1342.7874 | F24: =F9/F19*1000 -> 1399.5277 | G24: 1348 | H24: 1392 | I24: 1392 | J24: 1392 | K24: 1392 | M24: CG estimates through 2020; Straight line therafter
C26: Units % growth
C27: iPhone | E27: =E17/D17-1 -> 0.022993714 | F27: =F17/E17-1 -> 0.004456624 | G27: =G17/F17-1 -> -0.20219362 | H27: =H17/G17-1 -> 0.09890616 | I27: =I17/H17-1 -> 0 | J27: =J17/I17-1 -> 0 | K27: =K17/J17-1 -> 0
C28: iPad | E28: =E18/D18-1 -> -0.040293924 | F28: =F18/E18-1 -> -0.0049825155 | G28: =G18/F18-1 -> 0.060526014 | H28: =H18/G18-1 -> 0.066926576 | I28: =I18/H18-1 -> 0 | J28: =J18/I18-1 -> 0 | K28: =K18/J18-1 -> 0
C29: Mac | E29: =E19/D19-1 -> 0.041495347 | F29: =F19/E19-1 -> -0.054127058 | G29: =G19/F19-1 -> 0.080235049 | H29: =H19/G19-1 -> -0.026944586 | I29: =I19/H19-1 -> 0 | J29: =J19/I19-1 -> 0 | K29: =K19/J19-1 -> 0
C31: Average selling price % growth
C32: iPhone | E32: =E22/D22-1 -> 0.010552955 | F32: =F22/E22-1 -> 0.17436 | G32: =G22/F22-1 -> 0.034414268 | H32: =H22/G22-1 -> -0.08459596 | I32: =I22/H22-1 -> 0 | J32: =J22/I22-1 -> 0 | K32: =K22/J22-1 -> 0
C33: iPad | E33: =E23/D23-1 -> -0.029035826 | F33: =F23/E23-1 -> -0.016795059 | G33: =G23/F23-1 -> 0.014026341 | H33: =H23/G23-1 -> -0.051003402 | I33: =I23/H23-1 -> 0 | J33: =J23/I23-1 -> 0 | K33: =K23/J23-1 -> 0
C34: Mac | E34: =E24/D24-1 -> 0.087121986 | F34: =F24/E24-1 -> 0.042255624 | G34: =G24/F24-1 -> -0.036817925 | H34: =H24/G24-1 -> 0.03264095 | I34: =I24/H24-1 -> 0 | J34: =J24/I24-1 -> 0 | K34: =K24/J24-1 -> 0
C36: Revenue growth rate by product
C37: iPhone | E37: =E7/D7-1 -> 0.03378932 | F37: =F7/E7-1 -> 0.17959369 | G37: =G7/F7-1 -> -0.1747377 | H37: =H7/G7-1 -> 0.0059431389 | I37: =I7/H7-1 -> 0 | J37: =J7/I7-1 -> 0 | K37: =K7/J7-1 -> 0
C38: iPad | E38: =E8/D8-1 -> -0.068159783 | F38: =F8/E8-1 -> -0.021693892 | G38: =G8/F8-1 -> 0.075401313 | H38: =H8/G8-1 -> 0.012509691 | I38: =I8/H8-1 -> 0 | J38: =J8/I8-1 -> 0 | K38: =K8/J8-1 -> 0
C39: Mac | E39: =E9/D9-1 -> 0.13223249 | F39: =F9/E9-1 -> -0.014158607 | G39: =G9/F9-1 -> 0.040463036 | H39: =H9/G9-1 -> 0.004816867 | I39: =I9/H9-1 -> 0 | J39: =J9/I9-1 -> 0 | K39: =K9/J9-1 -> 0
C40: Services | E40: =E11/D11-1 -> 0.23131263 | F40: =F11/E11-1 -> 0.24049366 | G40: =G11/F11-1 -> 0.22621672 | H40: =H11/G11-1 -> 0.17518584 | I40: =H40 -> 0.17518584 | J40: =I40 -> 0.17518584 | K40: =J40 -> 0.17518584 | M40: CG estimates through 2020; Straight line growth rate thereafter
C41: Other products | E41: =E12/D12-1 -> 0.15549766 | F41: =F12/E12-1 -> 0.35403872 | G41: =G12/F12-1 -> 0.32508469 | H41: =H12/G12-1 -> 0.13861086 | I41: =H41 -> 0.13861086 | J41: =I41 -> 0.13861086 | K41: =J41 -> 0.13861086 | M41: CG estimates through 2020; Straight line growth rate thereafter
M43: "iPhone ASP will be primary driver as Apple continues to increase hardware prices."
M44: Jeffries research note January 30, 2019

Sheet 2019 FSM Update
C2: ="Financial Statement Model for "&D5 -> Financial Statement Model for Apple
C3: $ in thousands except per share
C5: Company name | D5: Apple | I5: Select an operating scenario: | L5: Base case
C6: Ticker | D6: AAPL
C7: Circ break 1=off, 0=on | D7: 1
C8: Latest closing share price | D8: 293.65
C9: Latest closing share price date | D9: 43830
C10: Latest fiscal year end date | D10: 43737
C11: Shares outstanding (millions) | D11: 4443.265
C13: INCOME STATEMENT
C14: Fiscal year | D14: =E14-1 -> 2016 | E14: =F14-1 -> 2017 | F14: =G14-1 -> 2018 | G14: =YEAR(D10) -> 2019 | H14: =G14+1 -> 2020 | I14: =H14+1 -> 2021 | J14: =I14+1 -> 2022 | K14: =J14+1 -> 2023 | L14: =K14+1 -> 2024
C15: Fiscal year end date | D15: =EOMONTH(E15,-12) -> 42643 | E15: =EOMONTH(F15,-12) -> 43008 | F15: 43372 | G15: =D10 -> 43737 | H15: =EOMONTH(G15,12) -> 44104 | I15: =EOMONTH(H15,12) -> 44469 | J15: =EOMONTH(I15,12) -> 44834 | K15: =EOMONTH(J15,12) -> 45199 | L15: =EOMONTH(K15,12) -> 45565
C17: Revenue | D17: 215639 | E17: 229234 | F17: 265595 | G17: 260174 | H17: =G17*(1+H36) -> 275784.44 | I17: =H17*(1+I36) -> 294813.57 | J17: =I17*(1+J36) -> 315155.7 | K17: =J17*(1+K36) -> 336901.45 | L17: =K17*(1+L36) -> 360147.65 | N17: Previous year's revenues x (1+revenue growth rate)
C18: Cost of sales (enter as -) | D18: -131376 | E18: -141048 | F18: -163756 | G18: -161782 | H18: =H19-H17 -> -171537.92 | I18: =I19-I17 -> -183374.04 | J18: =J19-J17 -> -196026.85 | K18: =K19-K17 -> -209552.7 | L18: =L19-L17 -> -224011.84 | N18: Plug = Revenue - Gross Profit
C19: Gross Profit | D19: =SUM(D17:D18) -> 84263 | E19: =SUM(E17:E18) -> 88186 | F19: =SUM(F17:F18) -> 101839 | G19: =SUM(G17:G18) -> 98392 | H19: =H17*H37 -> 104246.52 | I19: =I17*I37 -> 111439.53 | J19: =J17*J37 -> 119128.86 | K19: =K17*K37 -> 127348.75 | L19: =L17*L37 -> 136135.81 | N19: Revenue x Gross Profit Margin forecast
C20: Research & development (enter as -) | D20: -10045 | E20: -11581 | F20: -14236 | G20: -16217 | H20: =-H38*H17 -> -17098.635 | I20: =-I38*I17 -> -18278.441 | J20: =-J38*J17 -> -19539.654 | K20: =-K38*K17 -> -20887.89 | L20: =-L38*L17 -> -22329.154 | N20: Revenue x R&D % of sales forecast
C21: Selling, general & administrative (enter as -) | D21: -14194 | E21: -15261 | F21: -16705 | G21: -18245 | H21: =-H17*H39 -> -19304.911 | I21: =-I17*I39 -> -20636.95 | J21: =-J17*J39 -> -22060.899 | K21: =-K17*K39 -> -23583.101 | L21: =-L17*L39 -> -25210.335 | N21: Revenue x SG&A % of sales forecast
C22: Operating profit (EBIT) | D22: =D19+D20+D21 -> 60024 | E22: =E19+E20+E21 -> 61344 | F22: =F19+F20+F21 -> 70898 | G22: =G19+G20+G21 -> 63930 | H22: =H19+H20+H21 -> 67842.972 | I22: =I19+I20+I21 -> 72524.137 | J22: =J19+J20+J21 -> 77528.303 | K22: =K19+K20+K21 -> 82877.756 | L22: =L19+L20+L21 -> 88596.321 | N22: Gross Profit - R&D - SG&A
C23: Interest income | D23: 3999 | E23: 5201 | F23: 5686 | G23: 4961 | H23: =H156 -> 4386.8466 | I23: =I156 -> 4119.4834 | J23: =J156 -> 3871.0562 | K23: =K156 -> 3709.7511 | L23: =L156 -> 3643.4637 | N23: Reference from interest on cash schedule
C24: Interest expense (enter as -) | D24: -1456 | E24: -2323 | F24: -3240 | G24: -3576 | H24: =-H142 -> -3568.9466 | I24: =-I142 -> -3636.3706 | J24: =-J142 -> -3636.3706 | K24: =-K142 -> -3636.3706 | L24: =-L142 -> -3636.3706 | N24: Reference from interest expense schedule
C25: Other expense, net (enter as -) | D25: -1195 | E25: -133 | F25: -441 | G25: 422 | H25: =G25 -> 422 | I25: =H25 -> 422 | J25: =I25 -> 422 | K25: =J25 -> 422 | L25: =K25 -> 422 | N25: Straight-line
C26: Pretax profit | D26: =SUM(D22:D25) -> 61372 | E26: =SUM(E22:E25) -> 64089 | F26: =SUM(F22:F25) -> 72903 | G26: =SUM(G22:G25) -> 65737 | H26: =SUM(H22:H25) -> 69082.872 | I26: =SUM(I22:I25) -> 73429.25 | J26: =SUM(J22:J25) -> 78184.988 | K26: =SUM(K22:K25) -> 83373.136 | L26: =SUM(L22:L25) -> 89025.414 | N26: EBIT + interest income less interest expense less other expense
C27: Taxes (enter expense as -) | D27: -15685 | E27: -15738 | F27: -13372 | G27: -10481 | H27: =-H40*H26 -> -11014.46 | I27: =-I40*I26 -> -11707.44 | J27: =-J40*J26 -> -12465.687 | K27: =-K40*K26 -> -13292.877 | L27: =-L40*L26 -> -14194.067 | N27: Pre-tax Profit x Tax Rate forecast
C28: Net income | D28: =SUM(D26:D27) -> 45687 | E28: =SUM(E26:E27) -> 48351 | F28: =SUM(F26:F27) -> 59531 | G28: =SUM(G26:G27) -> 55256 | H28: =SUM(H26:H27) -> 58068.412 | I28: =SUM(I26:I27) -> 61721.81 | J28: =SUM(J26:J27) -> 65719.301 | K28: =SUM(K26:K27) -> 70080.259 | L28: =SUM(L26:L27) -> 74831.347 | N28: Pre-tax Profit less taxes
C30: Depreciation & amortization | D30: 10505 | E30: 10157 | F30: 10903 | G30: 12547 | H30: =H106 -> 11808.331 | I30: =I106 -> 12418.253 | J30: =J106 -> 13558.159 | K30: =K106 -> 14796.249 | L30: =L106 -> 16140.644 | N30: Reference from D&A schedule
C31: EBITDA | D31: =D22+D30 -> 70529 | E31: =E22+E30 -> 71501 | F31: =F22+F30 -> 81801 | G31: =G22+G30 -> 76477 | H31: =H22+H30 -> 79651.303 | I31: =I22+I30 -> 84942.391 | J31: =J22+J30 -> 91086.462 | K31: =K22+K30 -> 97674.004 | L31: =L22+L30 -> 104736.97 | N31: EBIT + D&A
C32: Stock based compensation | D32: 4210 | E32: 4840 | F32: 5340 | G32: 6068 | H32: =G32*(1+H36) -> 6432.08 | I32: =H32*(1+I36) -> 6875.8935 | J32: =I32*(1+J36) -> 7350.3302 | K32: =J32*(1+K36) -> 7857.503 | L32: =K32*(1+L36) -> 8399.6707 | N32: WSP assumption: grow SBC in-line with revenue growth
C33: Adjusted EBITDA | D33: =SUM(D31:D32) -> 74739 | E33: =SUM(E31:E32) -> 76341 | F33: =SUM(F31:F32) -> 87141 | G33: =SUM(G31:G32) -> 82545 | H33: =SUM(H31:H32) -> 86083.383 | I33: =SUM(I31:I32) -> 91818.284 | J33: =SUM(J31:J32) -> 98436.792 | K33: =SUM(K31:K32) -> 105531.51 | L33: =SUM(L31:L32) -> 113136.64 | N33: EBITDA + Stock-based compensation
C35: Growth rates & margins
C36: Revenue growth | E36: =E17/D17-1 -> 0.063045182 | F36: =F17/E17-1 -> 0.15861958 | G36: =G17/F17-1 -> -0.020410776 | H36: =H183 -> 0.06 | I36: =I183 -> 0.069 | J36: =J183 -> 0.069 | K36: =K183 -> 0.069 | L36: =L183 -> 0.069 | N36: Consensus estimates through 2021; straight-line growth rate thereafter
C37: Gross profit margin | D37: =D19/D17 -> 0.39075956 | E37: =E19/E17 -> 0.3846986 | F37: =F19/F17 -> 0.38343719 | G37: =G19/G17 -> 0.37817768 | H37: =H184 -> 0.378 | I37: =I184 -> 0.378 | J37: =J184 -> 0.378 | K37: =K184 -> 0.378 | L37: =L184 -> 0.378 | N37: Straight line last historical year
C38: R&D % of sales | D38: =-D20/D17 -> 0.046582483 | E38: =-E20/E17 -> 0.050520429 | F38: =-F20/F17 -> 0.053600407 | G38: =-G20/G17 -> 0.062331363 | H38: =H185 -> 0.062 | I38: =I185 -> 0.062 | J38: =J185 -> 0.062 | K38: =K185 -> 0.062 | L38: =L185 -> 0.062 | N38: Straight line last historical year
C39: SG&A % of sales | D39: =-D21/D17 -> 0.065822973 | E39: =-E21/E17 -> 0.066573894 | F39: =-F21/F17 -> 0.062896515 | G39: =-G21/G17 -> 0.070126146 | H39: =H186 -> 0.07 | I39: =I186 -> 0.07 | J39: =J186 -> 0.07 | K39: =K186 -> 0.07 | L39: =L186 -> 0.07 | N39: Straight line last historical year
C40: Tax rate | D40: =-(D27/D26) -> 0.25557257 | E40: =-(E27/E26) -> 0.24556476 | F40: =-(F27/F26) -> 0.18342181 | G40: =-(G27/G26) -> 0.15943837 | H40: =G40 -> 0.15943837 | I40: =H40 -> 0.15943837 | J40: =I40 -> 0.15943837 | K40: =J40 -> 0.15943837 | L40: =K40 -> 0.15943837 | N40: Straight line last historical year
C42: BALANCE SHEET
C43: =C14 -> Fiscal year | E43: =E14 -> 2017 | F43: =F14 -> 2018 | G43: =G14 -> 2019 | H43: =H14 -> 2020 | I43: =I14 -> 2021 | J43: =J14 -> 2022 | K43: =K14 -> 2023 | L43: =L14 -> 2024
C44: =C15 -> Fiscal year end date | E44: =E15 -> 43008 | F44: =F15 -> 43372 | G44: =G15 -> 43737 | H44: =H15 -> 44104 | I44: =I15 -> 44469 | J44: =J15 -> 44834 | K44: =K15 -> 45199 | L44: =L15 -> 45565
C45: Cash & equivalents, ST and LT marketable securities | E45: =20289+53892+194714 -> 268895 | F45: =25913+40388+170799 -> 237100 | G45: =48844+51713+105341 -> 205898 | H45: =H90+G45 -> 194727.26 | I45: =I90+H45 -> 181481.27 | J45: =J90+I45 -> 172039.84 | K45: =K90+J45 -> 166750.22 | L45: =L90+K45 -> 165986.19 | N45: Reference from 'net change in cash' line on the cash flow statement
C46: Accounts receivable | E46: 17874 | F46: 23186 | G46: 22926 | H46: =G46*(1+H36) -> 24301.56 | I46: =H46*(1+I36) -> 25978.368 | J46: =I46*(1+J36) -> 27770.875 | K46: =J46*(1+K36) -> 29687.065 | L46: =K46*(1+L36) -> 31735.473 | N46: Grow in-line with revenue growth
C47: Inventories | E47: 4855 | F47: 3956 | G47: 4106 | H47: =G47*H18/G18 -> 4353.6037 | I47: =H47*I18/H18 -> 4654.0023 | J47: =I47*J18/I18 -> 4975.1285 | K47: =J47*K18/J18 -> 5318.4123 | L47: =K47*L18/K18 -> 5685.3828 | N47: Grow in-line with cost of sales growth
C48: Other current assets | E48: =17799+13936 -> 31735 | F48: =25809+12087 -> 37896 | G48: =12352+22878 -> 35230 | H48: =G48*(1+H36) -> 37343.8 | I48: =H48*(1+I36) -> 39920.522 | J48: =I48*(1+J36) -> 42675.038 | K48: =J48*(1+K36) -> 45619.616 | L48: =K48*(1+L36) -> 48767.369 | N48: Grow in-line with revenue growth
C49: Property, plant & equipment | E49: 33783 | F49: 41304 | G49: 37378 | H49: =H99 -> 39817.319 | I49: =I99 -> 42050.931 | J49: =J99 -> 44155.616 | K49: =K99 -> 46102.948 | L49: =L99 -> 47861.192 | N49: Reference from PP&E schedule
C50: Other non current assets | E50: 18177 | F50: 22283 | G50: 32978 | H50: =G50*(1+H36) -> 34956.68 | I50: =H50*(1+I36) -> 37368.691 | J50: =I50*(1+J36) -> 39947.131 | K50: =J50*(1+K36) -> 42703.483 | L50: =K50*(1+L36) -> 45650.023 | N50: Grow in-line with revenue growth
C51: Total assets | E51: =SUM(E45:E50) -> 375319 | F51: =SUM(F45:F50) -> 365725 | G51: =SUM(G45:G50) -> 338516 | H51: =SUM(H45:H50) -> 335500.22 | I51: =SUM(I45:I50) -> 331453.79 | J51: =SUM(J45:J50) -> 331563.63 | K51: =SUM(K45:K50) -> 336181.75 | L51: =SUM(L45:L50) -> 345685.63
C53: Accounts payable | E53: 44242 | F53: 55888 | G53: 46236 | H53: =G53*H18/G18 -> 49024.164 | I53: =H53*I18/H18 -> 52406.832 | J53: =I53*J18/I18 -> 56022.903 | K53: =J53*K18/J18 -> 59888.483 | L53: =K53*L18/K18 -> 64020.789 | N53: Grow in-line with cost of sales growth
C54: Other current liabilities | E54: 30551 | F54: 33327 | G54: 37720 | H54: =G54*(1+H36) -> 39983.2 | I54: =H54*(1+I36) -> 42742.041 | J54: =I54*(1+J36) -> 45691.242 | K54: =J54*(1+K36) -> 48843.937 | L54: =K54*(1+L36) -> 52214.169 | N54: Grow in-line with revenue growth
C55: Deferred revenue (current) | E55: =7548+2836 -> 10384 | F55: 5966 | G55: 5522 | H55: =G55*(1+H36) -> 5853.32 | I55: =H55*(1+I36) -> 6257.1991 | J55: =I55*(1+J36) -> 6688.9458 | K55: =J55*(1+K36) -> 7150.4831 | L55: =K55*(1+L36) -> 7643.8664 | N55: Grow in-line with revenue growth
C56: Commercial paper / revolver | E56: 11977 | F56: 11964 | G56: 5980 | H56: =H135 -> 12000 | I56: =I135 -> 12000 | J56: =J135 -> 12000 | K56: =K135 -> 12000 | L56: =L135 -> 12000 | N56: Reference EOP balance from CP/revolver schedule
C57: Long term debt (includes current portion) | E57: =6496+97207 -> 103703 | F57: =8784+93735 -> 102519 | G57: =10260+91807 -> 102067 | H57: =G57 -> 102067 | I57: =H57 -> 102067 | J57: =I57 -> 102067 | K57: =J57 -> 102067 | L57: =K57 -> 102067 | N57: WSP assumption: straight-line
C58: Other non current liabilities | E58: 40415 | F58: 48914 | G58: 50503 | H58: =G58*(1+H36) -> 53533.18 | I58: =H58*(1+I36) -> 57226.969 | J58: =I58*(1+J36) -> 61175.63 | K58: =J58*(1+K36) -> 65396.749 | L58: =K58*(1+L36) -> 69909.124 | N58: Grow in-line with revenue growth
C59: Total liabilities | E59: =SUM(E53:E58) -> 241272 | F59: =SUM(F53:F58) -> 258578 | G59: =SUM(G53:G58) -> 248028 | H59: =SUM(H53:H58) -> 262460.86 | I59: =SUM(I53:I58) -> 272700.04 | J59: =SUM(J53:J58) -> 283645.72 | K59: =SUM(K53:K58) -> 295346.65 | L59: =SUM(L53:L58) -> 307854.95
C61: Common stock | E61: 35867 | F61: 40201 | G61: 45174 | H61: =G61+H32 -> 51606.08 | I61: =H61+I32 -> 58481.974 | J61: =I61+J32 -> 65832.304 | K61: =J61+K32 -> 73689.807 | L61: =K61+L32 -> 82089.477 | N61: Increase by stock-based compensation forecasted in the I/S section
C62: Retained earnings | E62: =98330 -> 98330 | F62: 70400 | G62: 45898 | H62: =H119 -> 22017.276 | I62: =I119 -> 855.77387 | J62: =J119 -> -17330.399 | K62: =K119 -> -32270.713 | L62: =L119 -> -43674.797 | N62: Reference from Retained Earnings schedule
C63: Other comprehensive income | E63: -150 | F63: -3454 | G63: -584 | H63: =G63 -> -584 | I63: =H63 -> -584 | J63: =I63 -> -584 | K63: =J63 -> -584 | L63: =K63 -> -584 | N63: WSP assumption: straight-line
C64: Total equity | E64: =SUM(E61:E63) -> 134047 | F64: =SUM(F61:F63) -> 107147 | G64: =SUM(G61:G63) -> 90488 | H64: =SUM(H61:H63) -> 73039.356 | I64: =SUM(I61:I63) -> 58753.747 | J64: =SUM(J61:J63) -> 47917.905 | K64: =SUM(K61:K63) -> 40835.093 | L64: =SUM(L61:L63) -> 37830.681
C66: Balance check | E66: =ROUND(E51-E59-E64,3) -> 0 | F66: =ROUND(F51-F59-F64,3) -> 0 | G66: =ROUND(G51-G59-G64,3) -> 0 | H66: =ROUND(H51-H59-H64,3) -> 0 | I66: =ROUND(I51-I59-I64,3) -> 0 | J66: =ROUND(J51-J59-J64,3) -> 0 | K66: =ROUND(K51-K59-K64,3) -> 0 | L66: =ROUND(L51-L59-L64,3) -> 0
C68: CASH FLOW STATEMENT
C69: =C14 -> Fiscal year | H69: =H14 -> 2020 | I69: =I14 -> 2021 | J69: =J14 -> 2022 | K69: =K14 -> 2023 | L69: =L14 -> 2024
C70: =C15 -> Fiscal year end date | H70: =H15 -> 44104 | I70: =I15 -> 44469 | J70: =J15 -> 44834 | K70: =K15 -> 45199 | L70: =L15 -> 45565
C72: Net income | H72: =H28 -> 58068.412 | I72: =I28 -> 61721.81 | J72: =J28 -> 65719.301 | K72: =K28 -> 70080.259 | L72: =L28 -> 74831.347
C73: Depreciation and amortization | H73: =H30 -> 11808.331 | I73: =I30 -> 12418.253 | J73: =J30 -> 13558.159 | K73: =K30 -> 14796.249 | L73: =L30 -> 16140.644 | N73: Reference from the I/S
C74: Stock based compensation | H74: =H32 -> 6432.08 | I74: =I32 -> 6875.8935 | J74: =J32 -> 7350.3302 | K74: =K32 -> 7857.503 | L74: =L32 -> 8399.6707
C75: Decreases / (Increases) in working capital assets | H75: =SUM(G46:G48)-SUM(H46:H48) -> -3736.9637 | I75: =SUM(H46:H48)-SUM(I46:I48) -> -4553.9285 | J75: =SUM(I46:I48)-SUM(J46:J48) -> -4868.1496 | K75: =SUM(J46:J48)-SUM(K46:K48) -> -5204.0519 | L75: =SUM(K46:K48)-SUM(L46:L48) -> -5563.1315
C76: Increases / (Decreases) in working capital liabilities | H76: =SUM(H53:H55)-SUM(G53:G55) -> 5382.6843 | I76: =SUM(I53:I55)-SUM(H53:H55) -> 6545.3872 | J76: =SUM(J53:J55)-SUM(I53:I55) -> 6997.0189 | K76: =SUM(K53:K55)-SUM(J53:J55) -> 7479.8132 | L76: =SUM(L53:L55)-SUM(K53:K55) -> 7995.9204
C77: Other non current assets | H77: =-H111 -> -3300.5 | I77: =-I111 -> -3825.0365 | J77: =-J111 -> -4088.964 | K77: =-K111 -> -4371.1025 | L77: =-L111 -> -4672.7086 | N77: Reference from schedule NOT the B/S: Only include 'Additions' (as outflow)
C78: Other non current liabilities | H78: =H58-G58 -> 3030.18 | I78: =I58-H58 -> 3693.7894 | J78: =J58-I58 -> 3948.6609 | K78: =K58-J58 -> 4221.1185 | L78: =L58-K58 -> 4512.3757
C79: Cash from operating activities | H79: =SUM(H72:H78) -> 77684.223 | I79: =SUM(I72:I78) -> 82876.169 | J79: =SUM(J72:J78) -> 88616.357 | K79: =SUM(K72:K78) -> 94859.788 | L79: =SUM(L72:L78) -> 101644.12
C81: Capital expenditures | H81: =-(H97) -> -12925.83 | I81: =-(I97) -> -13238.84 | J81: =-(J97) -> -14152.32 | K81: =-(K97) -> -15128.83 | L81: =-(L97) -> -16172.719 | N81: Reference from PP&E schedule
C82: Cash from investing activities | H82: =IFERROR(H81,"NA") -> -12925.83 | I82: =IFERROR(I81,"NA") -> -13238.84 | J82: =IFERROR(J81,"NA") -> -14152.32 | K82: =IFERROR(K81,"NA") -> -15128.83 | L82: =IFERROR(L81,"NA") -> -16172.719
C84: Long term debt | H84: =H57-G57 -> 0 | I84: =I57-H57 -> 0 | J84: =J57-I57 -> 0 | K84: =K57-J57 -> 0 | L84: =L57-K57 -> 0
C85: Commercial paper/ Revolver | H85: =H56-G56 -> 6020 | I85: =I56-H56 -> 0 | J85: =J56-I56 -> 0 | K85: =K56-J56 -> 0 | L85: =L56-K56 -> 0 | N85: Reference from B/S
C86: Share repurchases | H86: =H118 -> -67101 | I86: =I118 -> -67101 | J86: =J118 -> -67101 | K86: =K118 -> -67101 | L86: =L118 -> -67101 | N86: Reference from Retained Earnings schedule
C87: Common dividends | H87: =H117 -> -14848.136 | I87: =I117 -> -15782.312 | J87: =J117 -> -16804.474 | K87: =K117 -> -17919.574 | L87: =L117 -> -19134.431 | N87: Reference from Retained Earnings schedule
C88: Cash from financing activities | H88: =SUM(H84:H87) -> -75929.136 | I88: =SUM(I84:I87) -> -82883.312 | J88: =SUM(J84:J87) -> -83905.474 | K88: =SUM(K84:K87) -> -85020.574 | L88: =SUM(L84:L87) -> -86235.431
C90: Net change in cash during period | H90: =H79+H82+H88 -> -11170.742 | I90: =I79+I82+I88 -> -13245.984 | J90: =J79+J82+J88 -> -9441.4369 | K90: =K79+K82+K88 -> -5289.6157 | L90: =L79+L82+L88 -> -764.03196
C92: PROPERTY, PLANT & EQUIPMENT
C93: =C14 -> Fiscal year | E93: =E14 -> 2017 | F93: =F14 -> 2018 | G93: =G14 -> 2019 | H93: =H14 -> 2020 | I93: =I14 -> 2021 | J93: =J14 -> 2022 | K93: =K14 -> 2023 | L93: =L14 -> 2024
C94: =C15 -> Fiscal year end date | E94: =E15 -> 43008 | F94: =F15 -> 43372 | G94: =G15 -> 43737 | H94: =H15 -> 44104 | I94: =I15 -> 44469 | J94: =J15 -> 44834 | K94: =K15 -> 45199 | L94: =L15 -> 45565
H95: Forecast
C96: Beginning of period | H96: =G99 -> 37378 | I96: =H99 -> 39817.319 | J96: =I99 -> 42050.931 | K96: =J99 -> 44155.616 | L96: =K99 -> 46102.948 | N96: BOP = Previous year EOP
C97: Plus: Capital expenditures | D97: 12734 | E97: 12451 | F97: 13313 | G97: 10495 | H97: 12925.83 | I97: 13238.84 | J97: =I97*(1+J36) -> 14152.32 | K97: =J97*(1+K36) -> 15128.83 | L97: =K97*(1+L36) -> 16172.719 | N97: First two years - consensus estimates, then grow with revenue
C98: Less: Depreciation | D98: -8300 | E98: -8200 | F98: -9300 | G98: -11300 | H98: =-(H101*H97) -> -10486.511 | I98: =-(I101*I97) -> -11005.228 | J98: =-(J101*J97) -> -12047.635 | K98: =-(K101*K97) -> -13181.498 | L98: =-(L101*L97) -> -14414.476 | N98: Capex x 'D&A related to PP&E as a % of capex' ratio (below)
C99: End of period | D99: =D49 -> 0 | E99: =E49 -> 33783 | F99: =F49 -> 41304 | G99: =G49 -> 37378 | H99: =SUM(H96:H98) -> 39817.319 | I99: =SUM(I96:I98) -> 42050.931 | J99: =SUM(J96:J98) -> 44155.616 | K99: =SUM(K96:K98) -> 46102.948 | L99: =SUM(L96:L98) -> 47861.192 | N99: BOP + Capex - Depreciation
N100: Step
C101: D&A related to PP&E as a % of capex | E101: =-(E98/E97) -> 0.65858164 | F101: =-(F98/F97) -> 0.69856531 | G101: =-(G98/G97) -> 1.0767032 | H101: =AVERAGE(E101:G101) -> 0.81128338 | I101: =H101+$N$101 -> 0.83128338 | J101: =I101+$N$101 -> 0.85128338 | K101: =J101+$N$101 -> 0.87128338 | L101: =K101+$N$101 -> 0.89128338 | N101: 0.02
C103: IMPUTING TOTAL DEPRECIATION & AMORTIZATION
C104: D&A not related to PP&E | D104: =D106+D98 -> 2205 | E104: =E106+E98 -> 1957 | F104: =F106+F98 -> 1603 | G104: =G106+G98 -> 1247 | H104: =H105*H17 -> 1321.82 | I104: =I105*I17 -> 1413.0256 | J104: =J105*J17 -> 1510.5243 | K104: =K105*K17 -> 1614.7505 | L104: =L105*L17 -> 1726.1683 | N104: Revenue x 'as % of revenue' assumption
C105: as % of revenue | D105: =D104/D17 -> 0.010225423 | E105: =E104/E17 -> 0.008537128 | F105: =F104/F17 -> 0.0060355052 | G105: =G104/G17 -> 0.0047929463 | H105: =G105 -> 0.0047929463 | I105: =H105 -> 0.0047929463 | J105: =I105 -> 0.0047929463 | K105: =J105 -> 0.0047929463 | L105: =K105 -> 0.0047929463 | N105: Straight line last historical % of revenue - WSP assumption
C106: Depreciation & Amortization - Total | D106: =D30 -> 10505 | E106: =E30 -> 10157 | F106: =F30 -> 10903 | G106: =G30 -> 12547 | H106: =-H98+H104 -> 11808.331 | I106: =-I98+I104 -> 12418.253 | J106: =-J98+J104 -> 13558.159 | K106: =-K98+K104 -> 14796.249 | L106: =-L98+L104 -> 16140.644 | N106: D&A from PP&E + D&A not from PP&E
C108: OTHER NON-CURRENT ASSETS
C109: Beginning of period | H109: =G112 -> 32978 | I109: =H112 -> 34956.68 | J109: =I112 -> 37368.691 | K109: =J112 -> 39947.131 | L109: =K112 -> 42703.483 | N109: BOP = Previous year EOP
C110: Less: Amortization of intangible assets | H110: =-(H104) -> -1321.82 | I110: =-(I104) -> -1413.0256 | J110: =-(J104) -> -1510.5243 | K110: =-(K104) -> -1614.7505 | L110: =-(L104) -> -1726.1683 | N110: Assume all D&A not from PP&E is in non-current assets
C111: Plus: Additions | H111: =H112-H110-H109 -> 3300.5 | I111: =I112-I110-I109 -> 3825.0365 | J111: =J112-J110-J109 -> 4088.964 | K111: =K112-K110-K109 -> 4371.1025 | L111: =L112-L110-L109 -> 4672.7086 | N111: Because we already know the EOP balance, this is a plug: EOP - D&A not from PP&E - BOP
C112: End of period | E112: =E50 -> 18177 | F112: =F50 -> 22283 | G112: =G50 -> 32978 | H112: =H50 -> 34956.68 | I112: =I50 -> 37368.691 | J112: =J50 -> 39947.131 | K112: =K50 -> 42703.483 | L112: =L50 -> 45650.023 | N112: Referenced from balance sheet
C114: RETAINED EARNINGS
C115: Beginning of period | H115: =G119 -> 45898 | I115: =H119 -> 22017.276 | J115: =I119 -> 855.77387 | K115: =J119 -> -17330.399 | L115: =K119 -> -32270.713 | N115: BOP = Previous year EOP
C116: Plus: Net income | D116: =D28 -> 45687 | E116: =E28 -> 48351 | F116: =F28 -> 59531 | G116: =G28 -> 55256 | H116: =H28 -> 58068.412 | I116: =I28 -> 61721.81 | J116: =J28 -> 65719.301 | K116: =K28 -> 70080.259 | L116: =L28 -> 74831.347 | N116: Reference from income statement
C117: Less: Dividends | D117: -12188 | E117: -12803 | F117: -13735 | G117: -14129 | H117: =H116*G117/G116 -> -14848.136 | I117: =I116*H117/H116 -> -15782.312 | J117: =J116*I117/I116 -> -16804.474 | K117: =K116*J117/J116 -> -17919.574 | L117: =L116*K117/K116 -> -19134.431 | N117: WSP assumption: Hold last historical year's dividend payout ratio constant
C118: Less: Repurchases | D118: -29000 | E118: -33001 | F118: -73056 | G118: -67101 | H118: =G118 -> -67101 | I118: =H118 -> -67101 | J118: =I118 -> -67101 | K118: =J118 -> -67101 | L118: =K118 -> -67101 | N118: WSP assumption: Straight-line last historical year repurchases
C119: End of period | D119: =D62 -> 0 | E119: =E62 -> 98330 | F119: =F62 -> 70400 | G119: =G62 -> 45898 | H119: =SUM(H115:H118) -> 22017.276 | I119: =SUM(I115:I118) -> 855.77387 | J119: =SUM(J115:J118) -> -17330.399 | K119: =SUM(K115:K118) -> -32270.713 | L119: =SUM(L115:L118) -> -43674.797 | N119: BOP + net income - dividends - repurchases
...
