Workbook
Name beta_observed: #REF!
Name beta_unlev_comps: #REF!
Name conversionfactor: '[10]E&P'!$D$6
Name convfactor: #REF!
Name costdebtfirm: #REF!
Name costequity: #REF!
Name days_per_year: #REF!
Name debt: #REF!
Name debt_weight: #REF!
Name market_equity: #REF!
Name relevered_beta: #REF!
Name risk_free_rate: #REF!
Name risk_premium: #REF!
Name stubyear: #REF!
Name totalcap: #REF!
Name wacc: #REF!

Sheet Transaction Summary
B2: Transaction Summary | D2: Brooks Phillips
B4: Sources & Uses
D5: CLOSE | H5: HOLD
D6: Total | E6: % of Total | F6: Per Unit | H6: Total | I6: % of Total | J6: Per Unit
B7: Uses
B8: Purchase Price | D8: =Model!E95 -> 51000000 | E8: =D8/$D$12 -> 0.98425197 | F8: =D8/$J$23 -> 204000 | H8: =Model!F95 -> 51000000 | I8: =H8/$H$12 -> 0.95054377 | J8: =H8/$J$23 -> 204000
B9: Closing Costs | D9: =Model!E96 -> 637500 | E9: =D9/$D$12 -> 0.01230315 | F9: =D9/$J$23 -> 2550 | H9: =Model!F96 -> 637500 | I9: =H9/$H$12 -> 0.011881797 | J9: =H9/$J$23 -> 2550
B10: Capital Expenditures | D10: =Model!E97 -> 0 | E10: =D10/$D$12 -> 0 | F10: =D10/$J$23 -> 0 | H10: =Model!F97 -> 1837500 | I10: =H10/$H$12 -> 0.034247533 | J10: =H10/$J$23 -> 7350
B11: Financing Fees | D11: =Model!E98 -> 178500 | E11: =D11/$D$12 -> 0.0034448819 | F11: =D11/$J$23 -> 714 | H11: =Model!F98 -> 178500 | I11: =H11/$H$12 -> 0.0033269032 | J11: =H11/$J$23 -> 714
B12: Total Uses | D12: =SUM(D8:D11) -> 51816000 | E12: =SUM(E8:E11) -> 1 | F12: =SUM(F8:F11) -> 207264 | H12: =SUM(H8:H11) -> 53653500 | I12: =SUM(I8:I11) -> 1 | J12: =SUM(J8:J11) -> 214614
B14: Sources
B15: Equity | D15: =Model!E102 -> 16116000 | E15: =D15/$D$18 -> 0.31102362 | F15: =D15/$J$23 -> 64464 | H15: =Model!F102 -> 16204471 | I15: =H15/$H$18 -> 0.30202076 | J15: =H15/$J$23 -> 64817.884
B16: Debt | D16: =Model!E103 -> 35700000 | E16: =D16/$D$18 -> 0.68897638 | F16: =D16/$J$23 -> 142800 | H16: =Model!F103 -> 35700000 | I16: =H16/$H$18 -> 0.66538064 | J16: =H16/$J$23 -> 142800
B17: Operating Cashflow | D17: =Model!E104 -> 0 | E17: =D17/$D$18 -> 0 | F17: =D17/$J$23 -> 0 | H17: =Model!F104 -> 1749029 | I17: =H17/$H$18 -> 0.0325986 | J17: =H17/$J$23 -> 6996.116
B18: Total Sources | D18: =SUM(D15:D17) -> 51816000 | E18: =SUM(E15:E17) -> 1 | F18: =SUM(F15:F17) -> 207264 | H18: =SUM(H15:H17) -> 53653500 | I18: =SUM(I15:I17) -> 1 | J18: =SUM(J15:J17) -> 214614
B20: Returns Summary | H20: Property Overview
C21: Peak Equity | D21: IRR | E21: Profit | F21: Multiple | H21: Location | J21: ='Inputs & Drivers'!E7 -> 123 Wall Street, Boston, MA
B22: Unlevered Project | C22: {=TRANSPOSE(Model!C65:C68)} -> 51637500 | D22: 0.091856948 | E22: 25486681 | F22: 1.4935692 | H22: Vintage | J22: ='Inputs & Drivers'!E9 -> 2010
B23: Levered Project | C23: {=TRANSPOSE(Model!C88:C91)} -> 16204471 | D23: 0.1709843 | E23: 17412446 | F23: 2.0745458 | H23: Total Units | J23: ='Inputs & Drivers'!E8 -> 250
H24: Hold Period | J24: ='Inputs & Drivers'!E13 -> 60
H25: Rentable SF | J25: ='Inputs & Drivers'!I10*'Inputs & Drivers'!J10 -> 230000
H26: Avg Unit Size | J26: =J25/J23 -> 920
H27: Current Occ. | J27: ='Inputs & Drivers'!E35 -> 0.9
B29: NOI Summary | H29: Unit Mix
C30: NOI | D30: Growth | E30: NOI YoC | F30: Delta to Exit Cap | H30: Type | I30: Count | J30: %
B31: 1 | C31: {=TRANSPOSE(Model!EN44:ES44)} -> 2738296.4 | E31: =C31/$H$18 -> 0.051036679 | F31: =E31-$D$48 -> -0.0064633214 | H31: ='Inputs & Drivers'!G6 -> Studio | I31: ='Inputs & Drivers'!J6 -> 20 | J31: =I31/$I$35 -> 0.08
B32: =++B31+1 -> 2 | C32: 2989929.7 | D32: =C32/C31-1 -> 0.091894097 | E32: =C32/$H$18 -> 0.055726648 | F32: =E32-$D$48 -> -0.0017733519 | H32: ='Inputs & Drivers'!G7 -> 1 BR, 1 BA | I32: ='Inputs & Drivers'!J7 -> 140 | J32: =I32/$I$35 -> 0.56
B33: =++B32+1 -> 3 | C33: 3294209 | D33: =C33/C32-1 -> 0.10176802 | E33: =C33/$H$18 -> 0.061397839 | F33: =E33-$D$48 -> 0.0038978389 | H33: ='Inputs & Drivers'!G8 -> 2 BR, 2 BA | I33: ='Inputs & Drivers'!J8 -> 80 | J33: =I33/$I$35 -> 0.32
B34: =++B33+1 -> 4 | C34: 3432779.7 | D34: =C34/C33-1 -> 0.042064956 | E34: =C34/$H$18 -> 0.063980536 | F34: =E34-$D$48 -> 0.0064805364 | H34: ='Inputs & Drivers'!G9 -> 3 BR, 2 BA | I34: ='Inputs & Drivers'!J9 -> 10 | J34: =I34/$I$35 -> 0.04
B35: =++B34+1 -> 5 | C35: 3547442.2 | D35: =C35/C34-1 -> 0.033402221 | E35: =C35/$H$18 -> 0.066117628 | F35: =E35-$D$48 -> 0.0086176284 | H35: Total | I35: =SUM(I31:I34) -> 250 | J35: =I35/$I$35 -> 1
B36: =++B35+1 -> 6 | C36: 3665968.5 | D36: =C36/C35-1 -> 0.033411763 | E36: =C36/$H$18 -> 0.068326735 | F36: =E36-$D$48 -> 0.010826735
B38: Capital Expenditure Summary | H38: Debt Summary
E39: Per Unit | F39: Total | H39: Loan Proceeds | J39: ='Inputs & Drivers'!J22 -> 35700000
B40: Deferred Maintenance | E40: =F40/$J$23 -> 1050 | F40: ='Inputs & Drivers'!E22 -> 262500 | H40: Leverage (Close / Life) | J40: =TEXT(D16/D18,"0%")&" / "&TEXT(H16/H18,"0%") -> 69% / 67%
B41: Offensive Renovations | E41: =F41/$J$23 -> 6300 | F41: ='Inputs & Drivers'!E27 -> 1575000 | H41: Rate | J41: ='Inputs & Drivers'!J25 -> 0.0466275
B42: Subtotal | E42: =F42/$J$23 -> 7350 | F42: =SUM(F40:F41) -> 1837500 | H42: Fees | J42: ='Inputs & Drivers'!J28 -> 0.005
B43: Replacement Reserves | E43: =F43/J23 -> 1250 | F43: =-SUMIF(Model!$I$6:$EK$6,"<="&Model!$C$5,Model!I41:EK41) -> 312500 | H43: IO Period | J43: ='Inputs & Drivers'!J26 -> 48
B44: Total | E44: =F44/$J$23 -> 8600 | F44: =SUM(F42:F43) -> 2150000 | H44: Maturity | J44: ='Inputs & Drivers'!J21 -> 45291
B46: Exit Summary | H46: Unit Renovation ROI
C47: Fwd NOI | D47: Exit Cap | E47: Total $ | F47: Per Unit | H47: Units Renovated | I47: =J47/J23 -> 1 | J47: ='Inputs & Drivers'!E72 -> 250
B48: Sale Proceeds | C48: =SUMIF(Model!$I$6:$EK$6,'Inputs & Drivers'!$J$13,Model!I45:EK45) -> 3665968.5 | D48: ='Inputs & Drivers'!J14 -> 0.0575 | E48: =C48/D48 -> 63755973 | F48: =E48/J23 -> 255023.89 | H48: Upgrade Cost / Unit | J48: ='Inputs & Drivers'!D25 -> 6000
B49: Less: Sale Costs | E49: =-'Inputs & Drivers'!J16*E48 -> -796949.67 | H49: Rent Premium | I49: ='Inputs & Drivers'!E74 -> 125 | J49: =I49*12 -> 1500
B50: Net Sale Proceeds | E50: =SUM(E48:E49) -> 62959024 | H50: ROI | J50: =J49/J48 -> 0.25
B51: Less: Outstanding Debt | D51: Value | E51: =SUMIF(Model!$I$6:$EK$6,'Inputs & Drivers'!$J$13,Model!I81:EK81) -> -35140251
B52: Less: Equity | D52: Allocation | E52: =-C23 -> -16204471
B53: Terminal Value Profit | D53: =E53/$E$55 -> 0.66701152 | E53: =SUM(E50:E52) -> 11614302
B54: Interim Cash Flow | D54: =E54/$E$55 -> 0.33298848 | E54: =E23-E53 -> 5798144.1
B55: Total Profit | D55: =SUM(D53:D54) -> 1 | E55: =SUM(E53:E54) -> 17412446
B57: Revenue & Expense Summary
D58: T-12 | E58: T-3
D59: =Model!F4 -> Dec 2018 | E59: =D59 -> Dec 2018 | F59: ="Year "&Model!EN5 -> Year 1 | G59: ="Year "&Model!EO5 -> Year 2 | H59: ="Year "&Model!EP5 -> Year 3 | I59: ="Year "&Model!EQ5 -> Year 4 | J59: ="Year "&Model!ER5 -> Year 5
B60: Effective Rent | D60: =Model!F20 -> 2053.8001 | E60: =Model!E20 -> 2025.3721 | F60: =Model!EN20 -> 2077.6717 | G60: =Model!EO20 -> 2173.4197 | H60: =Model!EP20 -> 2287.252 | I60: =Model!EQ20 -> 2363.609 | J60: =Model!ER20 -> 2431.6985
B61: Occupancy | D61: =Model!F22 -> 0.9 | E61: =Model!E22 -> 0.9 | F61: =Model!EN22 -> 0.91 | G61: =Model!EO22 -> 0.92 | H61: =Model!EP22 -> 0.93 | I61: =Model!EQ22 -> 0.93 | J61: =Model!ER22 -> 0.93
B62: Total Income | D62: =Model!F29 -> 5873969.1 | E62: =Model!E29 -> 5846500.8 | F62: =Model!EN29 -> 6000346.1 | G62: =Model!EO29 -> 6336221.3 | H62: =Model!EP29 -> 6728315.8 | I62: =Model!EQ29 -> 6951626.8 | J62: =Model!ER29 -> 7152359
B63: Total Expenses | D63: =Model!F42 -> -3053699.5 | E63: =Model!E42 -> -3195787.1 | F63: =Model!EN42 -> -3262049.7 | G63: =Model!EO42 -> -3346291.6 | H63: =Model!EP42 -> -3434106.9 | I63: =Model!EQ42 -> -3518847.1 | J63: =Model!ER42 -> -3604916.8
B64: NOI | D64: =SUM(D62:D63) -> 2820269.6 | E64: =SUM(E62:E63) -> 2650713.6 | F64: =SUM(F62:F63) -> 2738296.4 | G64: =SUM(G62:G63) -> 2989929.7 | H64: =SUM(H62:H63) -> 3294209 | I64: =SUM(I62:I63) -> 3432779.7 | J64: =SUM(J62:J63) -> 3547442.2
B66: Effective Rent Growth | E66: =E60/D60-1 -> -0.013841658 | F66: =F60/E60-1 -> 0.025822182 | G66: =G60/F60-1 -> 0.046084315 | H66: =H60/G60-1 -> 0.052374727 | I66: =I60/H60-1 -> 0.033383748 | J66: =J60/I60-1 -> 0.028807402
B67: Revenue Growth | E67: =E62/D62-1 -> -0.0046762827 | F67: =F62/E62-1 -> 0.026314093 | G67: =G62/F62-1 -> 0.055975971 | H67: =H62/G62-1 -> 0.061881441 | I67: =I62/H62-1 -> 0.033189721 | J67: =J62/I62-1 -> 0.028875576
B68: Expense Growth | E68: =E63/D63-1 -> 0.046529664 | F68: =F63/E63-1 -> 0.020734343 | G68: =G63/F63-1 -> 0.025824843 | H68: =H63/G63-1 -> 0.026242563 | I68: =I63/H63-1 -> 0.024676043 | J68: =J63/I63-1 -> 0.024459647
B69: Expense / Unit | D69: =-D63/$J$23 -> 12214.798 | E69: =-E63/$J$23 -> 12783.149 | F69: =-F63/$J$23 -> 13048.199 | G69: =-G63/$J$23 -> 13385.166 | H69: =-H63/$J$23 -> 13736.428 | I69: =-I63/$J$23 -> 14075.388 | J69: =-J63/$J$23 -> 14419.667
B70: NOI Growth | E70: =E64/D64-1 -> -0.060120477 | F70: =F64/E64-1 -> 0.033041222 | G70: =G64/F64-1 -> 0.091894097 | H70: =H64/G64-1 -> 0.10176802 | I70: =I64/H64-1 -> 0.042064956 | J70: =J64/I64-1 -> 0.033402221
B71: NOI Margin | D71: =D64/D62 -> 0.48013013 | E71: =E64/E62 -> 0.45338464 | F71: =F64/F62 -> 0.45635641 | G71: =G64/G62 -> 0.47187899 | H71: =H64/H62 -> 0.48960379 | I71: =I64/I62 -> 0.49380955 | J71: =J64/J62 -> 0.49598212
B72: NOI / PP | D72: =D64/$D$8 -> 0.055299403 | E72: =E64/$D$8 -> 0.051974777 | F72: =F64/$D$8 -> 0.053692087 | G72: =G64/$D$8 -> 0.058626073 | H72: =H64/$D$8 -> 0.064592332 | I72: =I64/$D$8 -> 0.067309406 | J72: =J64/$D$8 -> 0.06955769
B73: NOI / Cost | D73: =D64/$H$18 -> 0.052564503 | E73: =E64/$H$18 -> 0.0494043 | F73: =Model!EN47 -> 0.051925845 | G73: =Model!EO47 -> 0.055863304 | H73: =Model!EP47 -> 0.061397839 | I73: =Model!EQ47 -> 0.063980536 | J73: =Model!ER47 -> 0.066117628
B74: NOI DSCR | F74: =Model!EN83 -> 1.6589416 | G74: =Model!EO83 -> 1.9068499 | H74: =Model!EP83 -> 2.145656 | I74: =Model!EQ83 -> 2.2032701 | J74: =Model!ER83 -> 1.6549532
B75: Cash-on-Cash | F75: =(Model!EN86-SUM(Model!EN57:EN60)-Model!EN81)/$C$23 -> 0.010424148 | G75: =(Model!EO86-SUM(Model!EO57:EO60)-Model!EO81)/$C$23 -> 0.039151875 | H75: =(Model!EP86-SUM(Model!EP57:EP60)-Model!EP81)/$C$23 -> 0.10044553 | I75: =(Model!EQ86-SUM(Model!EQ57:EQ60)-Model!EQ81)/$C$23 -> 0.11569283 | J75: =(Model!ER86-SUM(Model!ER57:ER60)-Model!ER81)/$C$23 -> 0.086637321

Sheet Inputs & Drivers
B2: Inputs | D2: Brooks Phillips | M2: LIBOR Index | Q2: Amortization Table
B4: Property Overview | G4: Unit Mix | M4: Date | N4: LIBOR | Q4: Date | R4: # | S4: Payment | T4: Beg. Balance | U4: Principal | V4: Interest | W4: End Balance
B5: Name | E5: Rock Creek Apartments | G5: Type | I5: Size | J5: Count | M5: 43465 | N5: 0.0251275 | Q5: =J19 -> 43465 | R5: 0 | S5: =-PMT($J$25/12,$J$27*12,$J$22) -> 184355.25 | T5: =J22 -> 35700000 | U5: =(S5-V5)*(R5>$J$26) -> 0 | V5: 0 | W5: =T5-U5 -> 35700000
B6: Type | E6: Multifamily | G6: Studio | I6: 500 | J6: 20 | M6: 43503 | N6: 0.0250547 | Q6: =EOMONTH(Q5,1) -> 43496 | R6: =++R5+1 -> 1 | S6: =S5 -> 184355.25 | T6: =W5 -> 35700000 | U6: =(S6-V6)*(R6>$J$26) -> 0 | V6: =$J$25*T6*((Q6-Q5)/365) -> 141377.13 | W6: =T6-U6 -> 35700000
B7: Location | E7: 123 Wall Street, Boston, MA | G7: 1 BR, 1 BA | I7: 750 | J7: 140 | M7: 43531 | N7: 0.0249624 | Q7: =EOMONTH(Q6,1) -> 43524 | R7: =++R6+1 -> 2 | S7: =S6 -> 184355.25 | T7: =W6 -> 35700000 | U7: =(S7-V7)*(R7>$J$26) -> 0 | V7: =$J$25*T7*((Q7-Q6)/365) -> 127695.48 | W7: =T7-U7 -> 35700000
B8: Units | E8: 250 | G8: 2 BR, 2 BA | I8: 1250 | J8: 80 | M8: 43563 | N8: 0.0249459 | Q8: =EOMONTH(Q7,1) -> 43555 | R8: =++R7+1 -> 3 | S8: =S7 -> 184355.25 | T8: =W7 -> 35700000 | U8: =(S8-V8)*(R8>$J$26) -> 0 | V8: =$J$25*T8*((Q8-Q7)/365) -> 141377.13 | W8: =T8-U8 -> 35700000
B9: Year Built | E9: 2010 | G9: 3 BR, 2 BA | I9: 1500 | J9: 10 | M9: 43592 | N9: 0.024956 | Q9: =EOMONTH(Q8,1) -> 43585 | R9: =++R8+1 -> 4 | S9: =S8 -> 184355.25 | T9: =W8 -> 35700000 | U9: =(S9-V9)*(R9>$J$26) -> 0 | V9: =$J$25*T9*((Q9-Q8)/365) -> 136816.58 | W9: =T9-U9 -> 35700000
G10: Total | I10: =SUMPRODUCT(I6:I9,J6:J9)/J10 -> 920 | J10: =SUM(J6:J9) -> 250 | M10: 43623 | N10: 0.0249169 | Q10: =EOMONTH(Q9,1) -> 43616 | R10: =++R9+1 -> 5 | S10: =S9 -> 184355.25 | T10: =W9 -> 35700000 | U10: =(S10-V10)*(R10>$J$26) -> 0 | V10: =$J$25*T10*((Q10-Q9)/365) -> 141377.13 | W10: =T10-U10 -> 35700000
B11: Acquisition Assumptions | M11: 43654 | N11: 0.0248534 | Q11: =EOMONTH(Q10,1) -> 43646 | R11: =++R10+1 -> 6 | S11: =S10 -> 184355.25 | T11: =W10 -> 35700000 | U11: =(S11-V11)*(R11>$J$26) -> 0 | V11: =$J$25*T11*((Q11-Q10)/365) -> 136816.58 | W11: =T11-U11 -> 35700000
B12: Acquisition Date | E12: 43465 | G12: Exit Assumptions | M12: 43684 | N12: 0.0247617 | Q12: =EOMONTH(Q11,1) -> 43677 | R12: =++R11+1 -> 7 | S12: =S11 -> 184355.25 | T12: =W11 -> 35700000 | U12: =(S12-V12)*(R12>$J$26) -> 0 | V12: =$J$25*T12*((Q12-Q11)/365) -> 141377.13 | W12: =T12-U12 -> 35700000
B13: Hold Period | E13: 60 | G13: Exit Date | J13: =EOMONTH(E12,E13) -> 45291 | M13: 43717 | N13: 0.0246092 | Q13: =EOMONTH(Q12,1) -> 43708 | R13: =++R12+1 -> 8 | S13: =S12 -> 184355.25 | T13: =W12 -> 35700000 | U13: =(S13-V13)*(R13>$J$26) -> 0 | V13: =$J$25*T13*((Q13-Q12)/365) -> 141377.13 | W13: =T13-U13 -> 35700000
B14: Purchase Price | E14: 51000000 | G14: Exit Cap Rate | J14: 0.0575 | M14: 43745 | N14: 0.0244316 | Q14: =EOMONTH(Q13,1) -> 43738 | R14: =++R13+1 -> 9 | S14: =S13 -> 184355.25 | T14: =W13 -> 35700000 | U14: =(S14-V14)*(R14>$J$26) -> 0 | V14: =$J$25*T14*((Q14-Q13)/365) -> 136816.58 | W14: =T14-U14 -> 35700000
B15: Acquisition Closing Costs | E15: 0.0125 | G15: Sale Price | J15: =SUM(Model!I59:EK59) -> 63755973 | M15: 43776 | N15: 0.0242373 | Q15: =EOMONTH(Q14,1) -> 43769 | R15: =++R14+1 -> 10 | S15: =S14 -> 184355.25 | T15: =W14 -> 35700000 | U15: =(S15-V15)*(R15>$J$26) -> 0 | V15: =$J$25*T15*((Q15-Q14)/365) -> 141377.13 | W15: =T15-U15 -> 35700000
G16: Exit Closing Costs | J16: 0.0125 | M16: 43808 | N16: 0.0239998 | Q16: =EOMONTH(Q15,1) -> 43799 | R16: =++R15+1 -> 11 | S16: =S15 -> 184355.25 | T16: =W15 -> 35700000 | U16: =(S16-V16)*(R16>$J$26) -> 0 | V16: =$J$25*T16*((Q16-Q15)/365) -> 136816.58 | W16: =T16-U16 -> 35700000
B17: Renovation Budget | M17: 43837 | N17: 0.0237498 | Q17: =EOMONTH(Q16,1) -> 43830 | R17: =++R16+1 -> 12 | S17: =S16 -> 184355.25 | T17: =W16 -> 35700000 | U17: =(S17-V17)*(R17>$J$26) -> 0 | V17: =$J$25*T17*((Q17-Q16)/365) -> 141377.13 | W17: =T17-U17 -> 35700000
D18: Per Unit | E18: Total | G18: Financing Assumptions | M18: 43868 | N18: 0.0234851 | Q18: =EOMONTH(Q17,1) -> 43861 | R18: =++R17+1 -> 13 | S18: =S17 -> 184355.25 | T18: =W17 -> 35700000 | U18: =(S18-V18)*(R18>$J$26) -> 0 | V18: =$J$25*T18*((Q18-Q17)/365) -> 141377.13 | W18: =T18-U18 -> 35700000
B19: Defensive | G19: Start Date | J19: =E12 -> 43465 | M19: 43899 | N19: 0.0231708 | Q19: =EOMONTH(Q18,1) -> 43890 | R19: =++R18+1 -> 14 | S19: =S18 -> 184355.25 | T19: =W18 -> 35700000 | U19: =(S19-V19)*(R19>$J$26) -> 0 | V19: =$J$25*T19*((Q19-Q18)/365) -> 132256.03 | W19: =T19-U19 -> 35700000
B20: Amount | D20: =E20/$E$8 -> 1000 | E20: 250000 | G20: Term | J20: =E13 -> 60 | M20: 43928 | N20: 0.0228538 | Q20: =EOMONTH(Q19,1) -> 43921 | R20: =++R19+1 -> 15 | S20: =S19 -> 184355.25 | T20: =W19 -> 35700000 | U20: =(S20-V20)*(R20>$J$26) -> 0 | V20: =$J$25*T20*((Q20-Q19)/365) -> 141377.13 | W20: =T20-U20 -> 35700000
B21: Contingency | D21: 0.05 | E21: =D21*E20 -> 12500 | G21: Maturity Date | J21: =EOMONTH(J19,J20) -> 45291 | M21: 43958 | N21: 0.0225506 | Q21: =EOMONTH(Q20,1) -> 43951 | R21: =++R20+1 -> 16 | S21: =S20 -> 184355.25 | T21: =W20 -> 35700000 | U21: =(S21-V21)*(R21>$J$26) -> 0 | V21: =$J$25*T21*((Q21-Q20)/365) -> 136816.58 | W21: =T21-U21 -> 35700000
B22: Subtotal | E22: =SUM(E20:E21) -> 262500 | G22: Loan Amount | J22: =J23*E14 -> 35700000 | M22: 43990 | N22: 0.0222459 | Q22: =EOMONTH(Q21,1) -> 43982 | R22: =++R21+1 -> 17 | S22: =S21 -> 184355.25 | T22: =W21 -> 35700000 | U22: =(S22-V22)*(R22>$J$26) -> 0 | V22: =$J$25*T22*((Q22-Q21)/365) -> 141377.13 | W22: =T22-U22 -> 35700000
G23: Loan-to-Purchase Price | J23: 0.7 | M23: 44019 | N23: 0.0219826 | Q23: =EOMONTH(Q22,1) -> 44012 | R23: =++R22+1 -> 18 | S23: =S22 -> 184355.25 | T23: =W22 -> 35700000 | U23: =(S23-V23)*(R23>$J$26) -> 0 | V23: =$J$25*T23*((Q23-Q22)/365) -> 136816.58 | W23: =T23-U23 -> 35700000
B24: Offensive | G24: Interest Rate Spread | J24: 215 | M24: 44050 | N24: 0.021773 | Q24: =EOMONTH(Q23,1) -> 44043 | R24: =++R23+1 -> 19 | S24: =S23 -> 184355.25 | T24: =W23 -> 35700000 | U24: =(S24-V24)*(R24>$J$26) -> 0 | V24: =$J$25*T24*((Q24-Q23)/365) -> 141377.13 | W24: =T24-U24 -> 35700000
B25: Amount | D25: 6000 | E25: =D25*$E$8 -> 1500000 | G25: All-in Rate | J25: =N5+J24/10000 -> 0.0466275 | M25: 44081 | N25: 0.0215892 | Q25: =EOMONTH(Q24,1) -> 44074 | R25: =++R24+1 -> 20 | S25: =S24 -> 184355.25 | T25: =W24 -> 35700000 | U25: =(S25-V25)*(R25>$J$26) -> 0 | V25: =$J$25*T25*((Q25-Q24)/365) -> 141377.13 | W25: =T25-U25 -> 35700000
B26: Contingency | D26: 0.05 | E26: =D26*E25 -> 75000 | G26: Interest Only Period | J26: 48 | M26: 44111 | N26: 0.0214692 | Q26: =EOMONTH(Q25,1) -> 44104 | R26: =++R25+1 -> 21 | S26: =S25 -> 184355.25 | T26: =W25 -> 35700000 | U26: =(S26-V26)*(R26>$J$26) -> 0 | V26: =$J$25*T26*((Q26-Q25)/365) -> 136816.58 | W26: =T26-U26 -> 35700000
B27: Subtotal | E27: =SUM(E25:E26) -> 1575000 | G27: Amortization Period | J27: 30 | M27: 44144 | N27: 0.0214124 | Q27: =EOMONTH(Q26,1) -> 44135 | R27: =++R26+1 -> 22 | S27: =S26 -> 184355.25 | T27: =W26 -> 35700000 | U27: =(S27-V27)*(R27>$J$26) -> 0 | V27: =$J$25*T27*((Q27-Q26)/365) -> 141377.13 | W27: =T27-U27 -> 35700000
B28: Total | E28: =E22+E27 -> 1837500 | G28: Origination Fee | J28: 0.005 | M28: 44172 | N28: 0.0213752 | Q28: =EOMONTH(Q27,1) -> 44165 | R28: =++R27+1 -> 23 | S28: =S27 -> 184355.25 | T28: =W27 -> 35700000 | U28: =(S28-V28)*(R28>$J$26) -> 0 | V28: =$J$25*T28*((Q28-Q27)/365) -> 136816.58 | W28: =T28-U28 -> 35700000
M29: 44203 | N29: 0.0213804 | Q29: =EOMONTH(Q28,1) -> 44196 | R29: =++R28+1 -> 24 | S29: =S28 -> 184355.25 | T29: =W28 -> 35700000 | U29: =(S29-V29)*(R29>$J$26) -> 0 | V29: =$J$25*T29*((Q29-Q28)/365) -> 141377.13 | W29: =T29-U29 -> 35700000
M30: 44235 | N30: 0.0214102 | Q30: =EOMONTH(Q29,1) -> 44227 | R30: =++R29+1 -> 25 | S30: =S29 -> 184355.25 | T30: =W29 -> 35700000 | U30: =(S30-V30)*(R30>$J$26) -> 0 | V30: =$J$25*T30*((Q30-Q29)/365) -> 141377.13 | W30: =T30-U30 -> 35700000
B31: Drivers | M31: 44263 | N31: 0.0214238 | Q31: =EOMONTH(Q30,1) -> 44255 | R31: =++R30+1 -> 26 | S31: =S30 -> 184355.25 | T31: =W30 -> 35700000 | U31: =(S31-V31)*(R31>$J$26) -> 0 | V31: =$J$25*T31*((Q31-Q30)/365) -> 127695.48 | W31: =T31-U31 -> 35700000
M32: 44293 | N32: 0.0214432 | Q32: =EOMONTH(Q31,1) -> 44286 | R32: =++R31+1 -> 27 | S32: =S31 -> 184355.25 | T32: =W31 -> 35700000 | U32: =(S32-V32)*(R32>$J$26) -> 0 | V32: =$J$25*T32*((Q32-Q31)/365) -> 141377.13 | W32: =T32-U32 -> 35700000
B33: Income Assumptions | G33: Operating Expense Assumptions | M33: 44323 | N33: 0.0214684 | Q33: =EOMONTH(Q32,1) -> 44316 | R33: =++R32+1 -> 28 | S33: =S32 -> 184355.25 | T33: =W32 -> 35700000 | U33: =(S33-V33)*(R33>$J$26) -> 0 | V33: =$J$25*T33*((Q33-Q32)/365) -> 136816.58 | W33: =T33-U33 -> 35700000
D34: Assumption | E34: Total | H34: % | I34: Per Unit | J34: Total | M34: 44354 | N34: 0.0214777 | Q34: =EOMONTH(Q33,1) -> 44347 | R34: =++R33+1 -> 29 | S34: =S33 -> 184355.25 | T34: =W33 -> 35700000 | U34: =(S34-V34)*(R34>$J$26) -> 0 | V34: =$J$25*T34*((Q34-Q33)/365) -> 141377.13 | W34: =T34-U34 -> 35700000
B35: Occupancy | E35: =Model!F22 -> 0.9 | G35: Repairs & Maintenance | I35: =Model!G32 -> 1327.92 | J35: =I35*$E$8 -> 331980 | M35: 44384 | N35: 0.0214958 | Q35: =EOMONTH(Q34,1) -> 44377 | R35: =++R34+1 -> 30 | S35: =S34 -> 184355.25 | T35: =W34 -> 35700000 | U35: =(S35-V35)*(R35>$J$26) -> 0 | V35: =$J$25*T35*((Q35-Q34)/365) -> 136816.58 | W35: =T35-U35 -> 35700000
B36: Effective Rent / Month | E36: =Model!F20 -> 2053.8001 | G36: Turnover | I36: =Model!G33 -> 351.648 | J36: =I36*$E$8 -> 87912 | M36: 44417 | N36: 0.0215259 | Q36: =EOMONTH(Q35,1) -> 44408 | R36: =++R35+1 -> 31 | S36: =S35 -> 184355.25 | T36: =W35 -> 35700000 | U36: =(S36-V36)*(R36>$J$26) -> 0 | V36: =$J$25*T36*((Q36-Q35)/365) -> 141377.13 | W36: =T36-U36 -> 35700000
G37: Marketing | I37: =Model!G34 -> 1158.512 | J37: =I37*$E$8 -> 289628 | M37: 44446 | N37: 0.021547 | Q37: =EOMONTH(Q36,1) -> 44439 | R37: =++R36+1 -> 32 | S37: =S36 -> 184355.25 | T37: =W36 -> 35700000 | U37: =(S37-V37)*(R37>$J$26) -> 0 | V37: =$J$25*T37*((Q37-Q36)/365) -> 141377.13 | W37: =T37-U37 -> 35700000
B38: Effective Rent | E38: =E36*E8*12 -> 6161400.4 | G38: General & Administrative | I38: =Model!G35 -> 280.544 | J38: =I38*$E$8 -> 70136 | M38: 44476 | N38: 0.0215818 | Q38: =EOMONTH(Q37,1) -> 44469 | R38: =++R37+1 -> 33 | S38: =S37 -> 184355.25 | T38: =W37 -> 35700000 | U38: =(S38-V38)*(R38>$J$26) -> 0 | V38: =$J$25*T38*((Q38-Q37)/365) -> 136816.58 | W38: =T38-U38 -> 35700000
B39: Vacancy Loss | E39: =Model!F16 -> -616140.04 | G39: Payroll | I39: =Model!G36 -> 1519.568 | J39: =I39*$E$8 -> 379892 | M39: 44508 | N39: 0.0216311 | Q39: =EOMONTH(Q38,1) -> 44500 | R39: =++R38+1 -> 34 | S39: =S38 -> 184355.25 | T39: =W38 -> 35700000 | U39: =(S39-V39)*(R39>$J$26) -> 0 | V39: =$J$25*T39*((Q39-Q38)/365) -> 141377.13 | W39: =T39-U39 -> 35700000
B40: Non-Revenue Units | D40: =-E40/$E$38 -> 0.0017138961 | E40: =Model!F17 -> -10560 | G40: Management Fees | H40: 0.029772407 | I40: =J40/E8 -> 656.22057 | J40: =H40*E42 -> 164055.14 | M40: 44537 | N40: 0.0216726 | Q40: =EOMONTH(Q39,1) -> 44530 | R40: =++R39+1 -> 35 | S40: =S39 -> 184355.25 | T40: =W39 -> 35700000 | U40: =(S40-V40)*(R40>$J$26) -> 0 | V40: =$J$25*T40*((Q40-Q39)/365) -> 136816.58 | W40: =T40-U40 -> 35700000
B41: Collection Loss | D41: =-E41/$E$38 -> 0.0039588403 | E41: =Model!F18 -> -24392 | G41: Utilities | I41: =Model!G38 -> 582.272 | J41: =I41*$E$8 -> 145568 | M41: 44568 | N41: 0.0217284 | Q41: =EOMONTH(Q40,1) -> 44561 | R41: =++R40+1 -> 36 | S41: =S40 -> 184355.25 | T41: =W40 -> 35700000 | U41: =(S41-V41)*(R41>$J$26) -> 0 | V41: =$J$25*T41*((Q41-Q40)/365) -> 141377.13 | W41: =T41-U41 -> 35700000
B42: Total Rental Income | E42: =SUM(E38:E41) -> 5510308.4 | G42: Real Estate Taxes | I42: =Model!G39 -> 6554.016 | J42: =I42*$E$8 -> 1638504 | M42: 44599 | N42: 0.0217982 | Q42: =EOMONTH(Q41,1) -> 44592 | R42: =++R41+1 -> 37 | S42: =S41 -> 184355.25 | T42: =W41 -> 35700000 | U42: =(S42-V42)*(R42>$J$26) -> 0 | V42: =$J$25*T42*((Q42-Q41)/365) -> 141377.13 | W42: =T42-U42 -> 35700000
B43: Utility Reimbursement | E43: =Model!F25 -> 99715.74 | G43: Property Insurance | I43: =Model!G40 -> 352.448 | J43: =I43*$E$8 -> 88112 | M43: 44627 | N43: 0.0218573 | Q43: =EOMONTH(Q42,1) -> 44620 | R43: =++R42+1 -> 38 | S43: =S42 -> 184355.25 | T43: =W42 -> 35700000 | U43: =(S43-V43)*(R43>$J$26) -> 0 | V43: =$J$25*T43*((Q43-Q42)/365) -> 127695.48 | W43: =T43-U43 -> 35700000
B44: Other Income | E44: =Model!F26 -> 263945 | G44: Subtotal | I44: =SUM(I35:I43) -> 12783.149 | J44: =SUM(J35:J43) -> 3195787.1 | M44: 44658 | N44: 0.0219293 | Q44: =EOMONTH(Q43,1) -> 44651 | R44: =++R43+1 -> 39 | S44: =S43 -> 184355.25 | T44: =W43 -> 35700000 | U44: =(S44-V44)*(R44>$J$26) -> 0 | V44: =$J$25*T44*((Q44-Q43)/365) -> 141377.13 | W44: =T44-U44 -> 35700000
B45: Total Income | E45: =SUM(E42:E44) -> 5873969.1 | G45: Replacement Reserve | I45: 250 | J45: =I45*$E$8 -> 62500 | M45: 44690 | N45: 0.0220135 | Q45: =EOMONTH(Q44,1) -> 44681 | R45: =++R44+1 -> 40 | S45: =S44 -> 184355.25 | T45: =W44 -> 35700000 | U45: =(S45-V45)*(R45>$J$26) -> 0 | V45: =$J$25*T45*((Q45-Q44)/365) -> 136816.58 | W45: =T45-U45 -> 35700000
B46: Operating Expenses | E46: =-J46 -> -3258287.1 | G46: Total | I46: =SUM(I44:I45) -> 13033.149 | J46: =SUM(J44:J45) -> 3258287.1 | M46: 44719 | N46: 0.0220843 | Q46: =EOMONTH(Q45,1) -> 44712 | R46: =++R45+1 -> 41 | S46: =S45 -> 184355.25 | T46: =W45 -> 35700000 | U46: =(S46-V46)*(R46>$J$26) -> 0 | V46: =$J$25*T46*((Q46-Q45)/365) -> 141377.13 | W46: =T46-U46 -> 35700000
B47: Net Operating Income | E47: =SUM(E45:E46) -> 2615682 | M47: 44749 | N47: 0.0221652 | Q47: =EOMONTH(Q46,1) -> 44742 | R47: =++R46+1 -> 42 | S47: =S46 -> 184355.25 | T47: =W46 -> 35700000 | U47: =(S47-V47)*(R47>$J$26) -> 0 | V47: =$J$25*T47*((Q47-Q46)/365) -> 136816.58 | W47: =T47-U47 -> 35700000
M48: 44781 | N48: 0.0222562 | Q48: =EOMONTH(Q47,1) -> 44773 | R48: =++R47+1 -> 43 | S48: =S47 -> 184355.25 | T48: =W47 -> 35700000 | U48: =(S48-V48)*(R48>$J$26) -> 0 | V48: =$J$25*T48*((Q48-Q47)/365) -> 141377.13 | W48: =T48-U48 -> 35700000
B49: Revenue & Expense Assumptions | M49: 44811 | N49: 0.0223325 | Q49: =EOMONTH(Q48,1) -> 44804 | R49: =++R48+1 -> 44 | S49: =S48 -> 184355.25 | T49: =W48 -> 35700000 | U49: =(S49-V49)*(R49>$J$26) -> 0 | V49: =$J$25*T49*((Q49-Q48)/365) -> 141377.13 | W49: =T49-U49 -> 35700000
E50: Rent | G50: Expense | H50: RET | J50: Other Income | M50: 44841 | N50: 0.0224177 | Q50: =EOMONTH(Q49,1) -> 44834 | R50: =++R49+1 -> 45 | S50: =S49 -> 184355.25 | T50: =W49 -> 35700000 | U50: =(S50-V50)*(R50>$J$26) -> 0 | V50: =$J$25*T50*((Q50-Q49)/365) -> 136816.58 | W50: =T50-U50 -> 35700000
B51: Year | D51: Occupancy | E51: Growth | G51: Growth | H51: Growth | J51: Growth | M51: 44872 | N51: 0.022512 | Q51: =EOMONTH(Q50,1) -> 44865 | R51: =++R50+1 -> 46 | S51: =S50 -> 184355.25 | T51: =W50 -> 35700000 | U51: =(S51-V51)*(R51>$J$26) -> 0 | V51: =$J$25*T51*((Q51-Q50)/365) -> 141377.13 | W51: =T51-U51 -> 35700000
B52: 1 | D52: 0.91 | E52: 0 | G52: 0 | H52: 0 | J52: 0 | M52: 44902 | N52: 0.0225918 | Q52: =EOMONTH(Q51,1) -> 44895 | R52: =++R51+1 -> 47 | S52: =S51 -> 184355.25 | T52: =W51 -> 35700000 | U52: =(S52-V52)*(R52>$J$26) -> 0 | V52: =$J$25*T52*((Q52-Q51)/365) -> 136816.58 | W52: =T52-U52 -> 35700000
B53: =++B52+1 -> 2 | D53: 0.92 | E53: 0.03 | G53: 0.03 | H53: 0.02 | J53: 0.03 | M53: 44935 | N53: 0.0226812 | Q53: =EOMONTH(Q52,1) -> 44926 | R53: =++R52+1 -> 48 | S53: =S52 -> 184355.25 | T53: =W52 -> 35700000 | U53: =(S53-V53)*(R53>$J$26) -> 0 | V53: =$J$25*T53*((Q53-Q52)/365) -> 141377.13 | W53: =T53-U53 -> 35700000
B54: =++B53+1 -> 3 | D54: 0.93 | E54: 0.04 | G54: =G53 -> 0.03 | H54: =H53 -> 0.02 | J54: =J53 -> 0.03 | M54: 44964 | N54: 0.0227792 | Q54: =EOMONTH(Q53,1) -> 44957 | R54: =++R53+1 -> 49 | S54: =S53 -> 184355.25 | T54: =W53 -> 35700000 | U54: =(S54-V54)*(R54>$J$26) -> 42978.112 | V54: =$J$25*T54*((Q54-Q53)/365) -> 141377.13 | W54: =T54-U54 -> 35657022
B55: =++B54+1 -> 4 | D55: =++D54 -> 0.93 | E55: 0.03 | G55: =G54 -> 0.03 | H55: =H54 -> 0.02 | J55: =J54 -> 0.03 | M55: 44992 | N55: 0.0228619 | Q55: =EOMONTH(Q54,1) -> 44985 | R55: =++R54+1 -> 50 | S55: =S54 -> 184355.25 | T55: =W54 -> 35657022 | U55: =(S55-V55)*(R55>$J$26) -> 56813.499 | V55: =$J$25*T55*((Q55-Q54)/365) -> 127541.75 | W55: =T55-U55 -> 35600208
B56: =++B55+1 -> 5 | D56: =++D55 -> 0.93 | E56: =E55 -> 0.03 | G56: =G55 -> 0.03 | H56: =H55 -> 0.02 | J56: =J55 -> 0.03 | M56: 45023 | N56: 0.0229436 | Q56: =EOMONTH(Q55,1) -> 45016 | R56: =++R55+1 -> 51 | S56: =S55 -> 184355.25 | T56: =W55 -> 35600208 | U56: =(S56-V56)*(R56>$J$26) -> 43373.301 | V56: =$J$25*T56*((Q56-Q55)/365) -> 140981.95 | W56: =T56-U56 -> 35556835
B57: =++B56+1 -> 6 | D57: =++D56 -> 0.93 | E57: =E56 -> 0.03 | G57: =G56 -> 0.03 | H57: =H56 -> 0.02 | J57: =J56 -> 0.03 | M57: 45054 | N57: 0.0230538 | Q57: =EOMONTH(Q56,1) -> 45046 | R57: =++R56+1 -> 52 | S57: =S56 -> 184355.25 | T57: =W56 -> 35556835 | U57: =(S57-V57)*(R57>$J$26) -> 48087.33 | V57: =$J$25*T57*((Q57-Q56)/365) -> 136267.92 | W57: =T57-U57 -> 35508748
B58: =++B57+1 -> 7 | D58: =++D57 -> 0.93 | E58: =E57 -> 0.03 | G58: =G57 -> 0.03 | H58: =H57 -> 0.02 | J58: =J57 -> 0.03 | M58: 45084 | N58: 0.0231378 | Q58: =EOMONTH(Q57,1) -> 45077 | R58: =++R57+1 -> 53 | S58: =S57 -> 184355.25 | T58: =W57 -> 35508748 | U58: =(S58-V58)*(R58>$J$26) -> 43735.498 | V58: =$J$25*T58*((Q58-Q57)/365) -> 140619.75 | W58: =T58-U58 -> 35465012
B59: =++B58+1 -> 8 | D59: =++D58 -> 0.93 | E59: =E58 -> 0.03 | G59: =G58 -> 0.03 | H59: =H58 -> 0.02 | J59: =J58 -> 0.03 | M59: 45114 | N59: 0.0232297 | Q59: =EOMONTH(Q58,1) -> 45107 | R59: =++R58+1 -> 54 | S59: =S58 -> 184355.25 | T59: =W58 -> 35465012 | U59: =(S59-V59)*(R59>$J$26) -> 48439.231 | V59: =$J$25*T59*((Q59-Q58)/365) -> 135916.02 | W59: =T59-U59 -> 35416573
B60: =++B59+1 -> 9 | D60: =++D59 -> 0.93 | E60: =E59 -> 0.03 | G60: =G59 -> 0.03 | H60: =H59 -> 0.02 | J60: =J59 -> 0.03 | M60: 45145 | N60: 0.02333 | Q60: =EOMONTH(Q59,1) -> 45138 | R60: =++R59+1 -> 55 | S60: =S59 -> 184355.25 | T60: =W59 -> 35416573 | U60: =(S60-V60)*(R60>$J$26) -> 44100.524 | V60: =$J$25*T60*((Q60-Q59)/365) -> 140254.72 | W60: =T60-U60 -> 35372473
B61: =++B60+1 -> 10 | D61: =++D60 -> 0.93 | E61: =E60 -> 0.03 | G61: =G60 -> 0.03 | H61: =H60 -> 0.02 | J61: =J60 -> 0.03 | M61: 45176 | N61: 0.0234155 | Q61: =EOMONTH(Q60,1) -> 45169 | R61: =++R60+1 -> 56 | S61: =S60 -> 184355.25 | T61: =W60 -> 35372473 | U61: =(S61-V61)*(R61>$J$26) -> 44275.168 | V61: =$J$25*T61*((Q61-Q60)/365) -> 140080.08 | W61: =T61-U61 -> 35328197
B62: =++B61+1 -> 11 | D62: =++D61 -> 0.93 | E62: =E61 -> 0.03 | G62: =G61 -> 0.03 | H62: =H61 -> 0.02 | J62: =J61 -> 0.03 | M62: 45208 | N62: 0.0235093 | Q62: =EOMONTH(Q61,1) -> 45199 | R62: =++R61+1 -> 57 | S62: =S61 -> 184355.25 | T62: =W61 -> 35328197 | U62: =(S62-V62)*(R62>$J$26) -> 48963.56 | V62: =$J$25*T62*((Q62-Q61)/365) -> 135391.69 | W62: =T62-U62 -> 35279234
M63: 45237 | N63: 0.0236101 | Q63: =EOMONTH(Q62,1) -> 45230 | R63: =++R62+1 -> 58 | S63: =S62 -> 184355.25 | T63: =W62 -> 35279234 | U63: =(S63-V63)*(R63>$J$26) -> 44644.407 | V63: =$J$25*T63*((Q63-Q62)/365) -> 139710.84 | W63: =T63-U63 -> 35234589
B64: Capital Expenditures | M64: 45267 | N64: 0.0236943 | Q64: =EOMONTH(Q63,1) -> 45260 | R64: =++R63+1 -> 59 | S64: =S63 -> 184355.25 | T64: =W63 -> 35234589 | U64: =(S64-V64)*(R64>$J$26) -> 49322.303 | V64: =$J$25*T64*((Q64-Q63)/365) -> 135032.94 | W64: =T64-U64 -> 35185267
B65: Schedule | M65: 45299 | N65: 0.0237867 | Q65: =EOMONTH(Q64,1) -> 45291 | R65: =++R64+1 -> 60 | S65: =S64 -> 184355.25 | T65: =W64 -> 35185267 | U65: =(S65-V65)*(R65>$J$26) -> 45016.528 | V65: =$J$25*T65*((Q65-Q64)/365) -> 139338.72 | W65: =T65-U65 -> 35140251
C66: Start | D66: End | E66: Duration | M66: 45329 | N66: 0.0238879 | Q66: =EOMONTH(Q65,1) -> 45322 | R66: =++R65+1 -> 61 | S66: =S65 -> 184355.25 | T66: =W65 -> 35140251 | U66: =(S66-V66)*(R66>$J$26) -> 45194.8 | V66: =$J$25*T66*((Q66-Q65)/365) -> 139160.45 | W66: =T66-U66 -> 35095056
B67: Defensive | C67: =EOMONTH($E$12,1) -> 43496 | D67: =EOMONTH(C67,E67) -> 43677 | E67: 6 | M67: 45358 | N67: 0.0239736 | Q67: =EOMONTH(Q66,1) -> 45351 | R67: =++R66+1 -> 62 | S67: =S66 -> 184355.25 | T67: =W66 -> 35095056 | U67: =(S67-V67)*(R67>$J$26) -> 54340.325 | V67: =$J$25*T67*((Q67-Q66)/365) -> 130014.92 | W67: =T67-U67 -> 35040715
B68: Offensive | C68: =EOMONTH($E$12,3) -> 43555 | D68: =EOMONTH(C68,E68) -> 44286 | E68: 24 | M68: 45390 | N68: 0.0240692 | Q68: =EOMONTH(Q67,1) -> 45382 | R68: =++R67+1 -> 63 | S68: =S67 -> 184355.25 | T68: =W67 -> 35040715 | U68: =(S68-V68)*(R68>$J$26) -> 45588.974 | V68: =$J$25*T68*((Q68-Q67)/365) -> 138766.27 | W68: =T68-U68 -> 34995126
M69: 45419 | N69: 0.0241741 | Q69: =EOMONTH(Q68,1) -> 45412 | R69: =++R68+1 -> 64 | S69: =S68 -> 184355.25 | T69: =W68 -> 34995126 | U69: =(S69-V69)*(R69>$J$26) -> 50240.02 | V69: =$J$25*T69*((Q69-Q68)/365) -> 134115.23 | W69: =T69-U69 -> 34944886
B70: Unit Renovations | M70: 45450 | N70: 0.0242639 | Q70: =EOMONTH(Q69,1) -> 45443 | R70: =++R69+1 -> 65 | S70: =S69 -> 184355.25 | T70: =W69 -> 34944886 | U70: =(S70-V70)*(R70>$J$26) -> 45968.47 | V70: =$J$25*T70*((Q70-Q69)/365) -> 138386.78 | W70: =T70-U70 -> 34898918
B71: Units Renovated | E71: 0 | M71: 45481 | N71: 0.0243634 | Q71: =EOMONTH(Q70,1) -> 45473 | R71: =++R70+1 -> 66 | S71: =S70 -> 184355.25 | T71: =W70 -> 34898918 | U71: =(S71-V71)*(R71>$J$26) -> 50608.729 | V71: =$J$25*T71*((Q71-Q70)/365) -> 133746.52 | W71: =T71-U71 -> 34848309
B72: Remaining Units | D72: =E72/E8 -> 1 | E72: =E8-E71 -> 250 | M72: 45511 | N72: 0.0244723 | Q72: =EOMONTH(Q71,1) -> 45504 | R72: =++R71+1 -> 67 | S72: =S71 -> 184355.25 | T72: =W71 -> 34848309 | U72: =(S72-V72)*(R72>$J$26) -> 46350.93 | V72: =$J$25*T72*((Q72-Q71)/365) -> 138004.32 | W72: =T72-U72 -> 34801958
B73: Units Renovated / Month | E73: =E72/E68 -> 10.416667 | M73: 45544 | N73: 0.0245659 | Q73: =EOMONTH(Q72,1) -> 45535 | R73: =++R72+1 -> 68 | S73: =S72 -> 184355.25 | T73: =W72 -> 34801958 | U73: =(S73-V73)*(R73>$J$26) -> 46534.486 | V73: =$J$25*T73*((Q73-Q72)/365) -> 137820.76 | W73: =T73-U73 -> 34755424
B74: Rent Premium | E74: 125 | M74: 45572 | N74: 0.0246672 | Q74: =EOMONTH(Q73,1) -> 45565 | R74: =++R73+1 -> 69 | S74: =S73 -> 184355.25 | T74: =W73 -> 34755424 | U74: =(S74-V74)*(R74>$J$26) -> 51158.656 | V74: =$J$25*T74*((Q74-Q73)/365) -> 133196.59 | W74: =T74-U74 -> 34704265
B75: ROI | E75: =E74*12/D25 -> 0.25 | M75: 45603 | N75: 0.0247764 | Q75: =EOMONTH(Q74,1) -> 45596 | R75: =++R74+1 -> 70 | S75: =S74 -> 184355.25 | T75: =W74 -> 34704265 | U75: =(S75-V75)*(R75>$J$26) -> 46921.365 | V75: =$J$25*T75*((Q75-Q74)/365) -> 137433.88 | W75: =T75-U75 -> 34657344
M76: 45635 | N76: 0.0248689 | Q76: =EOMONTH(Q75,1) -> 45626 | R76: =++R75+1 -> 71 | S76: =S75 -> 184355.25 | T76: =W75 -> 34657344 | U76: =(S76-V76)*(R76>$J$26) -> 51534.538 | V76: =$J$25*T76*((Q76-Q75)/365) -> 132820.71 | W76: =T76-U76 -> 34605809
M77: 45664 | N77: 0.0249675 | Q77: =EOMONTH(Q76,1) -> 45657 | R77: =++R76+1 -> 72 | S77: =S76 -> 184355.25 | T77: =W76 -> 34605809 | U77: =(S77-V77)*(R77>$J$26) -> 47311.265 | V77: =$J$25*T77*((Q77-Q76)/365) -> 137043.98 | W77: =T77-U77 -> 34558498
M78: 45695 | N78: 0.0250717 | Q78: =EOMONTH(Q77,1) -> 45688 | R78: =++R77+1 -> 73 | S78: =S77 -> 184355.25 | T78: =W77 -> 34558498 | U78: =(S78-V78)*(R78>$J$26) -> 47498.624 | V78: =$J$25*T78*((Q78-Q77)/365) -> 136856.62 | W78: =T78-U78 -> 34510999
M79: 45723 | N79: 0.0251563 | Q79: =EOMONTH(Q78,1) -> 45716 | R79: =++R78+1 -> 74 | S79: =S78 -> 184355.25 | T79: =W78 -> 34510999 | U79: =(S79-V79)*(R79>$J$26) -> 60912.711 | V79: =$J$25*T79*((Q79-Q78)/365) -> 123442.54 | W79: =T79-U79 -> 34450087
M80: 45754 | N80: 0.0252464 | Q80: =EOMONTH(Q79,1) -> 45747 | R80: =++R79+1 -> 75 | S80: =S79 -> 184355.25 | T80: =W79 -> 34450087 | U80: =(S80-V80)*(R80>$J$26) -> 47927.949 | V80: =$J$25*T80*((Q80-Q79)/365) -> 136427.3 | W80: =T80-U80 -> 34402159
M81: 45784 | N81: 0.0253421 | Q81: =EOMONTH(Q80,1) -> 45777 | R81: =++R80+1 -> 76 | S81: =S80 -> 184355.25 | T81: =W80 -> 34402159 | U81: =(S81-V81)*(R81>$J$26) -> 52512.508 | V81: =$J$25*T81*((Q81-Q80)/365) -> 131842.74 | W81: =T81-U81 -> 34349646
M82: 45817 | N82: 0.0254198 | Q82: =EOMONTH(Q81,1) -> 45808 | R82: =++R81+1 -> 77 | S82: =S81 -> 184355.25 | T82: =W81 -> 34349646 | U82: =(S82-V82)*(R82>$J$26) -> 48325.707 | V82: =$J$25*T82*((Q82-Q81)/365) -> 136029.54 | W82: =T82-U82 -> 34301320
M83: 45845 | N83: 0.0255025 | Q83: =EOMONTH(Q82,1) -> 45838 | R83: =++R82+1 -> 78 | S83: =S82 -> 184355.25 | T83: =W82 -> 34301320 | U83: =(S83-V83)*(R83>$J$26) -> 52898.96 | V83: =$J$25*T83*((Q83-Q82)/365) -> 131456.29 | W83: =T83-U83 -> 34248422
M84: 45876 | N84: 0.0255905 | Q84: =EOMONTH(Q83,1) -> 45869 | R84: =++R83+1 -> 79 | S84: =S83 -> 184355.25 | T84: =W83 -> 34248422 | U84: =(S84-V84)*(R84>$J$26) -> 48726.572 | V84: =$J$25*T84*((Q84-Q83)/365) -> 135628.68 | W84: =T84-U84 -> 34199695
M85: 45908 | N85: 0.02566 | Q85: =EOMONTH(Q84,1) -> 45900 | R85: =++R84+1 -> 80 | S85: =S84 -> 184355.25 | T85: =W84 -> 34199695 | U85: =(S85-V85)*(R85>$J$26) -> 48919.536 | V85: =$J$25*T85*((Q85-Q84)/365) -> 135435.71 | W85: =T85-U85 -> 34150775
M86: 45937 | N86: 0.0257344 | Q86: =EOMONTH(Q85,1) -> 45930 | R86: =++R85+1 -> 81 | S86: =S85 -> 184355.25 | T86: =W85 -> 34150775 | U86: =(S86-V86)*(R86>$J$26) -> 53475.909 | V86: =$J$25*T86*((Q86-Q85)/365) -> 130879.34 | W86: =T86-U86 -> 34097300
M87: 45968 | N87: 0.0258143 | Q87: =EOMONTH(Q86,1) -> 45961 | R87: =++R86+1 -> 82 | S87: =S86 -> 184355.25 | T87: =W86 -> 34097300 | U87: =(S87-V87)*(R87>$J$26) -> 49325.036 | V87: =$J$25*T87*((Q87-Q86)/365) -> 135030.21 | W87: =T87-U87 -> 34047974
... M125: 47126 | N125: 0.0278674 | Q125: =EOMONTH(Q124,1) -> 47118 | R125: =++R124+1 -> 120 | S125: =S124 -> 184355.25 | T125: =W124 -> 31982843 | U125: =(S125-V125)*(R125>$J$26) -> 57698.588 | V125: =$J$25*T125*((Q125-Q124)/365) -> 126656.66 | W125: =T125-U125 -> 31925144
Q126: =EOMONTH(Q125,1) -> 47149 | R126: =++R125+1 -> 121 | S126: =S125 -> 184355.25 | T126: =W125 -> 31925144 | U126: =(S126-V126)*(R126>$J$26) -> 57927.083 | V126: =$J$25*T126*((Q126-Q125)/365) -> 126428.16 | W126: =T126-U126 -> 31867217
Q127: =EOMONTH(Q126,1) -> 47177 | R127: =++R126+1 -> 122 | S127: =S126 -> 184355.25 | T127: =W126 -> 31867217 | U127: =(S127-V127)*(R127>$J$26) -> 70369.266 | V127: =$J$25*T127*((Q127-Q126)/365) -> 113985.98 | W127: =T127-U127 -> 31796848
Q128: =EOMONTH(Q127,1) -> 47208 | R128: =++R127+1 -> 123 | S128: =S127 -> 184355.25 | T128: =W127 -> 31796848 | U128: =(S128-V128)*(R128>$J$26) -> 58435.155 | V128: =$J$25*T128*((Q128-Q127)/365) -> 125920.09 | W128: =T128-U128 -> 31738413
Q129: =EOMONTH(Q128,1) -> 47238 | R129: =++R128+1 -> 124 | S129: =S128 -> 184355.25 | T129: =W128 -> 31738413 | U129: =(S129-V129)*(R129>$J$26) -> 62721.04 | V129: =$J$25*T129*((Q129-Q128)/365) -> 121634.21 | W129: =T129-U129 -> 31675692
Q130: =EOMONTH(Q129,1) -> 47269 | R130: =++R129+1 -> 125 | S130: =S129 -> 184355.25 | T130: =W129 -> 31675692 | U130: =(S130-V130)*(R130>$J$26) -> 58914.951 | V130: =$J$25*T130*((Q130-Q129)/365) -> 125440.3 | W130: =T130-U130 -> 31616777
Q131: =EOMONTH(Q130,1) -> 47299 | R131: =++R130+1 -> 126 | S131: =S130 -> 184355.25 | T131: =W130 -> 31616777 | U131: =(S131-V131)*(R131>$J$26) -> 63187.198 | V131: =$J$25*T131*((Q131-Q130)/365) -> 121168.05 | W131: =T131-U131 -> 31553590
Q132: =EOMONTH(Q131,1) -> 47330 | R132: =++R131+1 -> 127 | S132: =S131 -> 184355.25 | T132: =W131 -> 31553590 | U132: =(S132-V132)*(R132>$J$26) -> 59398.493 | V132: =$J$25*T132*((Q132-Q131)/365) -> 124956.75 | W132: =T132-U132 -> 31494191
Q133: =EOMONTH(Q132,1) -> 47361 | R133: =++R132+1 -> 128 | S133: =S132 -> 184355.25 | T133: =W132 -> 31494191 | U133: =(S133-V133)*(R133>$J$26) -> 59633.719 | V133: =$J$25*T133*((Q133-Q132)/365) -> 124721.53 | W133: =T133-U133 -> 31434558
Q134: =EOMONTH(Q133,1) -> 47391 | R134: =++R133+1 -> 129 | S134: =S133 -> 184355.25 | T134: =W133 -> 31434558 | U134: =(S134-V134)*(R134>$J$26) -> 63885.535 | V134: =$J$25*T134*((Q134-Q133)/365) -> 120469.71 | W134: =T134-U134 -> 31370672
Q135: =EOMONTH(Q134,1) -> 47422 | R135: =++R134+1 -> 130 | S135: =S134 -> 184355.25 | T135: =W134 -> 31370672 | U135: =(S135-V135)*(R135>$J$26) -> 60122.874 | V135: =$J$25*T135*((Q135-Q134)/365) -> 124232.37 | W135: =T135-U135 -> 31310549
Q136: =EOMONTH(Q135,1) -> 47452 | R136: =++R135+1 -> 131 | S136: =S135 -> 184355.25 | T136: =W135 -> 31310549 | U136: =(S136-V136)*(R136>$J$26) -> 64360.784 | V136: =$J$25*T136*((Q136-Q135)/365) -> 119994.46 | W136: =T136-U136 -> 31246188
Q137: =EOMONTH(Q136,1) -> 47483 | R137: =++R136+1 -> 132 | S137: =S136 -> 184355.25 | T137: =W136 -> 31246188 | U137: =(S137-V137)*(R137>$J$26) -> 60615.847 | V137: =$J$25*T137*((Q137-Q136)/365) -> 123739.4 | W137: =T137-U137 -> 31185573
... Q365: =EOMONTH(Q364,1) -> 54423 | R365: =++R364+1 -> 360 | S365: =S364 -> 184355.25 | T365: =W364 -> 8246395.8 | U365: =(S365-V365)*(R365>$J$26) -> 151698.33 | V365: =$J$25*T365*((Q365-Q364)/365) -> 32656.914 | W365: =T365-U365 -> 8094697.5

Sheet Model
B2: Model
B4: Acq. Date | C4: ='Inputs & Drivers'!E12 -> 43465 | E4: Dec 2018 | F4: Dec 2018 | I4: 0 | J4: 1 | K4: 1 | L4: 1 | M4: 1 | N4: 1 | O4: 1 | P4: 1 | Q4: 1 | R4: 1 | S4: 1 | T4: 1 | U4: 1 | V4: =J4+1 -> 2 | W4: =K4+1 -> 2 | X4: =L4+1 -> 2 | Y4: =M4+1 -> 2 | Z4: =N4+1 -> 2 | AA4: =O4+1 -> 2 | AB4: =P4+1 -> 2 | AC4: =Q4+1 -> 2 | ... EK4: =DY4+1 -> 11
B5: Exit Date | C5: ='Inputs & Drivers'!J13 -> 45291 | E5: T-3 Ann. | F5: T-12 | I5: 0 | J5: =++I5+1 -> 1 | K5: =++J5+1 -> 2 | L5: =++K5+1 -> 3 | M5: =++L5+1 -> 4 | N5: =++M5+1 -> 5 | O5: =++N5+1 -> 6 | P5: =++O5+1 -> 7 | Q5: =++P5+1 -> 8 | ... EK5: =++EJ5+1 -> 132 | EM5: 0 | EN5: =EM5+1 -> 1 | EO5: =EN5+1 -> 2 | EP5: =EO5+1 -> 3 | EQ5: =EP5+1 -> 4 | ER5: =EQ5+1 -> 5 | ES5: =ER5+1 -> 6 | ET5: =ES5+1 -> 7 | EU5: =ET5+1 -> 8 | ... EX5: =EW5+1 -> 11
B6: Size | C6: ='Inputs & Drivers'!E8 -> 250 | E6: 43465 | F6: 43465 | I6: =C4 -> 43465 | J6: =EOMONTH(I6,1) -> 43496 | K6: =EOMONTH(J6,1) -> 43524 | L6: =EOMONTH(K6,1) -> 43555 | M6: =EOMONTH(L6,1) -> 43585 | N6: =EOMONTH(M6,1) -> 43616 | O6: =EOMONTH(N6,1) -> 43646 | P6: =EOMONTH(O6,1) -> 43677 | Q6: =EOMONTH(P6,1) -> 43708 | ... EK6: =EOMONTH(EJ6,1) -> 47483 | EM6: =I6 -> 43465 | EN6: =EOMONTH(EM6,12) -> 43830 | EO6: =EOMONTH(EN6,12) -> 44196 | EP6: =EOMONTH(EO6,12) -> 44561 | EQ6: =EOMONTH(EP6,12) -> 44926 | ER6: =EOMONTH(EQ6,12) -> 45291 | ES6: =EOMONTH(ER6,12) -> 45657 | ET6: =EOMONTH(ES6,12) -> 46022 | EU6: =EOMONTH(ET6,12) -> 46387 | ... EX6: =EOMONTH(EW6,12) -> 47483
B8: Units Unrenovated | I8: =$C$6-I9 -> 250 | J8: =$C$6-J9 -> 250 | K8: =$C$6-K9 -> 250 | L8: =$C$6-L9 -> 239.58333 | M8: =$C$6-M9 -> 229.16667 | N8: =$C$6-N9 -> 218.75 | O8: =$C$6-O9 -> 208.33333 | P8: =$C$6-P9 -> 197.91667 | ... EK8: =$C$6-EK9 -> 0 | EM8: =SUMIF($I$6:$EK$6,EM$6,$I8:$EK8) -> 250 | EN8: =SUMIF($I$6:$EK$6,EN$6,$I8:$EK8) -> 145.83333 | EO8: =SUMIF($I$6:$EK$6,EO$6,$I8:$EK8) -> 20.833333 | EP8: =SUMIF($I$6:$EK$6,EP$6,$I8:$EK8) -> 0 | EQ8: =SUMIF($I$6:$EK$6,EQ$6,$I8:$EK8) -> 0 | ER8: =SUMIF($I$6:$EK$6,ER$6,$I8:$EK8) -> 0 | ES8: =SUMIF($I$6:$EK$6,ES$6,$I8:$EK8) -> 0 | ET8: =SUMIF($I$6:$EK$6,ET$6,$I8:$EK8) -> 0 | ... EX8: =SUMIF($I$6:$EK$6,EX$6,$I8:$EK8) -> 0
B9: Units Renovated | I9: ='Inputs & Drivers'!E71 -> 0 | J9: =I9+'Inputs & Drivers'!$E$73*(J$6>='Inputs & Drivers'!$C$68)*(J$6<'Inputs & Drivers'!$D$68) -> 0 | K9: =J9+'Inputs & Drivers'!$E$73*(K$6>='Inputs & Drivers'!$C$68)*(K$6<'Inputs & Drivers'!$D$68) -> 0 | L9: =K9+'Inputs & Drivers'!$E$73*(L$6>='Inputs & Drivers'!$C$68)*(L$6<'Inputs & Drivers'!$D$68) -> 10.416667 | M9: =L9+'Inputs & Drivers'!$E$73*(M$6>='Inputs & Drivers'!$C$68)*(M$6<'Inputs & Drivers'!$D$68) -> 20.833333 | N9: =M9+'Inputs & Drivers'!$E$73*(N$6>='Inputs & Drivers'!$C$68)*(N$6<'Inputs & Drivers'!$D$68) -> 31.25 | O9: =N9+'Inputs & Drivers'!$E$73*(O$6>='Inputs & Drivers'!$C$68)*(O$6<'Inputs & Drivers'!$D$68) -> 41.666667 | P9: =O9+'Inputs & Drivers'!$E$73*(P$6>='Inputs & Drivers'!$C$68)*(P$6<'Inputs & Drivers'!$D$68) -> 52.083333 | Q9: =P9+'Inputs & Drivers'!$E$73*(Q$6>='Inputs & Drivers'!$C$68)*(Q$6<'Inputs & Drivers'!$D$68) -> 62.5 | ... EK9: =EJ9+'Inputs & Drivers'!$E$73*(EK$6>='Inputs & Drivers'!$C$68)*(EK$6<'Inputs & Drivers'!$D$68) -> 250 | EM9: =SUMIF($I$6:$EK$6,EM$6,$I9:$EK9) -> 0 | EN9: =SUMIF($I$6:$EK$6,EN$6,$I9:$EK9) -> 104.16667 | EO9: =SUMIF($I$6:$EK$6,EO$6,$I9:$EK9) -> 229.16667 | EP9: =SUMIF($I$6:$EK$6,EP$6,$I9:$EK9) -> 250 | EQ9: =SUMIF($I$6:$EK$6,EQ$6,$I9:$EK9) -> 250 | ER9: =SUMIF($I$6:$EK$6,ER$6,$I9:$EK9) -> 250 | ES9: =SUMIF($I$6:$EK$6,ES$6,$I9:$EK9) -> 250 | ET9: =SUMIF($I$6:$EK$6,ET$6,$I9:$EK9) -> 250 | ... EX9: =SUMIF($I$6:$EK$6,EX$6,$I9:$EK9) -> 250
B10: Unrenovated Effective Rent | I10: ='Inputs & Drivers'!E36 -> 2053.8001 | J10: =I10*(1+J12) -> 2053.8001 | K10: =J10*(1+K12) -> 2053.8001 | L10: =K10*(1+L12) -> 2053.8001 | M10: =L10*(1+M12) -> 2053.8001 | N10: =M10*(1+N12) -> 2053.8001 | O10: =N10*(1+O12) -> 2053.8001 | P10: =O10*(1+P12) -> 2053.8001 | Q10: =P10*(1+Q12) -> 2053.8001 | ... EK10: =EJ10*(1+EK12) -> 2799.0731 | EM10: =SUMIF($I$6:$EK$6,EM$6,$I10:$EK10) -> 2053.8001 | EN10: =SUMIF($I$6:$EK$6,EN$6,$I10:$EK10) -> 2053.8001 | EO10: =SUMIF($I$6:$EK$6,EO$6,$I10:$EK10) -> 2116.2684 | EP10: =SUMIF($I$6:$EK$6,EP$6,$I10:$EK10) -> 2202.4885 | EQ10: =SUMIF($I$6:$EK$6,EQ$6,$I10:$EK10) -> 2269.4793 | ER10: =SUMIF($I$6:$EK$6,ER$6,$I10:$EK10) -> 2338.5076 | ES10: =SUMIF($I$6:$EK$6,ES$6,$I10:$EK10) -> 2409.6356 | ET10: =SUMIF($I$6:$EK$6,ET$6,$I10:$EK10) -> 2482.927 | ... EX10: =SUMIF($I$6:$EK$6,EX$6,$I10:$EK10) -> 2799.0731
B11: Renovated Effective Rent | I11: =I10+'Inputs & Drivers'!$E$74 -> 2178.8001 | J11: =J10+'Inputs & Drivers'!$E$74 -> 2178.8001 | K11: =K10+'Inputs & Drivers'!$E$74 -> 2178.8001 | L11: =L10+'Inputs & Drivers'!$E$74 -> 2178.8001 | M11: =M10+'Inputs & Drivers'!$E$74 -> 2178.8001 | N11: =N10+'Inputs & Drivers'!$E$74 -> 2178.8001 | O11: =O10+'Inputs & Drivers'!$E$74 -> 2178.8001 | P11: =P10+'Inputs & Drivers'!$E$74 -> 2178.8001 | ... EK11: =EK10+'Inputs & Drivers'!$E$74 -> 2924.0731 | EM11: =SUMIF($I$6:$EK$6,EM$6,$I11:$EK11) -> 2178.8001 | EN11: =SUMIF($I$6:$EK$6,EN$6,$I11:$EK11) -> 2178.8001 | EO11: =SUMIF($I$6:$EK$6,EO$6,$I11:$EK11) -> 2241.2684 | EP11: =SUMIF($I$6:$EK$6,EP$6,$I11:$EK11) -> 2327.4885 | EQ11: =SUMIF($I$6:$EK$6,EQ$6,$I11:$EK11) -> 2394.4793 | ER11: =SUMIF($I$6:$EK$6,ER$6,$I11:$EK11) -> 2463.5076 | ES11: =SUMIF($I$6:$EK$6,ES$6,$I11:$EK11) -> 2534.6356 | ET11: =SUMIF($I$6:$EK$6,ET$6,$I11:$EK11) -> 2607.927 | ... EX11: =SUMIF($I$6:$EK$6,EX$6,$I11:$EK11) -> 2924.0731
B12: Rent Growth | J12: =INDEX('Inputs & Drivers'!$E$52:$E$62,MATCH(Model!J$4,'Inputs & Drivers'!$B$52:$B$62,0))/12 -> 0 | K12: =INDEX('Inputs & Drivers'!$E$52:$E$62,MATCH(Model!K$4,'Inputs & Drivers'!$B$52:$B$62,0))/12 -> 0 | L12: =INDEX('Inputs & Drivers'!$E$52:$E$62,MATCH(Model!L$4,'Inputs & Drivers'!$B$52:$B$62,0))/12 -> 0 | M12: =INDEX('Inputs & Drivers'!$E$52:$E$62,MATCH(Model!M$4,'Inputs & Drivers'!$B$52:$B$62,0))/12 -> 0 | N12: =INDEX('Inputs & Drivers'!$E$52:$E$62,MATCH(Model!N$4,'Inputs & Drivers'!$B$52:$B$62,0))/12 -> 0 | O12: =INDEX('Inputs & Drivers'!$E$52:$E$62,MATCH(Model!O$4,'Inputs & Drivers'!$B$52:$B$62,0))/12 -> 0 | P12: =INDEX('Inputs & Drivers'!$E$52:$E$62,MATCH(Model!P$4,'Inputs & Drivers'!$B$52:$B$62,0))/12 -> 0 | Q12: =INDEX('Inputs & Drivers'!$E$52:$E$62,MATCH(Model!Q$4,'Inputs & Drivers'!$B$52:$B$62,0))/12 -> 0 | ... EK12: =INDEX('Inputs & Drivers'!$E$52:$E$62,MATCH(Model!EK$4,'Inputs & Drivers'!$B$52:$B$62,0))/12 -> 0.0025
B14: INCOME
B15: Effective Rent | E15: =SUM('Historical Financials'!M10:O10)*4 -> 6076116.4 | F15: =SUM('Historical Financials'!D10:O10) -> 6161400.4 | J15: =J8*J10+J9*J11 -> 513450.03 | K15: =K8*K10+K9*K11 -> 513450.03 | L15: =L8*L10+L9*L11 -> 514752.12 | M15: =M8*M10+M9*M11 -> 516054.2 | N15: =N8*N10+N9*N11 -> 517356.28 | O15: =O8*O10+O9*O11 -> 518658.37 | P15: =P8*P10+P9*P11 -> 519960.45 | Q15: =Q8*Q10+Q9*Q11 -> 521262.53 | ... EK15: =EK8*EK10+EK9*EK11 -> 731018.29 | EM15: =SUMIF($I$4:$EK$4,EM$5,$I15:$EK15) -> 0 | EN15: =SUMIF($I$4:$EK$4,EN$5,$I15:$EK15) -> 6233015 | EO15: =SUMIF($I$4:$EK$4,EO$5,$I15:$EK15) -> 6520259.2 | EP15: =SUMIF($I$4:$EK$4,EP$5,$I15:$EK15) -> 6861756 | EQ15: =SUMIF($I$4:$EK$4,EQ$5,$I15:$EK15) -> 7090827.1 | ER15: =SUMIF($I$4:$EK$4,ER$5,$I15:$EK15) -> 7295095.5 | ES15: =SUMIF($I$4:$EK$4,ES$5,$I15:$EK15) -> 7505576.8 | ET15: =SUMIF($I$4:$EK$4,ET$5,$I15:$EK15) -> 7722460.1 | ... EX15: =SUMIF($I$4:$EK$4,EX$5,$I15:$EK15) -> 8657997.6
B16: Vacancy Loss | E16: =SUM('Historical Financials'!M15:O15)*4 -> -607611.64 | F16: =SUM('Historical Financials'!D15:O15) -> -616140.04 | J16: =-(1-INDEX('Inputs & Drivers'!$D$52:$D$62,MATCH(Model!J$4,'Inputs & Drivers'!$B$52:$B$62,0)))*J15 -> -46210.503 | K16: =-(1-INDEX('Inputs & Drivers'!$D$52:$D$62,MATCH(Model!K$4,'Inputs & Drivers'!$B$52:$B$62,0)))*K15 -> -46210.503 | L16: =-(1-INDEX('Inputs & Drivers'!$D$52:$D$62,MATCH(Model!L$4,'Inputs & Drivers'!$B$52:$B$62,0)))*L15 -> -46327.69 | M16: =-(1-INDEX('Inputs & Drivers'!$D$52:$D$62,MATCH(Model!M$4,'Inputs & Drivers'!$B$52:$B$62,0)))*M15 -> -46444.878 | N16: =-(1-INDEX('Inputs & Drivers'!$D$52:$D$62,MATCH(Model!N$4,'Inputs & Drivers'!$B$52:$B$62,0)))*N15 -> -46562.065 | O16: =-(1-INDEX('Inputs & Drivers'!$D$52:$D$62,MATCH(Model!O$4,'Inputs & Drivers'!$B$52:$B$62,0)))*O15 -> -46679.253 | P16: =-(1-INDEX('Inputs & Drivers'!$D$52:$D$62,MATCH(Model!P$4,'Inputs & Drivers'!$B$52:$B$62,0)))*P15 -> -46796.44 | Q16: =-(1-INDEX('Inputs & Drivers'!$D$52:$D$62,MATCH(Model!Q$4,'Inputs & Drivers'!$B$52:$B$62,0)))*Q15 -> -46913.628 | ... EK16: =-(1-INDEX('Inputs & Drivers'!$D$52:$D$62,MATCH(Model!EK$4,'Inputs & Drivers'!$B$52:$B$62,0)))*EK15 -> -51171.28 | EM16: =SUMIF($I$4:$EK$4,EM$5,$I16:$EK16) -> 0 | EN16: =SUMIF($I$4:$EK$4,EN$5,$I16:$EK16) -> -560971.35 | EO16: =SUMIF($I$4:$EK$4,EO$5,$I16:$EK16) -> -521620.74 | EP16: =SUMIF($I$4:$EK$4,EP$5,$I16:$EK16) -> -480322.92 | EQ16: =SUMIF($I$4:$EK$4,EQ$5,$I16:$EK16) -> -496357.9 | ER16: =SUMIF($I$4:$EK$4,ER$5,$I16:$EK16) -> -510656.68 | ES16: =SUMIF($I$4:$EK$4,ES$5,$I16:$EK16) -> -525390.37 | ET16: =SUMIF($I$4:$EK$4,ET$5,$I16:$EK16) -> -540572.21 | ... EX16: =SUMIF($I$4:$EK$4,EX$5,$I16:$EK16) -> -606059.84
B17: Non-Revenue Units | E17: =SUM('Historical Financials'!M16:O16)*4 -> 0 | F17: =SUM('Historical Financials'!D16:O16) -> -10560 | J17: =-'Inputs & Drivers'!$D$40*J$15 -> -880 | K17: =-'Inputs & Drivers'!$D$40*K15 -> -880 | L17: =-'Inputs & Drivers'!$D$40*L15 -> -882.23164 | M17: =-'Inputs & Drivers'!$D$40*M15 -> -884.46327 | N17: =-'Inputs & Drivers'!$D$40*N15 -> -886.69491 | O17: =-'Inputs & Drivers'!$D$40*O15 -> -888.92654 | P17: =-'Inputs & Drivers'!$D$40*P15 -> -891.15818 | Q17: =-'Inputs & Drivers'!$D$40*Q15 -> -893.38981 | R17: =-'Inputs & Drivers'!$D$40*R15 -> -895.62145 | ... EK17: =-'Inputs & Drivers'!$D$40*EK15 -> -1252.8894 | EM17: =SUMIF($I$4:$EK$4,EM$5,$I17:$EK17) -> 0 | EN17: =SUMIF($I$4:$EK$4,EN$5,$I17:$EK17) -> -10682.74 | EO17: =SUMIF($I$4:$EK$4,EO$5,$I17:$EK17) -> -11175.047 | EP17: =SUMIF($I$4:$EK$4,EP$5,$I17:$EK17) -> -11760.337 | EQ17: =SUMIF($I$4:$EK$4,EQ$5,$I17:$EK17) -> -12152.941 | ER17: =SUMIF($I$4:$EK$4,ER$5,$I17:$EK17) -> -12503.036 | ES17: =SUMIF($I$4:$EK$4,ES$5,$I17:$EK17) -> -12863.779 | ET17: =SUMIF($I$4:$EK$4,ET$5,$I17:$EK17) -> -13235.494 | ... EX17: =SUMIF($I$4:$EK$4,EX$5,$I17:$EK17) -> -14838.908
B18: Uncollectible Rent | E18: =SUM('Historical Financials'!M17:O17)*4 -> 0 | F18: =SUM('Historical Financials'!D17:O17) -> -24392 | J18: =-'Inputs & Drivers'!$D$41*J$15 -> -2032.6667 | K18: =-'Inputs & Drivers'!$D$41*K$15 -> -2032.6667 | L18: =-'Inputs & Drivers'!$D$41*L$15 -> -2037.8214 | M18: =-'Inputs & Drivers'!$D$41*M$15 -> -2042.9761 | N18: =-'Inputs & Drivers'!$D$41*N$15 -> -2048.1309 | O18: =-'Inputs & Drivers'!$D$41*O$15 -> -2053.2856 | P18: =-'Inputs & Drivers'!$D$41*P$15 -> -2058.4404 | Q18: =-'Inputs & Drivers'!$D$41*Q$15 -> -2063.5951 | ... EK18: =-'Inputs & Drivers'!$D$41*EK$15 -> -2893.9846 | EM18: =SUMIF($I$4:$EK$4,EM$5,$I18:$EK18) -> 0 | EN18: =SUMIF($I$4:$EK$4,EN$5,$I18:$EK18) -> -24675.511 | EO18: =SUMIF($I$4:$EK$4,EO$5,$I18:$EK18) -> -25812.665 | EP18: =SUMIF($I$4:$EK$4,EP$5,$I18:$EK18) -> -27164.596 | EQ18: =SUMIF($I$4:$EK$4,EQ$5,$I18:$EK18) -> -28071.452 | ER18: =SUMIF($I$4:$EK$4,ER$5,$I18:$EK18) -> -28880.118 | ES18: =SUMIF($I$4:$EK$4,ES$5,$I18:$EK18) -> -29713.38 | ET18: =SUMIF($I$4:$EK$4,ET$5,$I18:$EK18) -> -30571.986 | ... EX18: =SUMIF($I$4:$EK$4,EX$5,$I18:$EK18) -> -34275.63
B19: Total Rental Income | E19: =SUM(E15:E18) -> 5468504.8 | F19: =SUM(F15:F18) -> 5510308.4 | J19: =SUM(J15:J18) -> 464326.86 | K19: =SUM(K15:K18) -> 464326.86 | L19: =SUM(L15:L18) -> 465504.37 | M19: =SUM(M15:M18) -> 466681.88 | N19: =SUM(N15:N18) -> 467859.39 | O19: =SUM(O15:O18) -> 469036.9 | P19: =SUM(P15:P18) -> 470214.41 | Q19: =SUM(Q15:Q18) -> 471391.92 | ... EK19: =SUM(EK15:EK18) -> 675700.13 | EM19: =SUM(EM15:EM18) -> 0 | EN19: =SUM(EN15:EN18) -> 5636685.4 | EO19: =SUM(EO15:EO18) -> 5961650.8 | EP19: =SUM(EP15:EP18) -> 6342508.2 | EQ19: =SUM(EQ15:EQ18) -> 6554244.8 | ER19: =SUM(ER15:ER18) -> 6743055.6 | ES19: =SUM(ES15:ES18) -> 6937609.2 | ET19: =SUM(ET15:ET18) -> 7138080.4 | ... EX19: =SUM(EX15:EX18) -> 8002823.3
B20: Effective Rent / Month | E20: =E15/$C$6/12 -> 2025.3721 | F20: =F15/$C$6/12 -> 2053.8001 | J20: =J15/$C$6 -> 2053.8001 | K20: =K15/$C$6 -> 2053.8001 | L20: =L15/$C$6 -> 2059.0085 | M20: =M15/$C$6 -> 2064.2168 | N20: =N15/$C$6 -> 2069.4251 | O20: =O15/$C$6 -> 2074.6335 | P20: =P15/$C$6 -> 2079.8418 | Q20: =Q15/$C$6 -> 2085.0501 | ... EK20: =EK15/$C$6 -> 2924.0731 | EN20: =EN15/$C$6/12 -> 2077.6717 | EO20: =EO15/$C$6/12 -> 2173.4197 | EP20: =EP15/$C$6/12 -> 2287.252 | EQ20: =EQ15/$C$6/12 -> 2363.609 | ER20: =ER15/$C$6/12 -> 2431.6985 | ES20: =ES15/$C$6/12 -> 2501.8589 | ET20: =ET15/$C$6/12 -> 2574.1534 | EU20: =EU15/$C$6/12 -> 2648.6467 | ... EX20: =EX15/$C$6/12 -> 2885.9992
B21: Effective Rent PSF / Month | E21: =E20/'Inputs & Drivers'!$I$10 -> 2.2014914 | F21: =F20/'Inputs & Drivers'!$I$10 -> 2.2323914 | J21: =J20/'Inputs & Drivers'!$I$10 -> 2.2323914 | K21: =K20/'Inputs & Drivers'!$I$10 -> 2.2323914 | L21: =L20/'Inputs & Drivers'!$I$10 -> 2.2380527 | M21: =M20/'Inputs & Drivers'!$I$10 -> 2.2437139 | N21: =N20/'Inputs & Drivers'!$I$10 -> 2.2493751 | O21: =O20/'Inputs & Drivers'!$I$10 -> 2.2550364 | P21: =P20/'Inputs & Drivers'!$I$10 -> 2.2606976 | Q21: =Q20/'Inputs & Drivers'!$I$10 -> 2.2663588 | ... EK21: =EK20/'Inputs & Drivers'!$I$10 -> 3.1783404 | EN21: =EN20/'Inputs & Drivers'!$I$10 -> 2.2583388 | EO21: =EO20/'Inputs & Drivers'!$I$10 -> 2.3624128 | EP21: =EP20/'Inputs & Drivers'!$I$10 -> 2.4861435 | EQ21: =EQ20/'Inputs & Drivers'!$I$10 -> 2.5691403 | ER21: =ER20/'Inputs & Drivers'!$I$10 -> 2.6431505 | ES21: =ES20/'Inputs & Drivers'!$I$10 -> 2.7194119 | ET21: =ET20/'Inputs & Drivers'!$I$10 -> 2.7979928 | EU21: =EU20/'Inputs & Drivers'!$I$10 -> 2.8789638 | ... EX21: =EX20/'Inputs & Drivers'!$I$10 -> 3.1369557
B22: Physical Occupancy | E22: =E16/E15+1 -> 0.9 | F22: =F16/F15+1 -> 0.9 | J22: =J16/J15+1 -> 0.91 | K22: =K16/K15+1 -> 0.91 | L22: =L16/L15+1 -> 0.91 | M22: =M16/M15+1 -> 0.91 | N22: =N16/N15+1 -> 0.91 | O22: =O16/O15+1 -> 0.91 | P22: =P16/P15+1 -> 0.91 | Q22: =Q16/Q15+1 -> 0.91 | ... EK22: =EK16/EK15+1 -> 0.93 | EN22: =EN16/EN15+1 -> 0.91 | EO22: =EO16/EO15+1 -> 0.92 | EP22: =EP16/EP15+1 -> 0.93 | EQ22: =EQ16/EQ15+1 -> 0.93 | ER22: =ER16/ER15+1 -> 0.93 | ES22: =ES16/ES15+1 -> 0.93 | ET22: =ET16/ET15+1 -> 0.93 | EU22: =EU16/EU15+1 -> 0.93 | ... EX22: =EX16/EX15+1 -> 0.93
B23: Economic Occupancy | E23: =E19/E15 -> 0.9 | F23: =F19/F15 -> 0.89432726 | J23: =J19/J15 -> 0.90432726 | K23: =K19/K15 -> 0.90432726 | L23: =L19/L15 -> 0.90432726 | M23: =M19/M15 -> 0.90432726 | N23: =N19/N15 -> 0.90432726 | O23: =O19/O15 -> 0.90432726 | P23: =P19/P15 -> 0.90432726 | Q23: =Q19/Q15 -> 0.90432726 | ... EK23: =EK19/EK15 -> 0.92432726 | EN23: =EN19/EN15 -> 0.90432726 | EO23: =EO19/EO15 -> 0.91432726 | EP23: =EP19/EP15 -> 0.92432726 | EQ23: =EQ19/EQ15 -> 0.92432726 | ER23: =ER19/ER15 -> 0.92432726 | ES23: =ES19/ES15 -> 0.92432726 | ET23: =ET19/ET15 -> 0.92432726 | EU23: =EU19/EU15 -> 0.92432726 | ... EX23: =EX19/EX15 -> 0.92432726
B25: Utility Reimbursement | E25: =SUM('Historical Financials'!M20:O20)*4 -> 106184 | F25: =SUM('Historical Financials'!D20:O20) -> 99715.74 | J25: ='Inputs & Drivers'!E43/12 -> 8309.645 | K25: =(1+INDEX('Inputs & Drivers'!$J$52:$J$62,MATCH(Model!K$4,'Inputs & Drivers'!$B$52:$B$62,0))*(K$4<>J$4))*J25 -> 8309.645 | L25: =(1+INDEX('Inputs & Drivers'!$J$52:$J$62,MATCH(Model!L$4,'Inputs & Drivers'!$B$52:$B$62,0))*(L$4<>K$4))*K25 -> 8309.645 | M25: =(1+INDEX('Inputs & Drivers'!$J$52:$J$62,MATCH(Model!M$4,'Inputs & Drivers'!$B$52:$B$62,0))*(M$4<>L$4))*L25 -> 8309.645 | N25: =(1+INDEX('Inputs & Drivers'!$J$52:$J$62,MATCH(Model!N$4,'Inputs & Drivers'!$B$52:$B$62,0))*(N$4<>M$4))*M25 -> 8309.645 | O25: =(1+INDEX('Inputs & Drivers'!$J$52:$J$62,MATCH(Model!O$4,'Inputs & Drivers'!$B$52:$B$62,0))*(O$4<>N$4))*N25 -> 8309.645 | P25: =(1+INDEX('Inputs & Drivers'!$J$52:$J$62,MATCH(Model!P$4,'Inputs & Drivers'!$B$52:$B$62,0))*(P$4<>O$4))*O25 -> 8309.645 | Q25: =(1+INDEX('Inputs & Drivers'!$J$52:$J$62,MATCH(Model!Q$4,'Inputs & Drivers'!$B$52:$B$62,0))*(Q$4<>P$4))*P25 -> 8309.645 | R25: =(1+INDEX('Inputs & Drivers'!$J$52:$J$62,MATCH(Model!R$4,'Inputs & Drivers'!$B$52:$B$62,0))*(R$4<>Q$4))*Q25 -> 8309.645 | ... EK25: =(1+INDEX('Inputs & Drivers'!$J$52:$J$62,MATCH(Model!EK$4,'Inputs & Drivers'!$B$52:$B$62,0))*(EK$4<>EJ$4))*EJ25 -> 11167.468 | EM25: =SUMIF($I$4:$EK$4,EM$5,$I25:$EK25) -> 0 | EN25: =SUMIF($I$4:$EK$4,EN$5,$I25:$EK25) -> 99715.74 | EO25: =SUMIF($I$4:$EK$4,EO$5,$I25:$EK25) -> 102707.21 | EP25: =SUMIF($I$4:$EK$4,EP$5,$I25:$EK25) -> 105788.43 | EQ25: =SUMIF($I$4:$EK$4,EQ$5,$I25:$EK25) -> 108962.08 | ER25: =SUMIF($I$4:$EK$4,ER$5,$I25:$EK25) -> 112230.94 | ES25: =SUMIF($I$4:$EK$4,ES$5,$I25:$EK25) -> 115597.87 | ET25: =SUMIF($I$4:$EK$4,ET$5,$I25:$EK25) -> 119065.81 | ... EX25: =SUMIF($I$4:$EK$4,EX$5,$I25:$EK25) -> 134009.62
B26: Other Revenue | E26: =SUM('Historical Financials'!M21:O22)*4 -> 271812 | F26: =SUM('Historical Financials'!D21:O22) -> 263945 | J26: ='Inputs & Drivers'!E44/12 -> 21995.417 | K26: =(1+INDEX('Inputs & Drivers'!$J$52:$J$62,MATCH(Model!K$4,'Inputs & Drivers'!$B$52:$B$62,0))*(K$4<>J$4))*J26 -> 21995.417 | L26: =(1+INDEX('Inputs & Drivers'!$J$52:$J$62,MATCH(Model!L$4,'Inputs & Drivers'!$B$52:$B$62,0))*(L$4<>K$4))*K26 -> 21995.417 | M26: =(1+INDEX('Inputs & Drivers'!$J$52:$J$62,MATCH(Model!M$4,'Inputs & Drivers'!$B$52:$B$62,0))*(M$4<>L$4))*L26 -> 21995.417 | N26: =(1+INDEX('Inputs & Drivers'!$J$52:$J$62,MATCH(Model!N$4,'Inputs & Drivers'!$B$52:$B$62,0))*(N$4<>M$4))*M26 -> 21995.417 | O26: =(1+INDEX('Inputs & Drivers'!$J$52:$J$62,MATCH(Model!O$4,'Inputs & Drivers'!$B$52:$B$62,0))*(O$4<>N$4))*N26 -> 21995.417 | P26: =(1+INDEX('Inputs & Drivers'!$J$52:$J$62,MATCH(Model!P$4,'Inputs & Drivers'!$B$52:$B$62,0))*(P$4<>O$4))*O26 -> 21995.417 | Q26: =(1+INDEX('Inputs & Drivers'!$J$52:$J$62,MATCH(Model!Q$4,'Inputs & Drivers'!$B$52:$B$62,0))*(Q$4<>P$4))*P26 -> 21995.417 | R26: =(1+INDEX('Inputs & Drivers'!$J$52:$J$62,MATCH(Model!R$4,'Inputs & Drivers'!$B$52:$B$62,0))*(R$4<>Q$4))*Q26 -> 21995.417 | ... EK26: =(1+INDEX('Inputs & Drivers'!$J$52:$J$62,MATCH(Model!EK$4,'Inputs & Drivers'!$B$52:$B$62,0))*(EK$4<>EJ$4))*EJ26 -> 29560.001 | EM26: =SUMIF($I$4:$EK$4,EM$5,$I26:$EK26) -> 0 | EN26: =SUMIF($I$4:$EK$4,EN$5,$I26:$EK26) -> 263945 | EO26: =SUMIF($I$4:$EK$4,EO$5,$I26:$EK26) -> 271863.35 | EP26: =SUMIF($I$4:$EK$4,EP$5,$I26:$EK26) -> 280019.25 | EQ26: =SUMIF($I$4:$EK$4,EQ$5,$I26:$EK26) -> 288419.83 | ER26: =SUMIF($I$4:$EK$4,ER$5,$I26:$EK26) -> 297072.42 | ES26: =SUMIF($I$4:$EK$4,ES$5,$I26:$EK26) -> 305984.6 | ET26: =SUMIF($I$4:$EK$4,ET$5,$I26:$EK26) -> 315164.13 | ... EX26: =SUMIF($I$4:$EK$4,EX$5,$I26:$EK26) -> 354720.01
B27: Total Other Revenue | E27: =SUM(E25:E26) -> 377996 | F27: =SUM(F25:F26) -> 363660.74 | J27: =SUM(J25:J26) -> 30305.062 | K27: =SUM(K25:K26) -> 30305.062 | L27: =SUM(L25:L26) -> 30305.062 | M27: =SUM(M25:M26) -> 30305.062 | N27: =SUM(N25:N26) -> 30305.062 | O27: =SUM(O25:O26) -> 30305.062 | P27: =SUM(P25:P26) -> 30305.062 | Q27: =SUM(Q25:Q26) -> 30305.062 | ... EK27: =SUM(EK25:EK26) -> 40727.469 | EM27: =SUM(EM25:EM26) -> 0 | EN27: =SUM(EN25:EN26) -> 363660.74 | EO27: =SUM(EO25:EO26) -> 374570.56 | EP27: =SUM(EP25:EP26) -> 385807.68 | EQ27: =SUM(EQ25:EQ26) -> 397381.91 | ER27: =SUM(ER25:ER26) -> 409303.37 | ES27: =SUM(ES25:ES26) -> 421582.47 | ET27: =SUM(ET25:ET26) -> 434229.94 | ... EX27: =SUM(EX25:EX26) -> 488729.63
B29: TOTAL INCOME | E29: =E19+E27 -> 5846500.8 | F29: =F19+F27 -> 5873969.1 | J29: =J19+J27 -> 494631.93 | K29: =K19+K27 -> 494631.93 | L29: =L19+L27 -> 495809.43 | M29: =M19+M27 -> 496986.94 | N29: =N19+N27 -> 498164.45 | O29: =O19+O27 -> 499341.96 | P29: =P19+P27 -> 500519.47 | Q29: =Q19+Q27 -> 501696.98 | ... EK29: =EK19+EK27 -> 716427.6 | EM29: =EM19+EM27 -> 0 | EN29: =EN19+EN27 -> 6000346.1 | EO29: =EO19+EO27 -> 6336221.3 | EP29: =EP19+EP27 -> 6728315.8 | EQ29: =EQ19+EQ27 -> 6951626.8 | ER29: =ER19+ER27 -> 7152359 | ES29: =ES19+ES27 -> 7359191.7 | ET29: =ET19+ET27 -> 7572310.3 | ... EX29: =EX19+EX27 -> 8491552.9
B31: OPERATING EXPENSES | G31: Per Unit
B32: Repairs & Maintenance | E32: =SUM('Historical Financials'!M28:O28)*4 -> -331980 | F32: =SUM('Historical Financials'!D28:O28) -> -294400 | G32: =-E32/$C$6 -> 1327.92 | J32: =-'Inputs & Drivers'!$J35/12 -> -27665 | K32: =(1+INDEX('Inputs & Drivers'!$G$52:$G$62,MATCH(Model!K$4,'Inputs & Drivers'!$B$52:$B$62,0))*(K$4<>J$4))*J32 -> -27665 | L32: =(1+INDEX('Inputs & Drivers'!$G$52:$G$62,MATCH(Model!L$4,'Inputs & Drivers'!$B$52:$B$62,0))*(L$4<>K$4))*K32 -> -27665 | M32: =(1+INDEX('Inputs & Drivers'!$G$52:$G$62,MATCH(Model!M$4,'Inputs & Drivers'!$B$52:$B$62,0))*(M$4<>L$4))*L32 -> -27665 | N32: =(1+INDEX('Inputs & Drivers'!$G$52:$G$62,MATCH(Model!N$4,'Inputs & Drivers'!$B$52:$B$62,0))*(N$4<>M$4))*M32 -> -27665 | O32: =(1+INDEX('Inputs & Drivers'!$G$52:$G$62,MATCH(Model!O$4,'Inputs & Drivers'!$B$52:$B$62,0))*(O$4<>N$4))*N32 -> -27665 | P32: =(1+INDEX('Inputs & Drivers'!$G$52:$G$62,MATCH(Model!P$4,'Inputs & Drivers'!$B$52:$B$62,0))*(P$4<>O$4))*O32 -> -27665 | Q32: =(1+INDEX('Inputs & Drivers'!$G$52:$G$62,MATCH(Model!Q$4,'Inputs & Drivers'!$B$52:$B$62,0))*(Q$4<>P$4))*P32 -> -27665 | R32: =(1+INDEX('Inputs & Drivers'!$G$52:$G$62,MATCH(Model!R$4,'Inputs & Drivers'!$B$52:$B$62,0))*(R$4<>Q$4))*Q32 -> -27665 | ... EK32: =(1+INDEX('Inputs & Drivers'!$G$52:$G$62,MATCH(Model!EK$4,'Inputs & Drivers'!$B$52:$B$62,0))*(EK$4<>EJ$4))*EJ32 -> -37179.447 | EM32: =SUMIF($I$4:$EK$4,EM$5,$I32:$EK32) -> 0 | EN32: =SUMIF($I$4:$EK$4,EN$5,$I32:$EK32) -> -331980 | EO32: =SUMIF($I$4:$EK$4,EO$5,$I32:$EK32) -> -341939.4 | EP32: =SUMIF($I$4:$EK$4,EP$5,$I32:$EK32) -> -352197.58 | EQ32: =SUMIF($I$4:$EK$4,EQ$5,$I32:$EK32) -> -362763.51 | ER32: =SUMIF($I$4:$EK$4,ER$5,$I32:$EK32) -> -373646.41 | ES32: =SUMIF($I$4:$EK$4,ES$5,$I32:$EK32) -> -384855.81 | ET32: =SUMIF($I$4:$EK$4,ET$5,$I32:$EK32) -> -396401.48 | ... EX32: =SUMIF($I$4:$EK$4,EX$5,$I32:$EK32) -> -446153.36
B33: Turnover | E33: =SUM('Historical Financials'!M29:O29)*4 -> -87912 | F33: =SUM('Historical Financials'!D29:O29) -> -74364 | G33: =-E33/$C$6 -> 351.648 | J33: =-'Inputs & Drivers'!$J36/12 -> -7326 | K33: =(1+INDEX('Inputs & Drivers'!$G$52:$G$62,MATCH(Model!K$4,'Inputs & Drivers'!$B$52:$B$62,0))*(K$4<>J$4))*J33 -> -7326 | L33: =(1+INDEX('Inputs & Drivers'!$G$52:$G$62,MATCH(Model!L$4,'Inputs & Drivers'!$B$52:$B$62,0))*(L$4<>K$4))*K33 -> -7326 | M33: =(1+INDEX('Inputs & Drivers'!$G$52:$G$62,MATCH(Model!M$4,'Inputs & Drivers'!$B$52:$B$62,0))*(M$4<>L$4))*L33 -> -7326 | N33: =(1+INDEX('Inputs & Drivers'!$G$52:$G$62,MATCH(Model!N$4,'Inputs & Drivers'!$B$52:$B$62,0))*(N$4<>M$4))*M33 -> -7326 | O33: =(1+INDEX('Inputs & Drivers'!$G$52:$G$62,MATCH(Model!O$4,'Inputs & Drivers'!$B$52:$B$62,0))*(O$4<>N$4))*N33 -> -7326 | P33: =(1+INDEX('Inputs & Drivers'!$G$52:$G$62,MATCH(Model!P$4,'Inputs & Drivers'!$B$52:$B$62,0))*(P$4<>O$4))*O33 -> -7326 | Q33: =(1+INDEX('Inputs & Drivers'!$G$52:$G$62,MATCH(Model!Q$4,'Inputs & Drivers'!$B$52:$B$62,0))*(Q$4<>P$4))*P33 -> -7326 | R33: =(1+INDEX('Inputs & Drivers'!$G$52:$G$62,MATCH(Model!R$4,'Inputs & Drivers'!$B$52:$B$62,0))*(R$4<>Q$4))*Q33 -> -7326 | ... EK33: =(1+INDEX('Inputs & Drivers'!$G$52:$G$62,MATCH(Model!EK$4,'Inputs & Drivers'!$B$52:$B$62,0))*(EK$4<>EJ$4))*EJ33 -> -9845.5314 | EM33: =SUMIF($I$4:$EK$4,EM$5,$I33:$EK33) -> 0 | EN33: =SUMIF($I$4:$EK$4,EN$5,$I33:$EK33) -> -87912 | EO33: =SUMIF($I$4:$EK$4,EO$5,$I33:$EK33) -> -90549.36 | EP33: =SUMIF($I$4:$EK$4,EP$5,$I33:$EK33) -> -93265.841 | EQ33: =SUMIF($I$4:$EK$4,EQ$5,$I33:$EK33) -> -96063.816 | ER33: =SUMIF($I$4:$EK$4,ER$5,$I33:$EK33) -> -98945.731 | ES33: =SUMIF($I$4:$EK$4,ES$5,$I33:$EK33) -> -101914.1 | ET33: =SUMIF($I$4:$EK$4,ET$5,$I33:$EK33) -> -104971.53 | ... EX33: =SUMIF($I$4:$EK$4,EX$5,$I33:$EK33) -> -118146.38
B34: Marketing | E34: =SUM('Historical Financials'!M30:O30)*4 -> -289628 | F34: =SUM('Historical Financials'!D30:O30) -> -183738 | G34: =-E34/$C$6 -> 1158.512 | J34: =-'Inputs & Drivers'!$J37/12 -> -24135.667 | K34: =(1+INDEX('Inputs & Drivers'!$G$52:$G$62,MATCH(Model!K$4,'Inputs & Drivers'!$B$52:$B$62,0))*(K$4<>J$4))*J34 -> -24135.667 | L34: =(1+INDEX('Inputs & Drivers'!$G$52:$G$62,MATCH(Model!L$4,'Inputs & Drivers'!$B$52:$B$62,0))*(L$4<>K$4))*K34 -> -24135.667 | M34: =(1+INDEX('Inputs & Drivers'!$G$52:$G$62,MATCH(Model!M$4,'Inputs & Drivers'!$B$52:$B$62,0))*(M$4<>L$4))*L34 -> -24135.667 | N34: =(1+INDEX('Inputs & Drivers'!$G$52:$G$62,MATCH(Model!N$4,'Inputs & Drivers'!$B$52:$B$62,0))*(N$4<>M$4))*M34 -> -24135.667 | O34: =(1+INDEX('Inputs & Drivers'!$G$52:$G$62,MATCH(Model!O$4,'Inputs & Drivers'!$B$52:$B$62,0))*(O$4<>N$4))*N34 -> -24135.667 | P34: =(1+INDEX('Inputs & Drivers'!$G$52:$G$62,MATCH(Model!P$4,'Inputs & Drivers'!$B$52:$B$62,0))*(P$4<>O$4))*O34 -> -24135.667 | Q34: =(1+INDEX('Inputs & Drivers'!$G$52:$G$62,MATCH(Model!Q$4,'Inputs & Drivers'!$B$52:$B$62,0))*(Q$4<>P$4))*P34 -> -24135.667 | R34: =(1+INDEX('Inputs & Drivers'!$G$52:$G$62,MATCH(Model!R$4,'Inputs & Drivers'!$B$52:$B$62,0))*(R$4<>Q$4))*Q34 -> -24135.667 | ... EK34: =(1+INDEX('Inputs & Drivers'!$G$52:$G$62,MATCH(Model!EK$4,'Inputs & Drivers'!$B$52:$B$62,0))*(EK$4<>EJ$4))*EJ34 -> -32436.318 | EM34: =SUMIF($I$4:$EK$4,EM$5,$I34:$EK34) -> 0 | EN34: =SUMIF($I$4:$EK$4,EN$5,$I34:$EK34) -> -289628 | EO34: =SUMIF($I$4:$EK$4,EO$5,$I34:$EK34) -> -298316.84 | EP34: =SUMIF($I$4:$EK$4,EP$5,$I34:$EK34) -> -307266.35 | EQ34: =SUMIF($I$4:$EK$4,EQ$5,$I34:$EK34) -> -316484.34 | ER34: =SUMIF($I$4:$EK$4,ER$5,$I34:$EK34) -> -325978.87 | ES34: =SUMIF($I$4:$EK$4,ES$5,$I34:$EK34) -> -335758.23 | ET34: =SUMIF($I$4:$EK$4,ET$5,$I34:$EK34) -> -345830.98 | ... EX34: =SUMIF($I$4:$EK$4,EX$5,$I34:$EK34) -> -389235.81
B35: General & Administrative | E35: =SUM('Historical Financials'!M31:O31)*4 -> -70136 | F35: =SUM('Historical Financials'!D31:O31) -> -59547 | G35: =-E35/$C$6 -> 280.544 | J35: =-'Inputs & Drivers'!$J38/12 -> -5844.6667 | K35: =(1+INDEX('Inputs & Drivers'!$G$52:$G$62,MATCH(Model!K$4,'Inputs & Drivers'!$B$52:$B$62,0))*(K$4<>J$4))*J35 -> -5844.6667 | L35: =(1+INDEX('Inputs & Drivers'!$G$52:$G$62,MATCH(Model!L$4,'Inputs & Drivers'!$B$52:$B$62,0))*(L$4<>K$4))*K35 -> -5844.6667 | M35: =(1+INDEX('Inputs & Drivers'!$G$52:$G$62,MATCH(Model!M$4,'Inputs & Drivers'!$B$52:$B$62,0))*(M$4<>L$4))*L35 -> -5844.6667 | N35: =(1+INDEX('Inputs & Drivers'!$G$52:$G$62,MATCH(Model!N$4,'Inputs & Drivers'!$B$52:$B$62,0))*(N$4<>M$4))*M35 -> -5844.6667 | O35: =(1+INDEX('Inputs & Drivers'!$G$52:$G$62,MATCH(Model!O$4,'Inputs & Drivers'!$B$52:$B$62,0))*(O$4<>N$4))*N35 -> -5844.6667 | P35: =(1+INDEX('Inputs & Drivers'!$G$52:$G$62,MATCH(Model!P$4,'Inputs & Drivers'!$B$52:$B$62,0))*(P$4<>O$4))*O35 -> -5844.6667 | Q35: =(1+INDEX('Inputs & Drivers'!$G$52:$G$62,MATCH(Model!Q$4,'Inputs & Drivers'!$B$52:$B$62,0))*(Q$4<>P$4))*P35 -> -5844.6667 | R35: =(1+INDEX('Inputs & Drivers'!$G$52:$G$62,MATCH(Model!R$4,'Inputs & Drivers'!$B$52:$B$62,0))*(R$4<>Q$4))*Q35 -> -5844.6667 | ... EK35: =(1+INDEX('Inputs & Drivers'!$G$52:$G$62,MATCH(Model!EK$4,'Inputs & Drivers'!$B$52:$B$62,0))*(EK$4<>EJ$4))*EJ35 -> -7854.7433 | EM35: =SUMIF($I$4:$EK$4,EM$5,$I35:$EK35) -> 0 | EN35: =SUMIF($I$4:$EK$4,EN$5,$I35:$EK35) -> -70136 | EO35: =SUMIF($I$4:$EK$4,EO$5,$I35:$EK35) -> -72240.08 | EP35: =SUMIF($I$4:$EK$4,EP$5,$I35:$EK35) -> -74407.282 | EQ35: =SUMIF($I$4:$EK$4,EQ$5,$I35:$EK35) -> -76639.501 | ER35: =SUMIF($I$4:$EK$4,ER$5,$I35:$EK35) -> -78938.686 | ES35: =SUMIF($I$4:$EK$4,ES$5,$I35:$EK35) -> -81306.846 | ET35: =SUMIF($I$4:$EK$4,ET$5,$I35:$EK35) -> -83746.052 | ... EX35: =SUMIF($I$4:$EK$4,EX$5,$I35:$EK35) -> -94256.919
B36: Payroll | E36: =SUM('Historical Financials'!M32:O32)*4 -> -379892 | F36: =SUM('Historical Financials'!D32:O32) -> -404335 | G36: =-E36/$C$6 -> 1519.568 | J36: =-'Inputs & Drivers'!$J39/12 -> -31657.667 | K36: =(1+INDEX('Inputs & Drivers'!$G$52:$G$62,MATCH(Model!K$4,'Inputs & Drivers'!$B$52:$B$62,0))*(K$4<>J$4))*J36 -> -31657.667 | L36: =(1+INDEX('Inputs & Drivers'!$G$52:$G$62,MATCH(Model!L$4,'Inputs & Drivers'!$B$52:$B$62,0))*(L$4<>K$4))*K36 -> -31657.667 | M36: =(1+INDEX('Inputs & Drivers'!$G$52:$G$62,MATCH(Model!M$4,'Inputs & Drivers'!$B$52:$B$62,0))*(M$4<>L$4))*L36 -> -31657.667 | N36: =(1+INDEX('Inputs & Drivers'!$G$52:$G$62,MATCH(Model!N$4,'Inputs & Drivers'!$B$52:$B$62,0))*(N$4<>M$4))*M36 -> -31657.667 | O36: =(1+INDEX('Inputs & Drivers'!$G$52:$G$62,MATCH(Model!O$4,'Inputs & Drivers'!$B$52:$B$62,0))*(O$4<>N$4))*N36 -> -31657.667 | P36: =(1+INDEX('Inputs & Drivers'!$G$52:$G$62,MATCH(Model!P$4,'Inputs & Drivers'!$B$52:$B$62,0))*(P$4<>O$4))*O36 -> -31657.667 | Q36: =(1+INDEX('Inputs & Drivers'!$G$52:$G$62,MATCH(Model!Q$4,'Inputs & Drivers'!$B$52:$B$62,0))*(Q$4<>P$4))*P36 -> -31657.667 | R36: =(1+INDEX('Inputs & Drivers'!$G$52:$G$62,MATCH(Model!R$4,'Inputs & Drivers'!$B$52:$B$62,0))*(R$4<>Q$4))*Q36 -> -31657.667 | ... EK36: =(1+INDEX('Inputs & Drivers'!$G$52:$G$62,MATCH(Model!EK$4,'Inputs & Drivers'!$B$52:$B$62,0))*(EK$4<>EJ$4))*EJ36 -> -42545.257 | EM36: =SUMIF($I$4:$EK$4,EM$5,$I36:$EK36) -> 0 | EN36: =SUMIF($I$4:$EK$4,EN$5,$I36:$EK36) -> -379892 | EO36: =SUMIF($I$4:$EK$4,EO$5,$I36:$EK36) -> -391288.76 | EP36: =SUMIF($I$4:$EK$4,EP$5,$I36:$EK36) -> -403027.42 | EQ36: =SUMIF($I$4:$EK$4,EQ$5,$I36:$EK36) -> -415118.25 | ER36: =SUMIF($I$4:$EK$4,ER$5,$I36:$EK36) -> -427571.79 | ES36: =SUMIF($I$4:$EK$4,ES$5,$I36:$EK36) -> -440398.95 | ET36: =SUMIF($I$4:$EK$4,ET$5,$I36:$EK36) -> -453610.92 | ... EX36: =SUMIF($I$4:$EK$4,EX$5,$I36:$EK36) -> -510543.08
B37: Management Fees | E37: =SUM('Historical Financials'!M33:O33)*4 -> -164055.14 | F37: =SUM('Historical Financials'!D33:O33) -> -165309.25 | G37: =-E37/$C$6 -> 656.22057 | J37: =-'Inputs & Drivers'!$H$40*J19 -> -13824.128 | K37: =-'Inputs & Drivers'!$H$40*K19 -> -13824.128 | L37: =-'Inputs & Drivers'!$H$40*L19 -> -13859.186 | M37: =-'Inputs & Drivers'!$H$40*M19 -> -13894.243 | N37: =-'Inputs & Drivers'!$H$40*N19 -> -13929.3 | O37: =-'Inputs & Drivers'!$H$40*O19 -> -13964.357 | P37: =-'Inputs & Drivers'!$H$40*P19 -> -13999.415 | Q37: =-'Inputs & Drivers'!$H$40*Q19 -> -14034.472 | ... EK37: =-'Inputs & Drivers'!$H$40*EK19 -> -20117.219 | EM37: =SUMIF($I$4:$EK$4,EM$5,$I37:$EK37) -> 0 | EN37: =SUMIF($I$4:$EK$4,EN$5,$I37:$EK37) -> -167817.69 | EO37: =SUMIF($I$4:$EK$4,EO$5,$I37:$EK37) -> -177492.69 | EP37: =SUMIF($I$4:$EK$4,EP$5,$I37:$EK37) -> -188831.73 | EQ37: =SUMIF($I$4:$EK$4,EQ$5,$I37:$EK37) -> -195135.64 | ER37: =SUMIF($I$4:$EK$4,ER$5,$I37:$EK37) -> -200757 | ES37: =SUMIF($I$4:$EK$4,ES$5,$I37:$EK37) -> -206549.33 | ET37: =SUMIF($I$4:$EK$4,ET$5,$I37:$EK37) -> -212517.83 | ... EX37: =SUMIF($I$4:$EK$4,EX$5,$I37:$EK37) -> -238263.31
B38: Utilities | E38: =SUM('Historical Financials'!M34:O34)*4 -> -145568 | F38: =SUM('Historical Financials'!D34:O34) -> -149581.28 | G38: =-E38/$C$6 -> 582.272 | J38: =-'Inputs & Drivers'!$J41/12 -> -12130.667 | K38: =(1+INDEX('Inputs & Drivers'!$G$52:$G$62,MATCH(Model!K$4,'Inputs & Drivers'!$B$52:$B$62,0))*(K$4<>J$4))*J38 -> -12130.667 | L38: =(1+INDEX('Inputs & Drivers'!$G$52:$G$62,MATCH(Model!L$4,'Inputs & Drivers'!$B$52:$B$62,0))*(L$4<>K$4))*K38 -> -12130.667 | M38: =(1+INDEX('Inputs & Drivers'!$G$52:$G$62,MATCH(Model!M$4,'Inputs & Drivers'!$B$52:$B$62,0))*(M$4<>L$4))*L38 -> -12130.667 | N38: =(1+INDEX('Inputs & Drivers'!$G$52:$G$62,MATCH(Model!N$4,'Inputs & Drivers'!$B$52:$B$62,0))*(N$4<>M$4))*M38 -> -12130.667 | O38: =(1+INDEX('Inputs & Drivers'!$G$52:$G$62,MATCH(Model!O$4,'Inputs & Drivers'!$B$52:$B$62,0))*(O$4<>N$4))*N38 -> -12130.667 | P38: =(1+INDEX('Inputs & Drivers'!$G$52:$G$62,MATCH(Model!P$4,'Inputs & Drivers'!$B$52:$B$62,0))*(P$4<>O$4))*O38 -> -12130.667 | Q38: =(1+INDEX('Inputs & Drivers'!$G$52:$G$62,MATCH(Model!Q$4,'Inputs & Drivers'!$B$52:$B$62,0))*(Q$4<>P$4))*P38 -> -12130.667 | R38: =(1+INDEX('Inputs & Drivers'!$G$52:$G$62,MATCH(Model!R$4,'Inputs & Drivers'!$B$52:$B$62,0))*(R$4<>Q$4))*Q38 -> -12130.667 | ... EK38: =(1+INDEX('Inputs & Drivers'!$G$52:$G$62,MATCH(Model!EK$4,'Inputs & Drivers'!$B$52:$B$62,0))*(EK$4<>EJ$4))*EJ38 -> -16302.602 | EM38: =SUMIF($I$4:$EK$4,EM$5,$I38:$EK38) -> 0 | EN38: =SUMIF($I$4:$EK$4,EN$5,$I38:$EK38) -> -145568 | EO38: =SUMIF($I$4:$EK$4,EO$5,$I38:$EK38) -> -149935.04 | EP38: =SUMIF($I$4:$EK$4,EP$5,$I38:$EK38) -> -154433.09 | EQ38: =SUMIF($I$4:$EK$4,EQ$5,$I38:$EK38) -> -159066.08 | ER38: =SUMIF($I$4:$EK$4,ER$5,$I38:$EK38) -> -163838.07 | ES38: =SUMIF($I$4:$EK$4,ES$5,$I38:$EK38) -> -168753.21 | ET38: =SUMIF($I$4:$EK$4,ET$5,$I38:$EK38) -> -173815.8 | ... EX38: =SUMIF($I$4:$EK$4,EX$5,$I38:$EK38) -> -195631.22
B39: Real Estate Taxes | E39: =SUM('Historical Financials'!M35:O35)*4 -> -1638504 | F39: =SUM('Historical Financials'!D35:O35) -> -1638504 | G39: =-E39/$C$6 -> 6554.016 | J39: =-'Inputs & Drivers'!$J42/12 -> -136542 | K39: =(1+INDEX('Inputs & Drivers'!$H$52:$H$62,MATCH(Model!K$4,'Inputs & Drivers'!$B$52:$B$62,0))*(K$4<>J$4))*J39 -> -136542 | L39: =(1+INDEX('Inputs & Drivers'!$H$52:$H$62,MATCH(Model!L$4,'Inputs & Drivers'!$B$52:$B$62,0))*(L$4<>K$4))*K39 -> -136542 | M39: =(1+INDEX('Inputs & Drivers'!$H$52:$H$62,MATCH(Model!M$4,'Inputs & Drivers'!$B$52:$B$62,0))*(M$4<>L$4))*L39 -> -136542 | N39: =(1+INDEX('Inputs & Drivers'!$H$52:$H$62,MATCH(Model!N$4,'Inputs & Drivers'!$B$52:$B$62,0))*(N$4<>M$4))*M39 -> -136542 | O39: =(1+INDEX('Inputs & Drivers'!$H$52:$H$62,MATCH(Model!O$4,'Inputs & Drivers'!$B$52:$B$62,0))*(O$4<>N$4))*N39 -> -136542 | P39: =(1+INDEX('Inputs & Drivers'!$H$52:$H$62,MATCH(Model!P$4,'Inputs & Drivers'!$B$52:$B$62,0))*(P$4<>O$4))*O39 -> -136542 | Q39: =(1+INDEX('Inputs & Drivers'!$H$52:$H$62,MATCH(Model!Q$4,'Inputs & Drivers'!$B$52:$B$62,0))*(Q$4<>P$4))*P39 -> -136542 | R39: =(1+INDEX('Inputs & Drivers'!$H$52:$H$62,MATCH(Model!R$4,'Inputs & Drivers'!$B$52:$B$62,0))*(R$4<>Q$4))*Q39 -> -136542 | ... EK39: =(1+INDEX('Inputs & Drivers'!$H$52:$H$62,MATCH(Model!EK$4,'Inputs & Drivers'!$B$52:$B$62,0))*(EK$4<>EJ$4))*EJ39 -> -166443.94 | EM39: =SUMIF($I$4:$EK$4,EM$5,$I39:$EK39) -> 0 | EN39: =SUMIF($I$4:$EK$4,EN$5,$I39:$EK39) -> -1638504 | EO39: =SUMIF($I$4:$EK$4,EO$5,$I39:$EK39) -> -1671274.1 | EP39: =SUMIF($I$4:$EK$4,EP$5,$I39:$EK39) -> -1704699.6 | EQ39: =SUMIF($I$4:$EK$4,EQ$5,$I39:$EK39) -> -1738793.6 | ER39: =SUMIF($I$4:$EK$4,ER$5,$I39:$EK39) -> -1773569.4 | ES39: =SUMIF($I$4:$EK$4,ES$5,$I39:$EK39) -> -1809040.8 | ET39: =SUMIF($I$4:$EK$4,ET$5,$I39:$EK39) -> -1845221.6 | ... EX39: =SUMIF($I$4:$EK$4,EX$5,$I39:$EK39) -> -1997327.2
B40: Property Insurance | E40: =SUM('Historical Financials'!M36:O36)*4 -> -88112 | F40: =SUM('Historical Financials'!D36:O36) -> -83921 | G40: =-E40/$C$6 -> 352.448 | J40: =-'Inputs & Drivers'!$J43/12 -> -7342.6667 | K40: =(1+INDEX('Inputs & Drivers'!$G$52:$G$62,MATCH(Model!K$4,'Inputs & Drivers'!$B$52:$B$62,0))*(K$4<>J$4))*J40 -> -7342.6667 | L40: =(1+INDEX('Inputs & Drivers'!$G$52:$G$62,MATCH(Model!L$4,'Inputs & Drivers'!$B$52:$B$62,0))*(L$4<>K$4))*K40 -> -7342.6667 | M40: =(1+INDEX('Inputs & Drivers'!$G$52:$G$62,MATCH(Model!M$4,'Inputs & Drivers'!$B$52:$B$62,0))*(M$4<>L$4))*L40 -> -7342.6667 | N40: =(1+INDEX('Inputs & Drivers'!$G$52:$G$62,MATCH(Model!N$4,'Inputs & Drivers'!$B$52:$B$62,0))*(N$4<>M$4))*M40 -> -7342.6667 | O40: =(1+INDEX('Inputs & Drivers'!$G$52:$G$62,MATCH(Model!O$4,'Inputs & Drivers'!$B$52:$B$62,0))*(O$4<>N$4))*N40 -> -7342.6667 | P40: =(1+INDEX('Inputs & Drivers'!$G$52:$G$62,MATCH(Model!P$4,'Inputs & Drivers'!$B$52:$B$62,0))*(P$4<>O$4))*O40 -> -7342.6667 | Q40: =(1+INDEX('Inputs & Drivers'!$G$52:$G$62,MATCH(Model!Q$4,'Inputs & Drivers'!$B$52:$B$62,0))*(Q$4<>P$4))*P40 -> -7342.6667 | R40: =(1+INDEX('Inputs & Drivers'!$G$52:$G$62,MATCH(Model!R$4,'Inputs & Drivers'!$B$52:$B$62,0))*(R$4<>Q$4))*Q40 -> -7342.6667 | ... EK40: =(1+INDEX('Inputs & Drivers'!$G$52:$G$62,MATCH(Model!EK$4,'Inputs & Drivers'!$B$52:$B$62,0))*(EK$4<>EJ$4))*EJ40 -> -9867.93 | EM40: =SUMIF($I$4:$EK$4,EM$5,$I40:$EK40) -> 0 | EN40: =SUMIF($I$4:$EK$4,EN$5,$I40:$EK40) -> -88112 | EO40: =SUMIF($I$4:$EK$4,EO$5,$I40:$EK40) -> -90755.36 | EP40: =SUMIF($I$4:$EK$4,EP$5,$I40:$EK40) -> -93478.021 | EQ40: =SUMIF($I$4:$EK$4,EQ$5,$I40:$EK40) -> -96282.361 | ER40: =SUMIF($I$4:$EK$4,ER$5,$I40:$EK40) -> -99170.832 | ES40: =SUMIF($I$4:$EK$4,ES$5,$I40:$EK40) -> -102145.96 | ET40: =SUMIF($I$4:$EK$4,ET$5,$I40:$EK40) -> -105210.34 | ... EX40: =SUMIF($I$4:$EK$4,EX$5,$I40:$EK40) -> -118415.16
B41: Replacement Reserve | E41: 0 | F41: 0 | G41: =-E41/$C$6 -> 0 | J41: =-'Inputs & Drivers'!J45/12 -> -5208.3333 | K41: =J41 -> -5208.3333 | L41: =K41 -> -5208.3333 | M41: =L41 -> -5208.3333 | N41: =M41 -> -5208.3333 | O41: =N41 -> -5208.3333 | P41: =O41 -> -5208.3333 | Q41: =P41 -> -5208.3333 | R41: =Q41 -> -5208.3333 | ... EK41: =EJ41 -> -5208.3333 | EM41: =SUMIF($I$4:$EK$4,EM$5,$I41:$EK41) -> 0 | EN41: =SUMIF($I$4:$EK$4,EN$5,$I41:$EK41) -> -62500 | EO41: =SUMIF($I$4:$EK$4,EO$5,$I41:$EK41) -> -62500 | EP41: =SUMIF($I$4:$EK$4,EP$5,$I41:$EK41) -> -62500 | EQ41: =SUMIF($I$4:$EK$4,EQ$5,$I41:$EK41) -> -62500 | ER41: =SUMIF($I$4:$EK$4,ER$5,$I41:$EK41) -> -62500 | ES41: =SUMIF($I$4:$EK$4,ES$5,$I41:$EK41) -> -62500 | ET41: =SUMIF($I$4:$EK$4,ET$5,$I41:$EK41) -> -62500 | ... EX41: =SUMIF($I$4:$EK$4,EX$5,$I41:$EK41) -> -62500
B42: TOTAL OPERATING EXPENSES | E42: =SUM(E32:E41) -> -3195787.1 | F42: =SUM(F32:F41) -> -3053699.5 | G42: =SUM(G32:G41) -> 12783.149 | J42: =SUM(J32:J41) -> -271676.79 | K42: =SUM(K32:K41) -> -271676.79 | L42: =SUM(L32:L41) -> -271711.85 | M42: =SUM(M32:M41) -> -271746.91 | N42: =SUM(N32:N41) -> -271781.97 | O42: =SUM(O32:O41) -> -271817.02 | P42: =SUM(P32:P41) -> -271852.08 | Q42: =SUM(Q32:Q41) -> -271887.14 | ... EK42: =SUM(EK32:EK41) -> -347801.32 | EM42: =SUM(EM32:EM41) -> 0 | EN42: =SUM(EN32:EN41) -> -3262049.7 | EO42: =SUM(EO32:EO41) -> -3346291.6 | EP42: =SUM(EP32:EP41) -> -3434106.9 | EQ42: =SUM(EQ32:EQ41) -> -3518847.1 | ER42: =SUM(ER32:ER41) -> -3604916.8 | ES42: =SUM(ES32:ES41) -> -3693223.2 | ET42: =SUM(ET32:ET41) -> -3783826.6 | ... EX42: =SUM(EX32:EX41) -> -4170472.5
B44: NET OPERATING INCOME | E44: =E29+E42 -> 2650713.6 | F44: =F29+F42 -> 2820269.6 | J44: =J29+J42 -> 222955.13 | K44: =K29+K42 -> 222955.13 | L44: =L29+L42 -> 224097.58 | M44: =M29+M42 -> 225240.03 | N44: =N29+N42 -> 226382.49 | O44: =O29+O42 -> 227524.94 | P44: =P29+P42 -> 228667.39 | Q44: =Q29+Q42 -> 229809.84 | ... EK44: =EK29+EK42 -> 368626.29 | EM44: =EM29+EM42 -> 0 | EN44: =EN29+EN42 -> 2738296.4 | EO44: =EO29+EO42 -> 2989929.7 | EP44: =EP29+EP42 -> 3294209 | EQ44: =EQ29+EQ42 -> 3432779.7 | ER44: =ER29+ER42 -> 3547442.2 | ES44: =ES29+ES42 -> 3665968.5 | ET44: =ET29+ET42 -> 3788483.8 | ... EX44: =EX29+EX42 -> 4321080.4
B45: Forward 12 Month NOI | J45: =SUM(K44:V44) -> 2751818 | K45: =SUM(L44:W44) -> 2767636.1 | L45: =SUM(M44:X44) -> 2784611.3 | M45: =SUM(N44:Y44) -> 2802746.5 | N45: =SUM(O44:Z44) -> 2822044.4 | O45: =SUM(P44:AA44) -> 2842507.9 | P45: =SUM(Q44:AB44) -> 2864140 | Q45: =SUM(R44:AC44) -> 2886943.5 | ... EK45: =SUM(EL44:EW44) -> 35599505
B46: Margin | E46: =E44/E29 -> 0.45338464 | F46: =F44/F29 -> 0.48013013 | J46: =J44/J29 -> 0.45074958 | K46: =K44/K29 -> 0.45074958 | L46: =L44/L29 -> 0.4519833 | M46: =M44/M29 -> 0.45321117 | N46: =N44/N29 -> 0.45443324 | O46: =O44/O29 -> 0.45564955 | P46: =P44/P29 -> 0.45686013 | Q46: =Q44/Q29 -> 0.45806503 | ... EK46: =EK44/EK29 -> 0.5145339 | EN46: =EN44/EN29 -> 0.45635641 | EO46: =EO44/EO29 -> 0.47187899 | EP46: =EP44/EP29 -> 0.48960379 | EQ46: =EQ44/EQ29 -> 0.49380955 | ER46: =ER44/ER29 -> 0.49598212 | ES46: =ES44/ES29 -> 0.49814825 | ET46: =ET44/ET29 -> 0.50030752 | EU46: =EU44/EU29 -> 0.50245952 | ... EX46: =EX44/EX29 -> 0.5088681
B47: Yield-on-Cost | J47: =(J44*12)/J99 -> 0.051590329 | K47: =(K44*12)/K99 -> 0.051546843 | L47: =(L44*12)/L99 -> 0.051702026 | M47: =(M44*12)/M99 -> 0.051856557 | N47: =(N44*12)/N99 -> 0.052010441 | O47: =(O44*12)/O99 -> 0.052163682 | P47: =(P44*12)/P99 -> 0.052359958 | Q47: =(Q44*12)/Q99 -> 0.052555744 | ... EK47: =(EK44*12)/EK99 -> 0.082445981 | EN47: =EN44/EN99 -> 0.051925845 | EO47: =EO44/EO99 -> 0.055863304 | EP47: =EP44/EP99 -> 0.061397839 | EQ47: =EQ44/EQ99 -> 0.063980536 | ER47: =ER44/ER99 -> 0.066117628 | ES47: =ES44/ES99 -> 0.068326735 | ET47: =ET44/ET99 -> 0.070610189 | EU47: =EU44/EU99 -> 0.072970399 | ... EX47: =EX44/EX99 -> 0.080536786
B49: CAPITAL EXPENDITURES
B50: Defensive Renovations | J50: =-('Inputs & Drivers'!$E$22/'Inputs & Drivers'!$E$67)*(J$6>='Inputs & Drivers'!$C$67)*(J$6<'Inputs & Drivers'!$D$67) -> -43750 | K50: =-('Inputs & Drivers'!$E$22/'Inputs & Drivers'!$E$67)*(K$6>='Inputs & Drivers'!$C$67)*(K$6<'Inputs & Drivers'!$D$67) -> -43750 | L50: =-('Inputs & Drivers'!$E$22/'Inputs & Drivers'!$E$67)*(L$6>='Inputs & Drivers'!$C$67)*(L$6<'Inputs & Drivers'!$D$67) -> -43750 | M50: =-('Inputs & Drivers'!$E$22/'Inputs & Drivers'!$E$67)*(M$6>='Inputs & Drivers'!$C$67)*(M$6<'Inputs & Drivers'!$D$67) -> -43750 | N50: =-('Inputs & Drivers'!$E$22/'Inputs & Drivers'!$E$67)*(N$6>='Inputs & Drivers'!$C$67)*(N$6<'Inputs & Drivers'!$D$67) -> -43750 | O50: =-('Inputs & Drivers'!$E$22/'Inputs & Drivers'!$E$67)*(O$6>='Inputs & Drivers'!$C$67)*(O$6<'Inputs & Drivers'!$D$67) -> -43750 | P50: =-('Inputs & Drivers'!$E$22/'Inputs & Drivers'!$E$67)*(P$6>='Inputs & Drivers'!$C$67)*(P$6<'Inputs & Drivers'!$D$67) -> 0 | Q50: =-('Inputs & Drivers'!$E$22/'Inputs & Drivers'!$E$67)*(Q$6>='Inputs & Drivers'!$C$67)*(Q$6<'Inputs & Drivers'!$D$67) -> 0 | ... EK50: =-('Inputs & Drivers'!$E$22/'Inputs & Drivers'!$E$67)*(EK$6>='Inputs & Drivers'!$C$67)*(EK$6<'Inputs & Drivers'!$D$67) -> 0 | EM50: =SUMIF($I$4:$EK$4,EM$5,$I50:$EK50) -> 0 | EN50: =SUMIF($I$4:$EK$4,EN$5,$I50:$EK50) -> -262500 | EO50: =SUMIF($I$4:$EK$4,EO$5,$I50:$EK50) -> 0 | EP50: =SUMIF($I$4:$EK$4,EP$5,$I50:$EK50) -> 0 | EQ50: =SUMIF($I$4:$EK$4,EQ$5,$I50:$EK50) -> 0 | ER50: =SUMIF($I$4:$EK$4,ER$5,$I50:$EK50) -> 0 | ES50: =SUMIF($I$4:$EK$4,ES$5,$I50:$EK50) -> 0 | ET50: =SUMIF($I$4:$EK$4,ET$5,$I50:$EK50) -> 0 | ... EX50: =SUMIF($I$4:$EK$4,EX$5,$I50:$EK50) -> 0
B51: Offensive Renovations | J51: =-('Inputs & Drivers'!$E$27/'Inputs & Drivers'!$E$68)*(J$6>='Inputs & Drivers'!$C$68)*(J$6<'Inputs & Drivers'!$D$68) -> 0 | K51: =-('Inputs & Drivers'!$E$27/'Inputs & Drivers'!$E$68)*(K$6>='Inputs & Drivers'!$C$68)*(K$6<'Inputs & Drivers'!$D$68) -> 0 | L51: =-('Inputs & Drivers'!$E$27/'Inputs & Drivers'!$E$68)*(L$6>='Inputs & Drivers'!$C$68)*(L$6<'Inputs & Drivers'!$D$68) -> -65625 | M51: =-('Inputs & Drivers'!$E$27/'Inputs & Drivers'!$E$68)*(M$6>='Inputs & Drivers'!$C$68)*(M$6<'Inputs & Drivers'!$D$68) -> -65625 | N51: =-('Inputs & Drivers'!$E$27/'Inputs & Drivers'!$E$68)*(N$6>='Inputs & Drivers'!$C$68)*(N$6<'Inputs & Drivers'!$D$68) -> -65625 | O51: =-('Inputs & Drivers'!$E$27/'Inputs & Drivers'!$E$68)*(O$6>='Inputs & Drivers'!$C$68)*(O$6<'Inputs & Drivers'!$D$68) -> -65625 | P51: =-('Inputs & Drivers'!$E$27/'Inputs & Drivers'!$E$68)*(P$6>='Inputs & Drivers'!$C$68)*(P$6<'Inputs & Drivers'!$D$68) -> -65625 | Q51: =-('Inputs & Drivers'!$E$27/'Inputs & Drivers'!$E$68)*(Q$6>='Inputs & Drivers'!$C$68)*(Q$6<'Inputs & Drivers'!$D$68) -> -65625 | ... EK51: =-('Inputs & Drivers'!$E$27/'Inputs & Drivers'!$E$68)*(EK$6>='Inputs & Drivers'!$C$68)*(EK$6<'Inputs & Drivers'!$D$68) -> 0 | EM51: =SUMIF($I$4:$EK$4,EM$5,$I51:$EK51) -> 0 | EN51: =SUMIF($I$4:$EK$4,EN$5,$I51:$EK51) -> -656250 | EO51: =SUMIF($I$4:$EK$4,EO$5,$I51:$EK51) -> -787500 | EP51: =SUMIF($I$4:$EK$4,EP$5,$I51:$EK51) -> -131250 | EQ51: =SUMIF($I$4:$EK$4,EQ$5,$I51:$EK51) -> 0 | ER51: =SUMIF($I$4:$EK$4,ER$5,$I51:$EK51) -> 0 | ES51: =SUMIF($I$4:$EK$4,ES$5,$I51:$EK51) -> 0 | ET51: =SUMIF($I$4:$EK$4,ET$5,$I51:$EK51) -> 0 | ... EX51: =SUMIF($I$4:$EK$4,EX$5,$I51:$EK51) -> 0
B52: TOTAL CAPITAL EXPENDITURES | J52: =SUM(J50:J51) -> -43750 | K52: =SUM(K50:K51) -> -43750 | L52: =SUM(L50:L51) -> -109375 | M52: =SUM(M50:M51) -> -109375 | N52: =SUM(N50:N51) -> -109375 | O52: =SUM(O50:O51) -> -109375 | P52: =SUM(P50:P51) -> -65625 | Q52: =SUM(Q50:Q51) -> -65625 | ... EK52: =SUM(EK50:EK51) -> 0 | EM52: =SUM(EM50:EM51) -> 0 | EN52: =SUM(EN50:EN51) -> -918750 | EO52: =SUM(EO50:EO51) -> -787500 | EP52: =SUM(EP50:EP51) -> -131250 | EQ52: =SUM(EQ50:EQ51) -> 0 | ER52: =SUM(ER50:ER51) -> 0 | ES52: =SUM(ES50:ES51) -> 0 | ET52: =SUM(ET50:ET51) -> 0 | ... EX52: =SUM(EX50:EX51) -> 0
B54: OPERATING CASH FLOW | J54: =(J44+J52)*(J$6<=$C$5) -> 179205.13 | K54: =(K44+K52)*(K$6<=$C$5) -> 179205.13 | L54: =(L44+L52)*(L$6<=$C$5) -> 114722.58 | M54: =(M44+M52)*(M$6<=$C$5) -> 115865.03 | N54: =(N44+N52)*(N$6<=$C$5) -> 117007.49 | O54: =(O44+O52)*(O$6<=$C$5) -> 118149.94 | P54: =(P44+P52)*(P$6<=$C$5) -> 163042.39 | Q54: =(Q44+Q52)*(Q$6<=$C$5) -> 164184.84 | ... EK54: =(EK44+EK52)*(EK$6<=$C$5) -> 0 | EM54: =(EM44+EM52)*(EM$6<=$C$5) -> 0 | EN54: =(EN44+EN52)*(EN$6<=$C$5) -> 1819546.4 | EO54: =(EO44+EO52)*(EO$6<=$C$5) -> 2202429.7 | EP54: =(EP44+EP52)*(EP$6<=$C$5) -> 3162959 | EQ54: =(EQ44+EQ52)*(EQ$6<=$C$5) -> 3432779.7 | ER54: =(ER44+ER52)*(ER$6<=$C$5) -> 3547442.2 | ES54: =(ES44+ES52)*(ES$6<=$C$5) -> 0 | ET54: =(ET44+ET52)*(ET$6<=$C$5) -> 0 | ... EX54: =(EX44+EX52)*(EX$6<=$C$5) -> 0
B56: ACQUISITION & SALE
B57: Purchase Price | I57: =-'Inputs & Drivers'!$E$14*(I$6='Inputs & Drivers'!$E$12) -> -51000000 | J57: =-'Inputs & Drivers'!$E$14*(J$6='Inputs & Drivers'!$E$12) -> 0 | K57: =-'Inputs & Drivers'!$E$14*(K$6='Inputs & Drivers'!$E$12) -> 0 | L57: =-'Inputs & Drivers'!$E$14*(L$6='Inputs & Drivers'!$E$12) -> 0 | M57: =-'Inputs & Drivers'!$E$14*(M$6='Inputs & Drivers'!$E$12) -> 0 | N57: =-'Inputs & Drivers'!$E$14*(N$6='Inputs & Drivers'!$E$12) -> 0 | O57: =-'Inputs & Drivers'!$E$14*(O$6='Inputs & Drivers'!$E$12) -> 0 | P57: =-'Inputs & Drivers'!$E$14*(P$6='Inputs & Drivers'!$E$12) -> 0 | ... EK57: =-'Inputs & Drivers'!$E$14*(EK$6='Inputs & Drivers'!$E$12) -> 0 | EM57: =SUMIF($I$4:$EK$4,EM$5,$I57:$EK57) -> -51000000 | EN57: =SUMIF($I$4:$EK$4,EN$5,$I57:$EK57) -> 0 | EO57: =SUMIF($I$4:$EK$4,EO$5,$I57:$EK57) -> 0 | EP57: =SUMIF($I$4:$EK$4,EP$5,$I57:$EK57) -> 0 | EQ57: =SUMIF($I$4:$EK$4,EQ$5,$I57:$EK57) -> 0 | ER57: =SUMIF($I$4:$EK$4,ER$5,$I57:$EK57) -> 0 | ES57: =SUMIF($I$4:$EK$4,ES$5,$I57:$EK57) -> 0 | ET57: =SUMIF($I$4:$EK$4,ET$5,$I57:$EK57) -> 0 | ... EX57: =SUMIF($I$4:$EK$4,EX$5,$I57:$EK57) -> 0
B58: Acquisition Closing Costs | I58: ='Inputs & Drivers'!$E$15*Model!I57 -> -637500 | J58: ='Inputs & Drivers'!$E$15*Model!J57 -> 0 | K58: ='Inputs & Drivers'!$E$15*Model!K57 -> 0 | L58: ='Inputs & Drivers'!$E$15*Model!L57 -> 0 | M58: ='Inputs & Drivers'!$E$15*Model!M57 -> 0 | N58: ='Inputs & Drivers'!$E$15*Model!N57 -> 0 | O58: ='Inputs & Drivers'!$E$15*Model!O57 -> 0 | P58: ='Inputs & Drivers'!$E$15*Model!P57 -> 0 | ... EK58: ='Inputs & Drivers'!$E$15*Model!EK57 -> 0 | EM58: =SUMIF($I$4:$EK$4,EM$5,$I58:$EK58) -> -637500 | EN58: =SUMIF($I$4:$EK$4,EN$5,$I58:$EK58) -> 0 | EO58: =SUMIF($I$4:$EK$4,EO$5,$I58:$EK58) -> 0 | EP58: =SUMIF($I$4:$EK$4,EP$5,$I58:$EK58) -> 0 | EQ58: =SUMIF($I$4:$EK$4,EQ$5,$I58:$EK58) -> 0 | ER58: =SUMIF($I$4:$EK$4,ER$5,$I58:$EK58) -> 0 | ES58: =SUMIF($I$4:$EK$4,ES$5,$I58:$EK58) -> 0 | ET58: =SUMIF($I$4:$EK$4,ET$5,$I58:$EK58) -> 0 | ... EX58: =SUMIF($I$4:$EK$4,EX$5,$I58:$EK58) -> 0
B59: Sale Proceeds | I59: =I45/'Inputs & Drivers'!$J$14*(I$6='Inputs & Drivers'!$J$13) -> 0 | J59: =J45/'Inputs & Drivers'!$J$14*(J$6='Inputs & Drivers'!$J$13) -> 0 | K59: =K45/'Inputs & Drivers'!$J$14*(K$6='Inputs & Drivers'!$J$13) -> 0 | L59: =L45/'Inputs & Drivers'!$J$14*(L$6='Inputs & Drivers'!$J$13) -> 0 | M59: =M45/'Inputs & Drivers'!$J$14*(M$6='Inputs & Drivers'!$J$13) -> 0 | N59: =N45/'Inputs & Drivers'!$J$14*(N$6='Inputs & Drivers'!$J$13) -> 0 | O59: =O45/'Inputs & Drivers'!$J$14*(O$6='Inputs & Drivers'!$J$13) -> 0 | P59: =P45/'Inputs & Drivers'!$J$14*(P$6='Inputs & Drivers'!$J$13) -> 0 | ... EK59: =EK45/'Inputs & Drivers'!$J$14*(EK$6='Inputs & Drivers'!$J$13) -> 0 | EM59: =SUMIF($I$4:$EK$4,EM$5,$I59:$EK59) -> 0 | EN59: =SUMIF($I$4:$EK$4,EN$5,$I59:$EK59) -> 0 | EO59: =SUMIF($I$4:$EK$4,EO$5,$I59:$EK59) -> 0 | EP59: =SUMIF($I$4:$EK$4,EP$5,$I59:$EK59) -> 0 | EQ59: =SUMIF($I$4:$EK$4,EQ$5,$I59:$EK59) -> 0 | ER59: =SUMIF($I$4:$EK$4,ER$5,$I59:$EK59) -> 63755973 | ES59: =SUMIF($I$4:$EK$4,ES$5,$I59:$EK59) -> 0 | ET59: =SUMIF($I$4:$EK$4,ET$5,$I59:$EK59) -> 0 | ... EX59: =SUMIF($I$4:$EK$4,EX$5,$I59:$EK59) -> 0
B60: Exit Closing Costs | I60: =-'Inputs & Drivers'!$J$16*I59 -> 0 | J60: =-'Inputs & Drivers'!$J$16*J59 -> 0 | K60: =-'Inputs & Drivers'!$J$16*K59 -> 0 | L60: =-'Inputs & Drivers'!$J$16*L59 -> 0 | M60: =-'Inputs & Drivers'!$J$16*M59 -> 0 | N60: =-'Inputs & Drivers'!$J$16*N59 -> 0 | O60: =-'Inputs & Drivers'!$J$16*O59 -> 0 | P60: =-'Inputs & Drivers'!$J$16*P59 -> 0 | ... EK60: =-'Inputs & Drivers'!$J$16*EK59 -> 0 | EM60: =SUMIF($I$4:$EK$4,EM$5,$I60:$EK60) -> 0 | EN60: =SUMIF($I$4:$EK$4,EN$5,$I60:$EK60) -> 0 | EO60: =SUMIF($I$4:$EK$4,EO$5,$I60:$EK60) -> 0 | EP60: =SUMIF($I$4:$EK$4,EP$5,$I60:$EK60) -> 0 | EQ60: =SUMIF($I$4:$EK$4,EQ$5,$I60:$EK60) -> 0 | ER60: =SUMIF($I$4:$EK$4,ER$5,$I60:$EK60) -> -796949.67 | ES60: =SUMIF($I$4:$EK$4,ES$5,$I60:$EK60) -> 0 | ET60: =SUMIF($I$4:$EK$4,ET$5,$I60:$EK60) -> 0 | ... EX60: =SUMIF($I$4:$EK$4,EX$5,$I60:$EK60) -> 0
B61: TOTAL PURCHASE & SALE | I61: =SUM(I57:I60) -> -51637500 | J61: =SUM(J57:J60) -> 0 | K61: =SUM(K57:K60) -> 0 | L61: =SUM(L57:L60) -> 0 | M61: =SUM(M57:M60) -> 0 | N61: =SUM(N57:N60) -> 0 | O61: =SUM(O57:O60) -> 0 | P61: =SUM(P57:P60) -> 0 | ... EK61: =SUM(EK57:EK60) -> 0 | EM61: =SUM(EM57:EM60) -> -51637500 | EN61: =SUM(EN57:EN60) -> 0 | EO61: =SUM(EO57:EO60) -> 0 | EP61: =SUM(EP57:EP60) -> 0 | EQ61: =SUM(EQ57:EQ60) -> 0 | ER61: =SUM(ER57:ER60) -> 62959024 | ES61: =SUM(ES57:ES60) -> 0 | ET61: =SUM(ET57:ET60) -> 0 | ... EX61: =SUM(EX57:EX60) -> 0
B63: UNLEVERED CASH FLOW | I63: =I54+I61 -> -51637500 | J63: =J54+J61 -> 179205.13 | K63: =K54+K61 -> 179205.13 | L63: =L54+L61 -> 114722.58 | M63: =M54+M61 -> 115865.03 | N63: =N54+N61 -> 117007.49 | O63: =O54+O61 -> 118149.94 | P63: =P54+P61 -> 163042.39 | ... EK63: =EK54+EK61 -> 0 | EM63: =EM54+EM61 -> -51637500 | EN63: =EN54+EN61 -> 1819546.4 | EO63: =EO54+EO61 -> 2202429.7 | EP63: =EP54+EP61 -> 3162959 | EQ63: =EQ54+EQ61 -> 3432779.7 | ER63: =ER54+ER61 -> 66506466 | ES63: =ES54+ES61 -> 0 | ET63: =ET54+ET61 -> 0 | ... EX63: =EX54+EX61 -> 0
B65: Peak Equity | C65: =-SUMIF(I63:EK63,"<"&0) -> 51637500
B66: IRR | C66: =XIRR(I63:EK63,$I$6:$EK$6) -> 0.091856948
B67: Profit | C67: =SUM(I63:EK63) -> 25486681
B68: Multiple | C68: =-SUMIF(I63:EK63,">"&0)/SUMIF(I63:EK63,"<"&0) -> 1.4935692
B70: FINANCING COSTS
B71: LIBOR Index | J71: =INDEX('Inputs & Drivers'!$N$5:$N$125,MATCH(Model!J$6,'Inputs & Drivers'!$M$5:$M$125,1)) -> 0.0251275 | K71: =INDEX('Inputs & Drivers'!$N$5:$N$125,MATCH(Model!K$6,'Inputs & Drivers'!$M$5:$M$125,1)) -> 0.0250547 | L71: =INDEX('Inputs & Drivers'!$N$5:$N$125,MATCH(Model!L$6,'Inputs & Drivers'!$M$5:$M$125,1)) -> 0.0249624 | M71: =INDEX('Inputs & Drivers'!$N$5:$N$125,MATCH(Model!M$6,'Inputs & Drivers'!$M$5:$M$125,1)) -> 0.0249459 | N71: =INDEX('Inputs & Drivers'!$N$5:$N$125,MATCH(Model!N$6,'Inputs & Drivers'!$M$5:$M$125,1)) -> 0.024956 | O71: =INDEX('Inputs & Drivers'!$N$5:$N$125,MATCH(Model!O$6,'Inputs & Drivers'!$M$5:$M$125,1)) -> 0.0249169 | P71: =INDEX('Inputs & Drivers'!$N$5:$N$125,MATCH(Model!P$6,'Inputs & Drivers'!$M$5:$M$125,1)) -> 0.0248534 | Q71: =INDEX('Inputs & Drivers'!$N$5:$N$125,MATCH(Model!Q$6,'Inputs & Drivers'!$M$5:$M$125,1)) -> 0.0247617 | ... EK71: =INDEX('Inputs & Drivers'!$N$5:$N$125,MATCH(Model!EK$6,'Inputs & Drivers'!$M$5:$M$125,1)) -> 0.0278674
B72: Interest Rate Spread | J72: ='Inputs & Drivers'!$J$24/10000 -> 0.0215 | K72: =J72 -> 0.0215 | L72: =K72 -> 0.0215 | M72: =L72 -> 0.0215 | N72: =M72 -> 0.0215 | O72: =N72 -> 0.0215 | P72: =O72 -> 0.0215 | Q72: =P72 -> 0.0215 | R72: =Q72 -> 0.0215 | ... EK72: =EJ72 -> 0.0215
B73: All-in Rate | J73: =SUM(J71:J72) -> 0.0466275 | K73: =SUM(K71:K72) -> 0.0465547 | L73: =SUM(L71:L72) -> 0.0464624 | M73: =SUM(M71:M72) -> 0.0464459 | N73: =SUM(N71:N72) -> 0.046456 | O73: =SUM(O71:O72) -> 0.0464169 | P73: =SUM(P71:P72) -> 0.0463534 | Q73: =SUM(Q71:Q72) -> 0.0462617 | ... EK73: =SUM(EK71:EK72) -> 0.0493674
B75: Interest Expense | J75: =-J73*J78*((J6-I6)/365) -> -141377.13 | K75: =-K73*K78*((K6-J6)/365) -> -127496.1 | L75: =-L73*L78*((L6-K6)/365) -> -140876.54 | M75: =-M73*M78*((M6-L6)/365) -> -136283.72 | N75: =-N73*N78*((N6-M6)/365) -> -140857.14 | O75: =-O73*O78*((O6-N6)/365) -> -136198.63 | P75: =-P73*P78*((P6-O6)/365) -> -140546.05 | Q75: =-Q73*Q78*((Q6-P6)/365) -> -140268.01 | ... EK75: =-EK73*EK78*((EK6-EJ6)/365) -> 0 | EM75: =SUMIF($I$4:$EK$4,EM$5,$I75:$EK75) -> 0 | EN75: =SUMIF($I$4:$EK$4,EN$5,$I75:$EK75) -> -1650628.6 | EO75: =SUMIF($I$4:$EK$4,EO$5,$I75:$EK75) -> -1567994.3 | EP75: =SUMIF($I$4:$EK$4,EP$5,$I75:$EK75) -> -1535292.2 | EQ75: =SUMIF($I$4:$EK$4,EQ$5,$I75:$EK75) -> -1558038.5 | ER75: =SUMIF($I$4:$EK$4,ER$5,$I75:$EK75) -> -1583780.8 | ES75: =SUMIF($I$4:$EK$4,ES$5,$I75:$EK75) -> 0 | ET75: =SUMIF($I$4:$EK$4,ET$5,$I75:$EK75) -> 0 | ... EX75: =SUMIF($I$4:$EK$4,EX$5,$I75:$EK75) -> 0
B77: Financing Fees | I77: =-'Inputs & Drivers'!$J$28*I79 -> -178500 | J77: =-'Inputs & Drivers'!$J$28*J79 -> 0 | K77: =-'Inputs & Drivers'!$J$28*K79 -> 0 | L77: =-'Inputs & Drivers'!$J$28*L79 -> 0 | M77: =-'Inputs & Drivers'!$J$28*M79 -> 0 | N77: =-'Inputs & Drivers'!$J$28*N79 -> 0 | O77: =-'Inputs & Drivers'!$J$28*O79 -> 0 | P77: =-'Inputs & Drivers'!$J$28*P79 -> 0 | ... EK77: =-'Inputs & Drivers'!$J$28*EK79 -> 0 | EM77: =SUMIF($I$4:$EK$4,EM$5,$I77:$EK77) -> -178500 | EN77: =SUMIF($I$4:$EK$4,EN$5,$I77:$EK77) -> 0 | EO77: =SUMIF($I$4:$EK$4,EO$5,$I77:$EK77) -> 0 | EP77: =SUMIF($I$4:$EK$4,EP$5,$I77:$EK77) -> 0 | EQ77: =SUMIF($I$4:$EK$4,EQ$5,$I77:$EK77) -> 0 | ER77: =SUMIF($I$4:$EK$4,ER$5,$I77:$EK77) -> 0 | ES77: =SUMIF($I$4:$EK$4,ES$5,$I77:$EK77) -> 0 | ET77: =SUMIF($I$4:$EK$4,ET$5,$I77:$EK77) -> 0 | ... EX77: =SUMIF($I$4:$EK$4,EX$5,$I77:$EK77) -> 0
B78: Beginning Balance | I78: 0 | J78: =I82 -> 35700000 | K78: =J82 -> 35700000 | L78: =K82 -> 35700000 | M78: =L82 -> 35700000 | N78: =M82 -> 35700000 | O78: =N82 -> 35700000 | P78: =O82 -> 35700000 | Q78: =P82 -> 35700000 | ... EK78: =EJ82 -> 0 | EM78: =SUMIF($I$4:$EK$4,EM$5,$I78:$EK78) -> 0 | EN78: =EM82 -> 35700000 | EO78: =EN82 -> 35700000 | EP78: =EO82 -> 35700000 | EQ78: =EP82 -> 35700000 | ER78: =EQ82 -> 35700000 | ES78: =ER82 -> 0 | ET78: =ES82 -> 0 | EU78: =ET82 -> 0 | ... EX78: =EW82 -> 0
B79: Loan Funding | I79: ='Inputs & Drivers'!$J$22*(I$6='Inputs & Drivers'!$J$19) -> 35700000 | J79: ='Inputs & Drivers'!$J$22*(J$6='Inputs & Drivers'!$J$19) -> 0 | K79: ='Inputs & Drivers'!$J$22*(K$6='Inputs & Drivers'!$J$19) -> 0 | L79: ='Inputs & Drivers'!$J$22*(L$6='Inputs & Drivers'!$J$19) -> 0 | M79: ='Inputs & Drivers'!$J$22*(M$6='Inputs & Drivers'!$J$19) -> 0 | N79: ='Inputs & Drivers'!$J$22*(N$6='Inputs & Drivers'!$J$19) -> 0 | O79: ='Inputs & Drivers'!$J$22*(O$6='Inputs & Drivers'!$J$19) -> 0 | P79: ='Inputs & Drivers'!$J$22*(P$6='Inputs & Drivers'!$J$19) -> 0 | ... EK79: ='Inputs & Drivers'!$J$22*(EK$6='Inputs & Drivers'!$J$19) -> 0 | EM79: =SUMIF($I$4:$EK$4,EM$5,$I79:$EK79) -> 35700000 | EN79: =SUMIF($I$4:$EK$4,EN$5,$I79:$EK79) -> 0 | EO79: =SUMIF($I$4:$EK$4,EO$5,$I79:$EK79) -> 0 | EP79: =SUMIF($I$4:$EK$4,EP$5,$I79:$EK79) -> 0 | EQ79: =SUMIF($I$4:$EK$4,EQ$5,$I79:$EK79) -> 0 | ER79: =SUMIF($I$4:$EK$4,ER$5,$I79:$EK79) -> 0 | ES79: =SUMIF($I$4:$EK$4,ES$5,$I79:$EK79) -> 0 | ET79: =SUMIF($I$4:$EK$4,ET$5,$I79:$EK79) -> 0 | ... EX79: =SUMIF($I$4:$EK$4,EX$5,$I79:$EK79) -> 0
B80: Amortization | I80: =-INDEX('Inputs & Drivers'!$U$5:$U$365,MATCH(Model!I$6,'Inputs & Drivers'!$Q$5:$Q$365,0))*(I$6<=$C$5) -> 0 | J80: =-INDEX('Inputs & Drivers'!$U$5:$U$365,MATCH(Model!J$6,'Inputs & Drivers'!$Q$5:$Q$365,0))*(J$6<=$C$5) -> 0 | K80: =-INDEX('Inputs & Drivers'!$U$5:$U$365,MATCH(Model!K$6,'Inputs & Drivers'!$Q$5:$Q$365,0))*(K$6<=$C$5) -> 0 | L80: =-INDEX('Inputs & Drivers'!$U$5:$U$365,MATCH(Model!L$6,'Inputs & Drivers'!$Q$5:$Q$365,0))*(L$6<=$C$5) -> 0 | M80: =-INDEX('Inputs & Drivers'!$U$5:$U$365,MATCH(Model!M$6,'Inputs & Drivers'!$Q$5:$Q$365,0))*(M$6<=$C$5) -> 0 | N80: =-INDEX('Inputs & Drivers'!$U$5:$U$365,MATCH(Model!N$6,'Inputs & Drivers'!$Q$5:$Q$365,0))*(N$6<=$C$5) -> 0 | O80: =-INDEX('Inputs & Drivers'!$U$5:$U$365,MATCH(Model!O$6,'Inputs & Drivers'!$Q$5:$Q$365,0))*(O$6<=$C$5) -> 0 | P80: =-INDEX('Inputs & Drivers'!$U$5:$U$365,MATCH(Model!P$6,'Inputs & Drivers'!$Q$5:$Q$365,0))*(P$6<=$C$5) -> 0 | ... EK80: =-INDEX('Inputs & Drivers'!$U$5:$U$365,MATCH(Model!EK$6,'Inputs & Drivers'!$Q$5:$Q$365,0))*(EK$6<=$C$5) -> 0 | EM80: =SUMIF($I$4:$EK$4,EM$5,$I80:$EK80) -> 0 | EN80: =SUMIF($I$4:$EK$4,EN$5,$I80:$EK80) -> 0 | EO80: =SUMIF($I$4:$EK$4,EO$5,$I80:$EK80) -> 0 | EP80: =SUMIF($I$4:$EK$4,EP$5,$I80:$EK80) -> 0 | EQ80: =SUMIF($I$4:$EK$4,EQ$5,$I80:$EK80) -> 0 | ER80: =SUMIF($I$4:$EK$4,ER$5,$I80:$EK80) -> -559749.46 | ES80: =SUMIF($I$4:$EK$4,ES$5,$I80:$EK80) -> 0 | ET80: =SUMIF($I$4:$EK$4,ET$5,$I80:$EK80) -> 0 | ... EX80: =SUMIF($I$4:$EK$4,EX$5,$I80:$EK80) -> 0
B81: Loan Payoff | I81: =-SUM(I78:I80)*(I$6='Inputs & Drivers'!$J$21) -> 0 | J81: =-SUM(J78:J80)*(J$6='Inputs & Drivers'!$J$21) -> 0 | K81: =-SUM(K78:K80)*(K$6='Inputs & Drivers'!$J$21) -> 0 | L81: =-SUM(L78:L80)*(L$6='Inputs & Drivers'!$J$21) -> 0 | M81: =-SUM(M78:M80)*(M$6='Inputs & Drivers'!$J$21) -> 0 | N81: =-SUM(N78:N80)*(N$6='Inputs & Drivers'!$J$21) -> 0 | O81: =-SUM(O78:O80)*(O$6='Inputs & Drivers'!$J$21) -> 0 | P81: =-SUM(P78:P80)*(P$6='Inputs & Drivers'!$J$21) -> 0 | ... EK81: =-SUM(EK78:EK80)*(EK$6='Inputs & Drivers'!$J$21) -> 0 | EM81: =SUMIF($I$4:$EK$4,EM$5,$I81:$EK81) -> 0 | EN81: =SUMIF($I$4:$EK$4,EN$5,$I81:$EK81) -> 0 | EO81: =SUMIF($I$4:$EK$4,EO$5,$I81:$EK81) -> 0 | EP81: =SUMIF($I$4:$EK$4,EP$5,$I81:$EK81) -> 0 | EQ81: =SUMIF($I$4:$EK$4,EQ$5,$I81:$EK81) -> 0 | ER81: =SUMIF($I$4:$EK$4,ER$5,$I81:$EK81) -> -35140251 | ES81: =SUMIF($I$4:$EK$4,ES$5,$I81:$EK81) -> 0 | ET81: =SUMIF($I$4:$EK$4,ET$5,$I81:$EK81) -> 0 | ... EX81: =SUMIF($I$4:$EK$4,EX$5,$I81:$EK81) -> 0
B82: Ending Balance | I82: =SUM(I78:I81) -> 35700000 | J82: =SUM(J78:J81) -> 35700000 | K82: =SUM(K78:K81) -> 35700000 | L82: =SUM(L78:L81) -> 35700000 | M82: =SUM(M78:M81) -> 35700000 | N82: =SUM(N78:N81) -> 35700000 | O82: =SUM(O78:O81) -> 35700000 | P82: =SUM(P78:P81) -> 35700000 | ... EK82: =SUM(EK78:EK81) -> 0 | EM82: =SUM(EM78:EM81) -> 35700000 | EN82: =SUM(EN78:EN81) -> 35700000 | EO82: =SUM(EO78:EO81) -> 35700000 | EP82: =SUM(EP78:EP81) -> 35700000 | EQ82: =SUM(EQ78:EQ81) -> 35700000 | ER82: =SUM(ER78:ER81) -> 0 | ES82: =SUM(ES78:ES81) -> 0 | ET82: =SUM(ET78:ET81) -> 0 | ... EX82: =SUM(EX78:EX81) -> 0
B83: DSCR | I83: =IFERROR(-I44/(I75+I80),"n/a") -> n/a | J83: =IFERROR(-J44/(J75+J80),"n/a") -> 1.577024 | K83: =IFERROR(-K44/(K75+K80),"n/a") -> 1.7487211 | L83: =IFERROR(-L44/(L75+L80),"n/a") -> 1.5907374 | M83: =IFERROR(-M44/(M75+M80),"n/a") -> 1.6527288 | N83: =IFERROR(-N44/(N75+N80),"n/a") -> 1.607178 | O83: =IFERROR(-O44/(O75+O80),"n/a") -> 1.6705376 | P83: =IFERROR(-P44/(P75+P80),"n/a") -> 1.6269927 | ... EK83: =IFERROR(-EK44/(EK75+EK80),"n/a") -> n/a | EM83: =IFERROR(-EM44/(EM75+EM80),"n/a") -> n/a | EN83: =IFERROR(-EN44/(EN75+EN80),"n/a") -> 1.6589416 | EO83: =IFERROR(-EO44/(EO75+EO80),"n/a") -> 1.9068499 | EP83: =IFERROR(-EP44/(EP75+EP80),"n/a") -> 2.145656 | EQ83: =IFERROR(-EQ44/(EQ75+EQ80),"n/a") -> 2.2032701 | ER83: =IFERROR(-ER44/(ER75+ER80),"n/a") -> 1.6549532 | ES83: =IFERROR(-ES44/(ES75+ES80),"n/a") -> n/a | ET83: =IFERROR(-ET44/(ET75+ET80),"n/a") -> n/a | ... EX83: =IFERROR(-EX44/(EX75+EX80),"n/a") -> n/a
B84: Debt Yield | I84: =IFERROR(I44*12/I82,"n/a") -> 0 | J84: =IFERROR(J44*12/J82,"n/a") -> 0.074942901 | K84: =IFERROR(K44*12/K82,"n/a") -> 0.074942901 | L84: =IFERROR(L44*12/L82,"n/a") -> 0.075326918 | M84: =IFERROR(M44*12/M82,"n/a") -> 0.075710936 | N84: =IFERROR(N44*12/N82,"n/a") -> 0.076094954 | O84: =IFERROR(O44*12/O82,"n/a") -> 0.076478971 | P84: =IFERROR(P44*12/P82,"n/a") -> 0.076862989 | ... EK84: =IFERROR(EK44*12/EK82,"n/a") -> n/a | EM84: =IFERROR(EM44/EM82,"n/a") -> 0 | EN84: =IFERROR(EN44/EN82,"n/a") -> 0.076702981 | EO84: =IFERROR(EO44/EO82,"n/a") -> 0.083751533 | EP84: =IFERROR(EP44/EP82,"n/a") -> 0.092274761 | EQ84: =IFERROR(EQ44/EQ82,"n/a") -> 0.096156294 | ER84: =IFERROR(ER44/ER82,"n/a") -> n/a | ES84: =IFERROR(ES44/ES82,"n/a") -> n/a | ET84: =IFERROR(ET44/ET82,"n/a") -> n/a | ... EX84: =IFERROR(EX44/EX82,"n/a") -> n/a
B86: LEVERED CASH FLOW | I86: =SUM(I63,I75,I77,I79:I81) -> -16116000 | J86: =SUM(J63,J75,J77,J79:J81) -> 37827.995 | K86: =SUM(K63,K75,K77,K79:K81) -> 51709.026 | L86: =SUM(L63,L75,L77,L79:L81) -> -26153.96 | M86: =SUM(M63,M75,M77,M79:M81) -> -20418.688 | N86: =SUM(N63,N75,N77,N79:N81) -> -23849.651 | O86: =SUM(O63,O75,O77,O79:O81) -> -18048.691 | P86: =SUM(P63,P75,P77,P79:P81) -> 22496.342 | ... EK86: =SUM(EK63,EK75,EK77,EK79:EK81) -> 0 | EM86: =SUM(EM63,EM75,EM77,EM79:EM81) -> -16116000 | EN86: =SUM(EN63,EN75,EN77,EN79:EN81) -> 168917.81 | EO86: =SUM(EO63,EO75,EO77,EO79:EO81) -> 634435.43 | EP86: =SUM(EP63,EP75,EP77,EP79:EP81) -> 1627666.7 | EQ86: =SUM(EQ63,EQ75,EQ77,EQ79:EQ81) -> 1874741.2 | ER86: =SUM(ER63,ER75,ER77,ER79:ER81) -> 29222685 | ES86: =SUM(ES63,ES75,ES77,ES79:ES81) -> 0 | ET86: =SUM(ET63,ET75,ET77,ET79:ET81) -> 0 | ... EX86: =SUM(EX63,EX75,EX77,EX79:EX81) -> 0
B88: Peak Equity | C88: =-SUMIF(I86:EK86,"<"&0) -> 16204471
B89: IRR | C89: =XIRR(I86:EK86,$I$6:$EK$6) -> 0.1709843
B90: Profit | C90: =SUM(I86:EK86) -> 17412446
B91: Multiple | C91: =-SUMIF(I86:EK86,">"&0)/SUMIF(I86:EK86,"<"&0) -> 2.0745458
B94: USES | E94: Close | F94: Hold
B95: Purchase Price | E95: =I95 -> 51000000 | F95: =_xlfn.MAXIFS(I95:EK95,$I$6:$EK$6,"<="&$C$5) -> 51000000 | I95: =-SUM($I$57:I57) -> 51000000 | J95: =-SUM($I$57:J57) -> 51000000 | K95: =-SUM($I$57:K57) -> 51000000 | L95: =-SUM($I$57:L57) -> 51000000 | M95: =-SUM($I$57:M57) -> 51000000 | N95: =-SUM($I$57:N57) -> 51000000 | O95: =-SUM($I$57:O57) -> 51000000 | P95: =-SUM($I$57:P57) -> 51000000 | ... EK95: =-SUM($I$57:EK57) -> 51000000 | EM95: =SUMIF($I$6:$EK$6,EM$6,$I95:$EK95) -> 51000000 | EN95: =SUMIF($I$6:$EK$6,EN$6,$I95:$EK95) -> 51000000 | EO95: =SUMIF($I$6:$EK$6,EO$6,$I95:$EK95) -> 51000000 | EP95: =SUMIF($I$6:$EK$6,EP$6,$I95:$EK95) -> 51000000 | EQ95: =SUMIF($I$6:$EK$6,EQ$6,$I95:$EK95) -> 51000000 | ER95: =SUMIF($I$6:$EK$6,ER$6,$I95:$EK95) -> 51000000 | ES95: =SUMIF($I$6:$EK$6,ES$6,$I95:$EK95) -> 51000000 | ET95: =SUMIF($I$6:$EK$6,ET$6,$I95:$EK95) -> 51000000 | ... EX95: =SUMIF($I$6:$EK$6,EX$6,$I95:$EK95) -> 51000000
B96: Closing Costs | E96: =I96 -> 637500 | F96: =_xlfn.MAXIFS(I96:EK96,$I$6:$EK$6,"<="&$C$5) -> 637500 | I96: =-SUM($I$58:I58) -> 637500 | J96: =-SUM($I$58:J58) -> 637500 | K96: =-SUM($I$58:K58) -> 637500 | L96: =-SUM($I$58:L58) -> 637500 | M96: =-SUM($I$58:M58) -> 637500 | N96: =-SUM($I$58:N58) -> 637500 | O96: =-SUM($I$58:O58) -> 637500 | P96: =-SUM($I$58:P58) -> 637500 | ... EK96: =-SUM($I$58:EK58) -> 637500 | EM96: =SUMIF($I$6:$EK$6,EM$6,$I96:$EK96) -> 637500 | EN96: =SUMIF($I$6:$EK$6,EN$6,$I96:$EK96) -> 637500 | EO96: =SUMIF($I$6:$EK$6,EO$6,$I96:$EK96) -> 637500 | EP96: =SUMIF($I$6:$EK$6,EP$6,$I96:$EK96) -> 637500 | EQ96: =SUMIF($I$6:$EK$6,EQ$6,$I96:$EK96) -> 637500 | ER96: =SUMIF($I$6:$EK$6,ER$6,$I96:$EK96) -> 637500 | ES96: =SUMIF($I$6:$EK$6,ES$6,$I96:$EK96) -> 637500 | ET96: =SUMIF($I$6:$EK$6,ET$6,$I96:$EK96) -> 637500 | ... EX96: =SUMIF($I$6:$EK$6,EX$6,$I96:$EK96) -> 637500
B97: Capital Expenditures | E97: =I97 -> 0 | F97: =_xlfn.MAXIFS(I97:EK97,$I$6:$EK$6,"<="&$C$5) -> 1837500 | I97: =-SUM($I$50:I51) -> 0 | J97: =-SUM($I$50:J51) -> 43750 | K97: =-SUM($I$50:K51) -> 87500 | L97: =-SUM($I$50:L51) -> 196875 | M97: =-SUM($I$50:M51) -> 306250 | N97: =-SUM($I$50:N51) -> 415625 | O97: =-SUM($I$50:O51) -> 525000 | P97: =-SUM($I$50:P51) -> 590625 | ... EK97: =-SUM($I$50:EK51) -> 1837500 | EM97: =SUMIF($I$6:$EK$6,EM$6,$I97:$EK97) -> 0 | EN97: =SUMIF($I$6:$EK$6,EN$6,$I97:$EK97) -> 918750 | EO97: =SUMIF($I$6:$EK$6,EO$6,$I97:$EK97) -> 1706250 | EP97: =SUMIF($I$6:$EK$6,EP$6,$I97:$EK97) -> 1837500 | EQ97: =SUMIF($I$6:$EK$6,EQ$6,$I97:$EK97) -> 1837500 | ER97: =SUMIF($I$6:$EK$6,ER$6,$I97:$EK97) -> 1837500 | ES97: =SUMIF($I$6:$EK$6,ES$6,$I97:$EK97) -> 1837500 | ET97: =SUMIF($I$6:$EK$6,ET$6,$I97:$EK97) -> 1837500 | ... EX97: =SUMIF($I$6:$EK$6,EX$6,$I97:$EK97) -> 1837500
B98: Financing Fees | E98: =I98 -> 178500 | F98: =_xlfn.MAXIFS(I98:EK98,$I$6:$EK$6,"<="&$C$5) -> 178500 | I98: =-SUM($I$77:I77) -> 178500 | J98: =-SUM($I$77:J77) -> 178500 | K98: =-SUM($I$77:K77) -> 178500 | L98: =-SUM($I$77:L77) -> 178500 | M98: =-SUM($I$77:M77) -> 178500 | N98: =-SUM($I$77:N77) -> 178500 | O98: =-SUM($I$77:O77) -> 178500 | P98: =-SUM($I$77:P77) -> 178500 | ... EK98: =-SUM($I$77:EK77) -> 178500 | EM98: =SUMIF($I$6:$EK$6,EM$6,$I98:$EK98) -> 178500 | EN98: =SUMIF($I$6:$EK$6,EN$6,$I98:$EK98) -> 178500 | EO98: =SUMIF($I$6:$EK$6,EO$6,$I98:$EK98) -> 178500 | EP98: =SUMIF($I$6:$EK$6,EP$6,$I98:$EK98) -> 178500 | EQ98: =SUMIF($I$6:$EK$6,EQ$6,$I98:$EK98) -> 178500 | ER98: =SUMIF($I$6:$EK$6,ER$6,$I98:$EK98) -> 178500 | ES98: =SUMIF($I$6:$EK$6,ES$6,$I98:$EK98) -> 178500 | ET98: =SUMIF($I$6:$EK$6,ET$6,$I98:$EK98) -> 178500 | ... EX98: =SUMIF($I$6:$EK$6,EX$6,$I98:$EK98) -> 178500
B99: TOTAL USES | E99: =SUM(E95:E98) -> 51816000 | F99: =SUM(F95:F98) -> 53653500 | I99: =SUM(I95:I98) -> 51816000 | J99: =SUM(J95:J98) -> 51859750 | K99: =SUM(K95:K98) -> 51903500 | L99: =SUM(L95:L98) -> 52012875 | M99: =SUM(M95:M98) -> 52122250 | N99: =SUM(N95:N98) -> 52231625 | O99: =SUM(O95:O98) -> 52341000 | P99: =SUM(P95:P98) -> 52406625 | ... EK99: =SUM(EK95:EK98) -> 53653500 | EM99: =SUM(EM95:EM98) -> 51816000 | EN99: =SUM(EN95:EN98) -> 52734750 | EO99: =SUM(EO95:EO98) -> 53522250 | EP99: =SUM(EP95:EP98) -> 53653500 | EQ99: =SUM(EQ95:EQ98) -> 53653500 | ER99: =SUM(ER95:ER98) -> 53653500 | ES99: =SUM(ES95:ES98) -> 53653500 | ET99: =SUM(ET95:ET98) -> 53653500 | ... EX99: =SUM(EX95:EX98) -> 53653500
B101: SOURCES
B102: Equity | E102: =I102 -> 16116000 | F102: =_xlfn.MAXIFS(I102:EK102,$I$6:$EK$6,"<="&$C$5) -> 16204471 | I102: =-SUMIF($I$86:I86,"<0") -> 16116000 | J102: =-SUMIF($I$86:J86,"<0") -> 16116000 | K102: =-SUMIF($I$86:K86,"<0") -> 16116000 | L102: =-SUMIF($I$86:L86,"<0") -> 16142154 | M102: =-SUMIF($I$86:M86,"<0") -> 16162573 | N102: =-SUMIF($I$86:N86,"<0") -> 16186422 | O102: =-SUMIF($I$86:O86,"<0") -> 16204471 | P102: =-SUMIF($I$86:P86,"<0") -> 16204471 | ... EK102: =-SUMIF($I$86:EK86,"<0") -> 16204471 | EM102: =SUMIF($I$6:$EK$6,EM$6,$I102:$EK102) -> 16116000 | EN102: =SUMIF($I$6:$EK$6,EN$6,$I102:$EK102) -> 16204471 | EO102: =SUMIF($I$6:$EK$6,EO$6,$I102:$EK102) -> 16204471 | EP102: =SUMIF($I$6:$EK$6,EP$6,$I102:$EK102) -> 16204471 | EQ102: =SUMIF($I$6:$EK$6,EQ$6,$I102:$EK102) -> 16204471 | ER102: =SUMIF($I$6:$EK$6,ER$6,$I102:$EK102) -> 16204471 | ES102: =SUMIF($I$6:$EK$6,ES$6,$I102:$EK102) -> 16204471 | ET102: =SUMIF($I$6:$EK$6,ET$6,$I102:$EK102) -> 16204471 | ... EX102: =SUMIF($I$6:$EK$6,EX$6,$I102:$EK102) -> 16204471
B103: Debt | E103: =I103 -> 35700000 | F103: =_xlfn.MAXIFS(I103:EK103,$I$6:$EK$6,"<="&$C$5) -> 35700000 | I103: =SUM($I$79:I79) -> 35700000 | J103: =SUM($I$79:J79) -> 35700000 | K103: =SUM($I$79:K79) -> 35700000 | L103: =SUM($I$79:L79) -> 35700000 | M103: =SUM($I$79:M79) -> 35700000 | N103: =SUM($I$79:N79) -> 35700000 | O103: =SUM($I$79:O79) -> 35700000 | P103: =SUM($I$79:P79) -> 35700000 | ... EK103: =SUM($I$79:EK79) -> 35700000 | EM103: =SUMIF($I$6:$EK$6,EM$6,$I103:$EK103) -> 35700000 | EN103: =SUMIF($I$6:$EK$6,EN$6,$I103:$EK103) -> 35700000 | EO103: =SUMIF($I$6:$EK$6,EO$6,$I103:$EK103) -> 35700000 | EP103: =SUMIF($I$6:$EK$6,EP$6,$I103:$EK103) -> 35700000 | EQ103: =SUMIF($I$6:$EK$6,EQ$6,$I103:$EK103) -> 35700000 | ER103: =SUMIF($I$6:$EK$6,ER$6,$I103:$EK103) -> 35700000 | ES103: =SUMIF($I$6:$EK$6,ES$6,$I103:$EK103) -> 35700000 | ET103: =SUMIF($I$6:$EK$6,ET$6,$I103:$EK103) -> 35700000 | ... EX103: =SUMIF($I$6:$EK$6,EX$6,$I103:$EK103) -> 35700000
B104: Operating Cashflow | E104: =I104 -> 0 | F104: =_xlfn.MAXIFS(I104:EK104,$I$6:$EK$6,"<="&$C$5) -> 1749029 | I104: =I99-SUM(I102:I103) -> 0 | J104: =J99-SUM(J102:J103) -> 43750 | K104: =K99-SUM(K102:K103) -> 87500 | L104: =L99-SUM(L102:L103) -> 170721.04 | M104: =M99-SUM(M102:M103) -> 259677.35 | N104: =N99-SUM(N102:N103) -> 345202.7 | O104: =O99-SUM(O102:O103) -> 436529.01 | P104: =P99-SUM(P102:P103) -> 502154.01 | ... EK104: =EK99-SUM(EK102:EK103) -> 1749029 | EM104: =SUMIF($I$6:$EK$6,EM$6,$I104:$EK104) -> 0 | EN104: =SUMIF($I$6:$EK$6,EN$6,$I104:$EK104) -> 830279.01 | EO104: =SUMIF($I$6:$EK$6,EO$6,$I104:$EK104) -> 1617779 | EP104: =SUMIF($I$6:$EK$6,EP$6,$I104:$EK104) -> 1749029 | EQ104: =SUMIF($I$6:$EK$6,EQ$6,$I104:$EK104) -> 1749029 | ER104: =SUMIF($I$6:$EK$6,ER$6,$I104:$EK104) -> 1749029 | ES104: =SUMIF($I$6:$EK$6,ES$6,$I104:$EK104) -> 1749029 | ET104: =SUMIF($I$6:$EK$6,ET$6,$I104:$EK104) -> 1749029 | ... EX104: =SUMIF($I$6:$EK$6,EX$6,$I104:$EK104) -> 1749029
B105: TOTAL SOURCES | E105: =SUM(E102:E104) -> 51816000 | F105: =SUM(F102:F104) -> 53653500 | I105: =SUM(I102:I104) -> 51816000 | J105: =SUM(J102:J104) -> 51859750 | K105: =SUM(K102:K104) -> 51903500 | L105: =SUM(L102:L104) -> 52012875 | M105: =SUM(M102:M104) -> 52122250 | N105: =SUM(N102:N104) -> 52231625 | O105: =SUM(O102:O104) -> 52341000 | P105: =SUM(P102:P104) -> 52406625 | ... EK105: =SUM(EK102:EK104) -> 53653500 | EM105: =SUM(EM102:EM104) -> 51816000 | EN105: =SUM(EN102:EN104) -> 52734750 | EO105: =SUM(EO102:EO104) -> 53522250 | EP105: =SUM(EP102:EP104) -> 53653500 | EQ105: =SUM(EQ102:EQ104) -> 53653500 | ER105: =SUM(ER102:ER104) -> 53653500 | ES105: =SUM(ES102:ES104) -> 53653500 | ET105: =SUM(ET102:ET104) -> 53653500 | ... EX105: =SUM(EX102:EX104) -> 53653500
B107: Check | E107: =IF(E99=E105,"Ok","Check") -> Ok | F107: =IF(F99=F105,"Ok","Check") -> Ok | I107: =IF(I99=I105,"Ok","Check") -> Ok | J107: =IF(J99=J105,"Ok","Check") -> Ok | K107: =IF(K99=K105,"Ok","Check") -> Ok | L107: =IF(L99=L105,"Ok","Check") -> Ok | M107: =IF(M99=M105,"Ok","Check") -> Ok | N107: =IF(N99=N105,"Ok","Check") -> Ok | O107: =IF(O99=O105,"Ok","Check") -> Ok | P107: =IF(P99=P105,"Ok","Check") -> Ok | ... EK107: =IF(EK99=EK105,"Ok","Check") -> Ok | EM107: =IF(EM99=EM105,"Ok","Check") -> Ok | EN107: =IF(EN99=EN105,"Ok","Check") -> Ok | EO107: =IF(EO99=EO105,"Ok","Check") -> Ok | EP107: =IF(EP99=EP105,"Ok","Check") -> Ok | EQ107: =IF(EQ99=EQ105,"Ok","Check") -> Ok | ER107: =IF(ER99=ER105,"Ok","Check") -> Ok | ES107: =IF(ES99=ES105,"Ok","Check") -> Ok | ET107: =IF(ET99=ET105,"Ok","Check") -> Ok | ... EX107: =IF(EX99=EX105,"Ok","Check") -> Ok

Sheet Historical Financials
B2: 2018 Historical Financials
D4: 43131 | E4: 43159 | F4: 43190 | G4: 43220 | H4: 43251 | I4: 43281 | J4: 43312 | K4: 43343 | L4: 43373 | M4: 43404 | N4: 43434 | O4: 43465
B5: INCOME
B6: Rental Income
B7: Gross Potential Rent | D7: 527980 | E7: 488820 | F7: 499280 | G7: 529495 | H7: 594645 | I7: 513771 | J7: 495575 | K7: 489920 | L7: 485890 | M7: 475795 | N7: 492355 | O7: 497485
B8: Concessions | D8: -2434.3 | E8: -2434.3 | F8: -2434.3 | G8: -2434.3 | H8: -2434.3 | I8: -2434.3 | J8: -2434.3 | K8: -2434.3 | L8: -2434.3 | M8: -2434.3 | N8: -2434.3 | O8: -2434.3
B9: Loss to Lease | D9: -5832 | E9: 31626 | F9: 19193 | G9: -9891 | H9: -71784 | I9: 5533 | J9: 21182 | K9: 23576 | L9: 25301 | M9: 33369 | N9: 16498 | O9: 10830
B10: Effective Rent | D10: 519713.7 | E10: 518011.7 | F10: 516038.7 | G10: 517169.7 | H10: 520426.7 | I10: 516869.7 | J10: 514322.7 | K10: 511061.7 | L10: 508756.7 | M10: 506729.7 | N10: 506418.7 | O10: 505880.7
B11: Effective Rent / Unit | D11: 2078.8548 | E11: 2072.0468 | F11: 2064.1548 | G11: 2068.6788 | H11: 2081.7068 | I11: 2067.4788 | J11: 2057.2908 | K11: 2044.2468 | L11: 2035.0268 | M11: 2026.9188 | N11: 2025.6748 | O11: 2023.5228
B12: Effective Rent / SF | D12: 2.2596248 | E12: 2.2522248 | F12: 2.2436465 | G12: 2.2485639 | H12: 2.2627248 | I12: 2.2472596 | J12: 2.2361857 | K12: 2.2220074 | L12: 2.2119857 | M12: 2.2031726 | N12: 2.2018204 | O12: 2.1994813
B13: Occupancy | D13: 0.9 | E13: 0.9 | F13: 0.9 | G13: 0.9 | H13: 0.9 | I13: 0.9 | J13: 0.9 | K13: 0.9 | L13: 0.9 | M13: 0.9 | N13: 0.9 | O13: 0.9
B15: Vacancy Loss | D15: -51971.37 | E15: -51801.17 | F15: -51603.87 | G15: -51716.97 | H15: -52042.67 | I15: -51686.97 | J15: -51432.27 | K15: -51106.17 | L15: -50875.67 | M15: -50672.97 | N15: -50641.87 | O15: -50588.07
B16: Non-Revenue Units | D16: -1200 | E16: -1200 | F16: -1200 | G16: -1200 | H16: -1200 | I16: -1200 | J16: -1200 | K16: -1200 | L16: -960 | M16: 0 | N16: 0 | O16: 0
B17: Uncollectible Rent | D17: -5257 | E17: -5122 | F17: -4797 | G17: -4702 | H17: -3418 | I17: -1096 | J17: 0 | K17: 0 | L17: 0 | M17: 0 | N17: 0 | O17: 0
B18: Total Rental Income | D18: 461285.33 | E18: 459888.53 | F18: 458437.83 | G18: 459550.73 | H18: 463766.03 | I18: 462886.73 | J18: 461690.43 | K18: 458755.53 | L18: 456921.03 | M18: 456056.73 | N18: 455776.83 | O18: 455292.63
B20: Utility Reimbursement | D20: 8130.21 | E20: 9348.98 | F20: 7113.38 | G20: 8437.89 | H20: 7849.68 | I20: 7206.62 | J20: 8281.98 | K20: 8550 | L20: 8251 | M20: 8545 | N20: 8459 | O20: 9542
... B25: TOTAL INCOME | D25: 488823.54 | E25: 490615.51 | F25: 482959.21 | G25: 489007.62 | H25: 490142.71 | I25: 487133.35 | J25: 498566.41 | K25: 500007.53 | L25: 485088.03 | M25: 489862.73 | N25: 483032.83 | O25: 488729.63
B27: OPERATING EXPENSES
B28: Repairs & Maintenance | D28: -40029 | E28: -13007 | F28: -20133 | G28: -24116 | H28: -24604 | I28: -22633 | J28: -25246 | K28: -16643 | L28: -24994 | M28: -27415 | N28: -26795 | O28: -28785
B29: Turnover Costs | D29: -8298 | E29: -2032 | F29: -1682 | G29: -7910 | H29: -9931 | I29: -3657 | J29: -8294 | K29: -6868 | L29: -3714 | M29: -11253 | N29: -5918 | O29: -4807
B30: Marketing/Leasing Costs | D30: -16544 | E30: -5694 | F30: -8813 | G30: -10169 | H30: -4840 | I30: -21655 | J30: -8720 | K30: -16224 | L30: -18672 | M30: -19738 | N30: -23279 | O30: -29390
B31: General/Administrative | D31: -6268 | E31: -5101 | F31: -5183 | G31: -4794 | H31: -4144 | I31: -3867 | J31: -4581 | K31: -4775 | L31: -3300 | M31: -6369 | N31: -4591 | O31: -6574
B32: Property Payroll | D32: -30347 | E32: -28774 | F32: -41566 | G32: -31498 | H32: -33333 | I32: -31422 | J32: -31945 | K32: -44440 | L32: -36037 | M32: -33162 | N32: -31520 | O32: -30291
B33: Management Fees | D33: -13838.56 | E33: -13796.656 | F33: -13753.135 | G33: -13786.522 | H33: -13912.981 | I33: -13886.602 | J33: -13850.713 | K33: -13762.666 | L33: -13707.631 | M33: -13681.702 | N33: -13673.305 | O33: -13658.779
B34: Utilities | D34: -11936.03 | E34: -15609.79 | F34: -12599.6 | G34: -11820.53 | H34: -11403.12 | I34: -11007.15 | J34: -11788.06 | K34: -14763 | L34: -12262 | M34: -12578 | N34: -12238 | O34: -11576
B35: Real Estate Taxes | D35: -136542 | E35: -136542 | F35: -136542 | G35: -136542 | H35: -136542 | I35: -136542 | J35: -136542 | K35: -136542 | L35: -136542 | M35: -136542 | N35: -136542 | O35: -136542
B36: Property Insurance | D36: -6187 | E36: -6187 | F36: -7092 | G36: -7092 | H36: -6967 | I36: -7092 | J36: -6967 | K36: -6967 | L36: -7342 | M36: -7594 | N36: -6967 | O36: -7467
B37: TOTAL OPERATING EXPENSES | D37: -269989.59 | E37: -226743.45 | F37: -247363.73 | G37: -247728.05 | H37: -245677.1 | I37: -251761.75 | J37: -247933.77 | K37: -260984.67 | L37: -256570.63 | M37: -268332.7 | N37: -261523.3 | O37: -269090.78
B39: NET OPERATING INCOME | D39: 218833.95 | E39: 263872.06 | F39: 235595.48 | G39: 241279.57 | H39: 244465.61 | I39: 235371.6 | J39: 250632.64 | K39: 239022.86 | L39: 228517.4 | M39: 221530.03 | N39: 221509.53 | O39: 219638.85
